{
 "resumen": [
  {
   "delito": "AMENAZAS CON ARMAS",
   "CODCOM": 11201,
   "2024": 16,
   "2025": 10,
   "variacion": -38,
   "situación": "Disminución de Casos",
   "COMUNA": "Aisén"
  },
  {
   "delito": "AMENAZAS Y RIÑAS",
   "CODCOM": 11201,
   "2024": 190,
   "2025": 223,
   "variacion": 17,
   "situación": "Aumento de Casos",
   "COMUNA": "Aisén"
  },
  {
   "delito": "CONSUMO DE ALCOHOL Y DE DROGAS EN LA VÍA PÚBLICA",
   "CODCOM": 11201,
   "2024": 582,
   "2025": 580,
   "variacion": 0,
   "situación": "Sin variación de Casos",
   "COMUNA": "Aisén"
  },
  {
   "delito": "DAÑOS",
   "CODCOM": 11201,
   "2024": 205,
   "2025": 152,
   "variacion": -26,
   "situación": "Disminución de Casos",
   "COMUNA": "Aisén"
  },
  {
   "delito": "DELITOS EN CONTEXTO DE VIOLENCIA INTRAFAMILIAR",
   "CODCOM": 11201,
   "2024": 392,
   "2025": 295,
   "variacion": -25,
   "situación": "Disminución de Casos",
   "COMUNA": "Aisén"
  },
  {
   "delito": "HOMICIDIOS Y FEMICIDIOS",
   "CODCOM": 11201,
   "2024": 2,
   "2025": 1,
   "variacion": -50,
   "situación": "Disminución de Casos",
   "COMUNA": "Aisén"
  },
  {
   "delito": "HURTOS",
   "CODCOM": 11201,
   "2024": 137,
   "2025": 104,
   "variacion": -24,
   "situación": "Disminución de Casos",
   "COMUNA": "Aisén"
  },
  {
   "delito": "INCIVILIDADES",
   "CODCOM": 11201,
   "2024": 194,
   "2025": 165,
   "variacion": -15,
   "situación": "Disminución de Casos",
   "COMUNA": "Aisén"
  },
  {
   "delito": "LESIONES GRAVES",
   "CODCOM": 11201,
   "2024": 16,
   "2025": 11,
   "variacion": -31,
   "situación": "Disminución de Casos",
   "COMUNA": "Aisén"
  },
  {
   "delito": "LESIONES LEVES",
   "CODCOM": 11201,
   "2024": 108,
   "2025": 100,
   "variacion": -7,
   "situación": "Disminución de Casos",
   "COMUNA": "Aisén"
  },
  {
   "delito": "LESIONES MENOS GRAVES",
   "CODCOM": 11201,
   "2024": 26,
   "2025": 29,
   "variacion": 12,
   "situación": "Aumento de Casos",
   "COMUNA": "Aisén"
  },
  {
   "delito": "LEY DE CONTROL DE ARMAS",
   "CODCOM": 11201,
   "2024": 18,
   "2025": 27,
   "variacion": 50,
   "situación": "Aumento de Casos",
   "COMUNA": "Aisén"
  },
  {
   "delito": "LEY DE DROGAS",
   "CODCOM": 11201,
   "2024": 13,
   "2025": 27,
   "variacion": 108,
   "situación": "Aumento de Casos",
   "COMUNA": "Aisén"
  },
  {
   "delito": "OTROS DESÓRDENES PÚBLICOS",
   "CODCOM": 11201,
   "2024": 5,
   "2025": 4,
   "variacion": -20,
   "situación": "Disminución de Casos",
   "COMUNA": "Aisén"
  },
  {
   "delito": "OTROS ROBOS CON FUERZA EN LAS COSAS",
   "CODCOM": 11201,
   "2024": 2,
   "2025": 9,
   "variacion": 350,
   "situación": "Aumento de Casos",
   "COMUNA": "Aisén"
  },
  {
   "delito": "RECEPTACIÓN",
   "CODCOM": 11201,
   "2024": 12,
   "2025": 10,
   "variacion": -17,
   "situación": "Disminución de Casos",
   "COMUNA": "Aisén"
  },
  {
   "delito": "ROBOS CON VIOLENCIA E INTIMIDACIÓN",
   "CODCOM": 11201,
   "2024": 22,
   "2025": 19,
   "variacion": -14,
   "situación": "Disminución de Casos",
   "COMUNA": "Aisén"
  },
  {
   "delito": "ROBOS DE VEHÍCULOS Y SUS ACCESORIOS",
   "CODCOM": 11201,
   "2024": 20,
   "2025": 23,
   "variacion": 15,
   "situación": "Aumento de Casos",
   "COMUNA": "Aisén"
  },
  {
   "delito": "ROBOS EN LUGARES HABITADOS Y NO HABITADOS",
   "CODCOM": 11201,
   "2024": 89,
   "2025": 58,
   "variacion": -35,
   "situación": "Disminución de Casos",
   "COMUNA": "Aisén"
  },
  {
   "delito": "ROBOS POR SORPRESA",
   "CODCOM": 11201,
   "2024": 2,
   "2025": 5,
   "variacion": 150,
   "situación": "Aumento de Casos",
   "COMUNA": "Aisén"
  },
  {
   "delito": "VIOLACIONES Y DELITOS SEXUALES",
   "CODCOM": 11201,
   "2024": 19,
   "2025": 20,
   "variacion": 5,
   "situación": "Aumento de Casos",
   "COMUNA": "Aisén"
  }
 ],
 "mensual": [
  {
   "delito": "AMENAZAS CON ARMAS",
   "CODCOM": 11201,
   "anio": 2024,
   "mes": 1,
   "casos": 2,
   "COMUNA": "Aisén"
  },
  {
   "delito": "AMENAZAS CON ARMAS",
   "CODCOM": 11201,
   "anio": 2024,
   "mes": 2,
   "casos": 2,
   "COMUNA": "Aisén"
  },
  {
   "delito": "AMENAZAS CON ARMAS",
   "CODCOM": 11201,
   "anio": 2024,
   "mes": 3,
   "casos": 0,
   "COMUNA": "Aisén"
  },
  {
   "delito": "AMENAZAS CON ARMAS",
   "CODCOM": 11201,
   "anio": 2024,
   "mes": 4,
   "casos": 1,
   "COMUNA": "Aisén"
  },
  {
   "delito": "AMENAZAS CON ARMAS",
   "CODCOM": 11201,
   "anio": 2024,
   "mes": 5,
   "casos": 0,
   "COMUNA": "Aisén"
  },
  {
   "delito": "AMENAZAS CON ARMAS",
   "CODCOM": 11201,
   "anio": 2024,
   "mes": 6,
   "casos": 2,
   "COMUNA": "Aisén"
  },
  {
   "delito": "AMENAZAS CON ARMAS",
   "CODCOM": 11201,
   "anio": 2024,
   "mes": 7,
   "casos": 1,
   "COMUNA": "Aisén"
  },
  {
   "delito": "AMENAZAS CON ARMAS",
   "CODCOM": 11201,
   "anio": 2024,
   "mes": 8,
   "casos": 4,
   "COMUNA": "Aisén"
  },
  {
   "delito": "AMENAZAS CON ARMAS",
   "CODCOM": 11201,
   "anio": 2024,
   "mes": 9,
   "casos": 1,
   "COMUNA": "Aisén"
  },
  {
   "delito": "AMENAZAS CON ARMAS",
   "CODCOM": 11201,
   "anio": 2024,
   "mes": 10,
   "casos": 0,
   "COMUNA": "Aisén"
  },
  {
   "delito": "AMENAZAS CON ARMAS",
   "CODCOM": 11201,
   "anio": 2024,
   "mes": 11,
   "casos": 2,
   "COMUNA": "Aisén"
  },
  {
   "delito": "AMENAZAS CON ARMAS",
   "CODCOM": 11201,
   "anio": 2024,
   "mes": 12,
   "casos": 2,
   "COMUNA": "Aisén"
  },
  {
   "delito": "AMENAZAS CON ARMAS",
   "CODCOM": 11201,
   "anio": 2025,
   "mes": 1,
   "casos": 0,
   "COMUNA": "Aisén"
  },
  {
   "delito": "AMENAZAS CON ARMAS",
   "CODCOM": 11201,
   "anio": 2025,
   "mes": 2,
   "casos": 1,
   "COMUNA": "Aisén"
  },
  {
   "delito": "AMENAZAS CON ARMAS",
   "CODCOM": 11201,
   "anio": 2025,
   "mes": 3,
   "casos": 0,
   "COMUNA": "Aisén"
  },
  {
   "delito": "AMENAZAS CON ARMAS",
   "CODCOM": 11201,
   "anio": 2025,
   "mes": 4,
   "casos": 0,
   "COMUNA": "Aisén"
  },
  {
   "delito": "AMENAZAS CON ARMAS",
   "CODCOM": 11201,
   "anio": 2025,
   "mes": 5,
   "casos": 1,
   "COMUNA": "Aisén"
  },
  {
   "delito": "AMENAZAS CON ARMAS",
   "CODCOM": 11201,
   "anio": 2025,
   "mes": 6,
   "casos": 4,
   "COMUNA": "Aisén"
  },
  {
   "delito": "AMENAZAS CON ARMAS",
   "CODCOM": 11201,
   "anio": 2025,
   "mes": 7,
   "casos": 0,
   "COMUNA": "Aisén"
  },
  {
   "delito": "AMENAZAS CON ARMAS",
   "CODCOM": 11201,
   "anio": 2025,
   "mes": 8,
   "casos": 1,
   "COMUNA": "Aisén"
  },
  {
   "delito": "AMENAZAS CON ARMAS",
   "CODCOM": 11201,
   "anio": 2025,
   "mes": 9,
   "casos": 1,
   "COMUNA": "Aisén"
  },
  {
   "delito": "AMENAZAS CON ARMAS",
   "CODCOM": 11201,
   "anio": 2025,
   "mes": 10,
   "casos": 2,
   "COMUNA": "Aisén"
  },
  {
   "delito": "AMENAZAS CON ARMAS",
   "CODCOM": 11201,
   "anio": 2025,
   "mes": 11,
   "casos": 0,
   "COMUNA": "Aisén"
  },
  {
   "delito": "AMENAZAS CON ARMAS",
   "CODCOM": 11201,
   "anio": 2025,
   "mes": 12,
   "casos": 0,
   "COMUNA": "Aisén"
  },
  {
   "delito": "AMENAZAS Y RIÑAS",
   "CODCOM": 11201,
   "anio": 2024,
   "mes": 1,
   "casos": 20,
   "COMUNA": "Aisén"
  },
  {
   "delito": "AMENAZAS Y RIÑAS",
   "CODCOM": 11201,
   "anio": 2024,
   "mes": 2,
   "casos": 18,
   "COMUNA": "Aisén"
  },
  {
   "delito": "AMENAZAS Y RIÑAS",
   "CODCOM": 11201,
   "anio": 2024,
   "mes": 3,
   "casos": 15,
   "COMUNA": "Aisén"
  },
  {
   "delito": "AMENAZAS Y RIÑAS",
   "CODCOM": 11201,
   "anio": 2024,
   "mes": 4,
   "casos": 10,
   "COMUNA": "Aisén"
  },
  {
   "delito": "AMENAZAS Y RIÑAS",
   "CODCOM": 11201,
   "anio": 2024,
   "mes": 5,
   "casos": 13,
   "COMUNA": "Aisén"
  },
  {
   "delito": "AMENAZAS Y RIÑAS",
   "CODCOM": 11201,
   "anio": 2024,
   "mes": 6,
   "casos": 14,
   "COMUNA": "Aisén"
  },
  {
   "delito": "AMENAZAS Y RIÑAS",
   "CODCOM": 11201,
   "anio": 2024,
   "mes": 7,
   "casos": 15,
   "COMUNA": "Aisén"
  },
  {
   "delito": "AMENAZAS Y RIÑAS",
   "CODCOM": 11201,
   "anio": 2024,
   "mes": 8,
   "casos": 21,
   "COMUNA": "Aisén"
  },
  {
   "delito": "AMENAZAS Y RIÑAS",
   "CODCOM": 11201,
   "anio": 2024,
   "mes": 9,
   "casos": 19,
   "COMUNA": "Aisén"
  },
  {
   "delito": "AMENAZAS Y RIÑAS",
   "CODCOM": 11201,
   "anio": 2024,
   "mes": 10,
   "casos": 22,
   "COMUNA": "Aisén"
  },
  {
   "delito": "AMENAZAS Y RIÑAS",
   "CODCOM": 11201,
   "anio": 2024,
   "mes": 11,
   "casos": 9,
   "COMUNA": "Aisén"
  },
  {
   "delito": "AMENAZAS Y RIÑAS",
   "CODCOM": 11201,
   "anio": 2024,
   "mes": 12,
   "casos": 16,
   "COMUNA": "Aisén"
  },
  {
   "delito": "AMENAZAS Y RIÑAS",
   "CODCOM": 11201,
   "anio": 2025,
   "mes": 1,
   "casos": 19,
   "COMUNA": "Aisén"
  },
  {
   "delito": "AMENAZAS Y RIÑAS",
   "CODCOM": 11201,
   "anio": 2025,
   "mes": 2,
   "casos": 24,
   "COMUNA": "Aisén"
  },
  {
   "delito": "AMENAZAS Y RIÑAS",
   "CODCOM": 11201,
   "anio": 2025,
   "mes": 3,
   "casos": 18,
   "COMUNA": "Aisén"
  },
  {
   "delito": "AMENAZAS Y RIÑAS",
   "CODCOM": 11201,
   "anio": 2025,
   "mes": 4,
   "casos": 13,
   "COMUNA": "Aisén"
  },
  {
   "delito": "AMENAZAS Y RIÑAS",
   "CODCOM": 11201,
   "anio": 2025,
   "mes": 5,
   "casos": 18,
   "COMUNA": "Aisén"
  },
  {
   "delito": "AMENAZAS Y RIÑAS",
   "CODCOM": 11201,
   "anio": 2025,
   "mes": 6,
   "casos": 32,
   "COMUNA": "Aisén"
  },
  {
   "delito": "AMENAZAS Y RIÑAS",
   "CODCOM": 11201,
   "anio": 2025,
   "mes": 7,
   "casos": 12,
   "COMUNA": "Aisén"
  },
  {
   "delito": "AMENAZAS Y RIÑAS",
   "CODCOM": 11201,
   "anio": 2025,
   "mes": 8,
   "casos": 17,
   "COMUNA": "Aisén"
  },
  {
   "delito": "AMENAZAS Y RIÑAS",
   "CODCOM": 11201,
   "anio": 2025,
   "mes": 9,
   "casos": 28,
   "COMUNA": "Aisén"
  },
  {
   "delito": "AMENAZAS Y RIÑAS",
   "CODCOM": 11201,
   "anio": 2025,
   "mes": 10,
   "casos": 20,
   "COMUNA": "Aisén"
  },
  {
   "delito": "AMENAZAS Y RIÑAS",
   "CODCOM": 11201,
   "anio": 2025,
   "mes": 11,
   "casos": 10,
   "COMUNA": "Aisén"
  },
  {
   "delito": "AMENAZAS Y RIÑAS",
   "CODCOM": 11201,
   "anio": 2025,
   "mes": 12,
   "casos": 12,
   "COMUNA": "Aisén"
  },
  {
   "delito": "CONSUMO DE ALCOHOL Y DE DROGAS EN LA VÍA PÚBLICA",
   "CODCOM": 11201,
   "anio": 2024,
   "mes": 1,
   "casos": 76,
   "COMUNA": "Aisén"
  },
  {
   "delito": "CONSUMO DE ALCOHOL Y DE DROGAS EN LA VÍA PÚBLICA",
   "CODCOM": 11201,
   "anio": 2024,
   "mes": 2,
   "casos": 51,
   "COMUNA": "Aisén"
  },
  {
   "delito": "CONSUMO DE ALCOHOL Y DE DROGAS EN LA VÍA PÚBLICA",
   "CODCOM": 11201,
   "anio": 2024,
   "mes": 3,
   "casos": 47,
   "COMUNA": "Aisén"
  },
  {
   "delito": "CONSUMO DE ALCOHOL Y DE DROGAS EN LA VÍA PÚBLICA",
   "CODCOM": 11201,
   "anio": 2024,
   "mes": 4,
   "casos": 43,
   "COMUNA": "Aisén"
  },
  {
   "delito": "CONSUMO DE ALCOHOL Y DE DROGAS EN LA VÍA PÚBLICA",
   "CODCOM": 11201,
   "anio": 2024,
   "mes": 5,
   "casos": 40,
   "COMUNA": "Aisén"
  },
  {
   "delito": "CONSUMO DE ALCOHOL Y DE DROGAS EN LA VÍA PÚBLICA",
   "CODCOM": 11201,
   "anio": 2024,
   "mes": 6,
   "casos": 58,
   "COMUNA": "Aisén"
  },
  {
   "delito": "CONSUMO DE ALCOHOL Y DE DROGAS EN LA VÍA PÚBLICA",
   "CODCOM": 11201,
   "anio": 2024,
   "mes": 7,
   "casos": 47,
   "COMUNA": "Aisén"
  },
  {
   "delito": "CONSUMO DE ALCOHOL Y DE DROGAS EN LA VÍA PÚBLICA",
   "CODCOM": 11201,
   "anio": 2024,
   "mes": 8,
   "casos": 65,
   "COMUNA": "Aisén"
  },
  {
   "delito": "CONSUMO DE ALCOHOL Y DE DROGAS EN LA VÍA PÚBLICA",
   "CODCOM": 11201,
   "anio": 2024,
   "mes": 9,
   "casos": 67,
   "COMUNA": "Aisén"
  },
  {
   "delito": "CONSUMO DE ALCOHOL Y DE DROGAS EN LA VÍA PÚBLICA",
   "CODCOM": 11201,
   "anio": 2024,
   "mes": 10,
   "casos": 40,
   "COMUNA": "Aisén"
  },
  {
   "delito": "CONSUMO DE ALCOHOL Y DE DROGAS EN LA VÍA PÚBLICA",
   "CODCOM": 11201,
   "anio": 2024,
   "mes": 11,
   "casos": 27,
   "COMUNA": "Aisén"
  },
  {
   "delito": "CONSUMO DE ALCOHOL Y DE DROGAS EN LA VÍA PÚBLICA",
   "CODCOM": 11201,
   "anio": 2024,
   "mes": 12,
   "casos": 45,
   "COMUNA": "Aisén"
  },
  {
   "delito": "CONSUMO DE ALCOHOL Y DE DROGAS EN LA VÍA PÚBLICA",
   "CODCOM": 11201,
   "anio": 2025,
   "mes": 1,
   "casos": 108,
   "COMUNA": "Aisén"
  },
  {
   "delito": "CONSUMO DE ALCOHOL Y DE DROGAS EN LA VÍA PÚBLICA",
   "CODCOM": 11201,
   "anio": 2025,
   "mes": 2,
   "casos": 24,
   "COMUNA": "Aisén"
  },
  {
   "delito": "CONSUMO DE ALCOHOL Y DE DROGAS EN LA VÍA PÚBLICA",
   "CODCOM": 11201,
   "anio": 2025,
   "mes": 3,
   "casos": 38,
   "COMUNA": "Aisén"
  },
  {
   "delito": "CONSUMO DE ALCOHOL Y DE DROGAS EN LA VÍA PÚBLICA",
   "CODCOM": 11201,
   "anio": 2025,
   "mes": 4,
   "casos": 44,
   "COMUNA": "Aisén"
  },
  {
   "delito": "CONSUMO DE ALCOHOL Y DE DROGAS EN LA VÍA PÚBLICA",
   "CODCOM": 11201,
   "anio": 2025,
   "mes": 5,
   "casos": 45,
   "COMUNA": "Aisén"
  },
  {
   "delito": "CONSUMO DE ALCOHOL Y DE DROGAS EN LA VÍA PÚBLICA",
   "CODCOM": 11201,
   "anio": 2025,
   "mes": 6,
   "casos": 43,
   "COMUNA": "Aisén"
  },
  {
   "delito": "CONSUMO DE ALCOHOL Y DE DROGAS EN LA VÍA PÚBLICA",
   "CODCOM": 11201,
   "anio": 2025,
   "mes": 7,
   "casos": 31,
   "COMUNA": "Aisén"
  },
  {
   "delito": "CONSUMO DE ALCOHOL Y DE DROGAS EN LA VÍA PÚBLICA",
   "CODCOM": 11201,
   "anio": 2025,
   "mes": 8,
   "casos": 60,
   "COMUNA": "Aisén"
  },
  {
   "delito": "CONSUMO DE ALCOHOL Y DE DROGAS EN LA VÍA PÚBLICA",
   "CODCOM": 11201,
   "anio": 2025,
   "mes": 9,
   "casos": 72,
   "COMUNA": "Aisén"
  },
  {
   "delito": "CONSUMO DE ALCOHOL Y DE DROGAS EN LA VÍA PÚBLICA",
   "CODCOM": 11201,
   "anio": 2025,
   "mes": 10,
   "casos": 40,
   "COMUNA": "Aisén"
  },
  {
   "delito": "CONSUMO DE ALCOHOL Y DE DROGAS EN LA VÍA PÚBLICA",
   "CODCOM": 11201,
   "anio": 2025,
   "mes": 11,
   "casos": 42,
   "COMUNA": "Aisén"
  },
  {
   "delito": "CONSUMO DE ALCOHOL Y DE DROGAS EN LA VÍA PÚBLICA",
   "CODCOM": 11201,
   "anio": 2025,
   "mes": 12,
   "casos": 33,
   "COMUNA": "Aisén"
  },
  {
   "delito": "DAÑOS",
   "CODCOM": 11201,
   "anio": 2024,
   "mes": 1,
   "casos": 21,
   "COMUNA": "Aisén"
  },
  {
   "delito": "DAÑOS",
   "CODCOM": 11201,
   "anio": 2024,
   "mes": 2,
   "casos": 15,
   "COMUNA": "Aisén"
  },
  {
   "delito": "DAÑOS",
   "CODCOM": 11201,
   "anio": 2024,
   "mes": 3,
   "casos": 12,
   "COMUNA": "Aisén"
  },
  {
   "delito": "DAÑOS",
   "CODCOM": 11201,
   "anio": 2024,
   "mes": 4,
   "casos": 13,
   "COMUNA": "Aisén"
  },
  {
   "delito": "DAÑOS",
   "CODCOM": 11201,
   "anio": 2024,
   "mes": 5,
   "casos": 22,
   "COMUNA": "Aisén"
  },
  {
   "delito": "DAÑOS",
   "CODCOM": 11201,
   "anio": 2024,
   "mes": 6,
   "casos": 20,
   "COMUNA": "Aisén"
  },
  {
   "delito": "DAÑOS",
   "CODCOM": 11201,
   "anio": 2024,
   "mes": 7,
   "casos": 19,
   "COMUNA": "Aisén"
  },
  {
   "delito": "DAÑOS",
   "CODCOM": 11201,
   "anio": 2024,
   "mes": 8,
   "casos": 12,
   "COMUNA": "Aisén"
  },
  {
   "delito": "DAÑOS",
   "CODCOM": 11201,
   "anio": 2024,
   "mes": 9,
   "casos": 24,
   "COMUNA": "Aisén"
  },
  {
   "delito": "DAÑOS",
   "CODCOM": 11201,
   "anio": 2024,
   "mes": 10,
   "casos": 21,
   "COMUNA": "Aisén"
  },
  {
   "delito": "DAÑOS",
   "CODCOM": 11201,
   "anio": 2024,
   "mes": 11,
   "casos": 14,
   "COMUNA": "Aisén"
  },
  {
   "delito": "DAÑOS",
   "CODCOM": 11201,
   "anio": 2024,
   "mes": 12,
   "casos": 18,
   "COMUNA": "Aisén"
  },
  {
   "delito": "DAÑOS",
   "CODCOM": 11201,
   "anio": 2025,
   "mes": 1,
   "casos": 16,
   "COMUNA": "Aisén"
  },
  {
   "delito": "DAÑOS",
   "CODCOM": 11201,
   "anio": 2025,
   "mes": 2,
   "casos": 20,
   "COMUNA": "Aisén"
  },
  {
   "delito": "DAÑOS",
   "CODCOM": 11201,
   "anio": 2025,
   "mes": 3,
   "casos": 25,
   "COMUNA": "Aisén"
  },
  {
   "delito": "DAÑOS",
   "CODCOM": 11201,
   "anio": 2025,
   "mes": 4,
   "casos": 10,
   "COMUNA": "Aisén"
  },
  {
   "delito": "DAÑOS",
   "CODCOM": 11201,
   "anio": 2025,
   "mes": 5,
   "casos": 13,
   "COMUNA": "Aisén"
  },
  {
   "delito": "DAÑOS",
   "CODCOM": 11201,
   "anio": 2025,
   "mes": 6,
   "casos": 14,
   "COMUNA": "Aisén"
  },
  {
   "delito": "DAÑOS",
   "CODCOM": 11201,
   "anio": 2025,
   "mes": 7,
   "casos": 11,
   "COMUNA": "Aisén"
  },
  {
   "delito": "DAÑOS",
   "CODCOM": 11201,
   "anio": 2025,
   "mes": 8,
   "casos": 12,
   "COMUNA": "Aisén"
  },
  {
   "delito": "DAÑOS",
   "CODCOM": 11201,
   "anio": 2025,
   "mes": 9,
   "casos": 16,
   "COMUNA": "Aisén"
  },
  {
   "delito": "DAÑOS",
   "CODCOM": 11201,
   "anio": 2025,
   "mes": 10,
   "casos": 10,
   "COMUNA": "Aisén"
  },
  {
   "delito": "DAÑOS",
   "CODCOM": 11201,
   "anio": 2025,
   "mes": 11,
   "casos": 4,
   "COMUNA": "Aisén"
  },
  {
   "delito": "DAÑOS",
   "CODCOM": 11201,
   "anio": 2025,
   "mes": 12,
   "casos": 1,
   "COMUNA": "Aisén"
  },
  {
   "delito": "DELITOS EN CONTEXTO DE VIOLENCIA INTRAFAMILIAR",
   "CODCOM": 11201,
   "anio": 2024,
   "mes": 1,
   "casos": 44,
   "COMUNA": "Aisén"
  },
  {
   "delito": "DELITOS EN CONTEXTO DE VIOLENCIA INTRAFAMILIAR",
   "CODCOM": 11201,
   "anio": 2024,
   "mes": 2,
   "casos": 34,
   "COMUNA": "Aisén"
  },
  {
   "delito": "DELITOS EN CONTEXTO DE VIOLENCIA INTRAFAMILIAR",
   "CODCOM": 11201,
   "anio": 2024,
   "mes": 3,
   "casos": 20,
   "COMUNA": "Aisén"
  },
  {
   "delito": "DELITOS EN CONTEXTO DE VIOLENCIA INTRAFAMILIAR",
   "CODCOM": 11201,
   "anio": 2024,
   "mes": 4,
   "casos": 29,
   "COMUNA": "Aisén"
  },
  {
   "delito": "DELITOS EN CONTEXTO DE VIOLENCIA INTRAFAMILIAR",
   "CODCOM": 11201,
   "anio": 2024,
   "mes": 5,
   "casos": 33,
   "COMUNA": "Aisén"
  },
  {
   "delito": "DELITOS EN CONTEXTO DE VIOLENCIA INTRAFAMILIAR",
   "CODCOM": 11201,
   "anio": 2024,
   "mes": 6,
   "casos": 24,
   "COMUNA": "Aisén"
  },
  {
   "delito": "DELITOS EN CONTEXTO DE VIOLENCIA INTRAFAMILIAR",
   "CODCOM": 11201,
   "anio": 2024,
   "mes": 7,
   "casos": 39,
   "COMUNA": "Aisén"
  },
  {
   "delito": "DELITOS EN CONTEXTO DE VIOLENCIA INTRAFAMILIAR",
   "CODCOM": 11201,
   "anio": 2024,
   "mes": 8,
   "casos": 28,
   "COMUNA": "Aisén"
  },
  {
   "delito": "DELITOS EN CONTEXTO DE VIOLENCIA INTRAFAMILIAR",
   "CODCOM": 11201,
   "anio": 2024,
   "mes": 9,
   "casos": 41,
   "COMUNA": "Aisén"
  },
  {
   "delito": "DELITOS EN CONTEXTO DE VIOLENCIA INTRAFAMILIAR",
   "CODCOM": 11201,
   "anio": 2024,
   "mes": 10,
   "casos": 39,
   "COMUNA": "Aisén"
  },
  {
   "delito": "DELITOS EN CONTEXTO DE VIOLENCIA INTRAFAMILIAR",
   "CODCOM": 11201,
   "anio": 2024,
   "mes": 11,
   "casos": 38,
   "COMUNA": "Aisén"
  },
  {
   "delito": "DELITOS EN CONTEXTO DE VIOLENCIA INTRAFAMILIAR",
   "CODCOM": 11201,
   "anio": 2024,
   "mes": 12,
   "casos": 32,
   "COMUNA": "Aisén"
  },
  {
   "delito": "DELITOS EN CONTEXTO DE VIOLENCIA INTRAFAMILIAR",
   "CODCOM": 11201,
   "anio": 2025,
   "mes": 1,
   "casos": 34,
   "COMUNA": "Aisén"
  },
  {
   "delito": "DELITOS EN CONTEXTO DE VIOLENCIA INTRAFAMILIAR",
   "CODCOM": 11201,
   "anio": 2025,
   "mes": 2,
   "casos": 28,
   "COMUNA": "Aisén"
  },
  {
   "delito": "DELITOS EN CONTEXTO DE VIOLENCIA INTRAFAMILIAR",
   "CODCOM": 11201,
   "anio": 2025,
   "mes": 3,
   "casos": 23,
   "COMUNA": "Aisén"
  },
  {
   "delito": "DELITOS EN CONTEXTO DE VIOLENCIA INTRAFAMILIAR",
   "CODCOM": 11201,
   "anio": 2025,
   "mes": 4,
   "casos": 22,
   "COMUNA": "Aisén"
  },
  {
   "delito": "DELITOS EN CONTEXTO DE VIOLENCIA INTRAFAMILIAR",
   "CODCOM": 11201,
   "anio": 2025,
   "mes": 5,
   "casos": 21,
   "COMUNA": "Aisén"
  },
  {
   "delito": "DELITOS EN CONTEXTO DE VIOLENCIA INTRAFAMILIAR",
   "CODCOM": 11201,
   "anio": 2025,
   "mes": 6,
   "casos": 27,
   "COMUNA": "Aisén"
  },
  {
   "delito": "DELITOS EN CONTEXTO DE VIOLENCIA INTRAFAMILIAR",
   "CODCOM": 11201,
   "anio": 2025,
   "mes": 7,
   "casos": 22,
   "COMUNA": "Aisén"
  },
  {
   "delito": "DELITOS EN CONTEXTO DE VIOLENCIA INTRAFAMILIAR",
   "CODCOM": 11201,
   "anio": 2025,
   "mes": 8,
   "casos": 26,
   "COMUNA": "Aisén"
  },
  {
   "delito": "DELITOS EN CONTEXTO DE VIOLENCIA INTRAFAMILIAR",
   "CODCOM": 11201,
   "anio": 2025,
   "mes": 9,
   "casos": 39,
   "COMUNA": "Aisén"
  },
  {
   "delito": "DELITOS EN CONTEXTO DE VIOLENCIA INTRAFAMILIAR",
   "CODCOM": 11201,
   "anio": 2025,
   "mes": 10,
   "casos": 21,
   "COMUNA": "Aisén"
  },
  {
   "delito": "DELITOS EN CONTEXTO DE VIOLENCIA INTRAFAMILIAR",
   "CODCOM": 11201,
   "anio": 2025,
   "mes": 11,
   "casos": 16,
   "COMUNA": "Aisén"
  },
  {
   "delito": "DELITOS EN CONTEXTO DE VIOLENCIA INTRAFAMILIAR",
   "CODCOM": 11201,
   "anio": 2025,
   "mes": 12,
   "casos": 16,
   "COMUNA": "Aisén"
  },
  {
   "delito": "HOMICIDIOS Y FEMICIDIOS",
   "CODCOM": 11201,
   "anio": 2024,
   "mes": 1,
   "casos": 0,
   "COMUNA": "Aisén"
  },
  {
   "delito": "HOMICIDIOS Y FEMICIDIOS",
   "CODCOM": 11201,
   "anio": 2024,
   "mes": 2,
   "casos": 0,
   "COMUNA": "Aisén"
  },
  {
   "delito": "HOMICIDIOS Y FEMICIDIOS",
   "CODCOM": 11201,
   "anio": 2024,
   "mes": 3,
   "casos": 1,
   "COMUNA": "Aisén"
  },
  {
   "delito": "HOMICIDIOS Y FEMICIDIOS",
   "CODCOM": 11201,
   "anio": 2024,
   "mes": 4,
   "casos": 0,
   "COMUNA": "Aisén"
  },
  {
   "delito": "HOMICIDIOS Y FEMICIDIOS",
   "CODCOM": 11201,
   "anio": 2024,
   "mes": 5,
   "casos": 0,
   "COMUNA": "Aisén"
  },
  {
   "delito": "HOMICIDIOS Y FEMICIDIOS",
   "CODCOM": 11201,
   "anio": 2024,
   "mes": 6,
   "casos": 0,
   "COMUNA": "Aisén"
  },
  {
   "delito": "HOMICIDIOS Y FEMICIDIOS",
   "CODCOM": 11201,
   "anio": 2024,
   "mes": 7,
   "casos": 0,
   "COMUNA": "Aisén"
  },
  {
   "delito": "HOMICIDIOS Y FEMICIDIOS",
   "CODCOM": 11201,
   "anio": 2024,
   "mes": 8,
   "casos": 0,
   "COMUNA": "Aisén"
  },
  {
   "delito": "HOMICIDIOS Y FEMICIDIOS",
   "CODCOM": 11201,
   "anio": 2024,
   "mes": 9,
   "casos": 1,
   "COMUNA": "Aisén"
  },
  {
   "delito": "HOMICIDIOS Y FEMICIDIOS",
   "CODCOM": 11201,
   "anio": 2024,
   "mes": 10,
   "casos": 0,
   "COMUNA": "Aisén"
  },
  {
   "delito": "HOMICIDIOS Y FEMICIDIOS",
   "CODCOM": 11201,
   "anio": 2024,
   "mes": 11,
   "casos": 0,
   "COMUNA": "Aisén"
  },
  {
   "delito": "HOMICIDIOS Y FEMICIDIOS",
   "CODCOM": 11201,
   "anio": 2024,
   "mes": 12,
   "casos": 0,
   "COMUNA": "Aisén"
  },
  {
   "delito": "HOMICIDIOS Y FEMICIDIOS",
   "CODCOM": 11201,
   "anio": 2025,
   "mes": 1,
   "casos": 0,
   "COMUNA": "Aisén"
  },
  {
   "delito": "HOMICIDIOS Y FEMICIDIOS",
   "CODCOM": 11201,
   "anio": 2025,
   "mes": 2,
   "casos": 0,
   "COMUNA": "Aisén"
  },
  {
   "delito": "HOMICIDIOS Y FEMICIDIOS",
   "CODCOM": 11201,
   "anio": 2025,
   "mes": 3,
   "casos": 0,
   "COMUNA": "Aisén"
  },
  {
   "delito": "HOMICIDIOS Y FEMICIDIOS",
   "CODCOM": 11201,
   "anio": 2025,
   "mes": 4,
   "casos": 0,
   "COMUNA": "Aisén"
  },
  {
   "delito": "HOMICIDIOS Y FEMICIDIOS",
   "CODCOM": 11201,
   "anio": 2025,
   "mes": 5,
   "casos": 0,
   "COMUNA": "Aisén"
  },
  {
   "delito": "HOMICIDIOS Y FEMICIDIOS",
   "CODCOM": 11201,
   "anio": 2025,
   "mes": 6,
   "casos": 0,
   "COMUNA": "Aisén"
  },
  {
   "delito": "HOMICIDIOS Y FEMICIDIOS",
   "CODCOM": 11201,
   "anio": 2025,
   "mes": 7,
   "casos": 0,
   "COMUNA": "Aisén"
  },
  {
   "delito": "HOMICIDIOS Y FEMICIDIOS",
   "CODCOM": 11201,
   "anio": 2025,
   "mes": 8,
   "casos": 1,
   "COMUNA": "Aisén"
  },
  {
   "delito": "HOMICIDIOS Y FEMICIDIOS",
   "CODCOM": 11201,
   "anio": 2025,
   "mes": 9,
   "casos": 0,
   "COMUNA": "Aisén"
  },
  {
   "delito": "HOMICIDIOS Y FEMICIDIOS",
   "CODCOM": 11201,
   "anio": 2025,
   "mes": 10,
   "casos": 0,
   "COMUNA": "Aisén"
  },
  {
   "delito": "HOMICIDIOS Y FEMICIDIOS",
   "CODCOM": 11201,
   "anio": 2025,
   "mes": 11,
   "casos": 0,
   "COMUNA": "Aisén"
  },
  {
   "delito": "HOMICIDIOS Y FEMICIDIOS",
   "CODCOM": 11201,
   "anio": 2025,
   "mes": 12,
   "casos": 0,
   "COMUNA": "Aisén"
  },
  {
   "delito": "HURTOS",
   "CODCOM": 11201,
   "anio": 2024,
   "mes": 1,
   "casos": 17,
   "COMUNA": "Aisén"
  },
  {
   "delito": "HURTOS",
   "CODCOM": 11201,
   "anio": 2024,
   "mes": 2,
   "casos": 4,
   "COMUNA": "Aisén"
  },
  {
   "delito": "HURTOS",
   "CODCOM": 11201,
   "anio": 2024,
   "mes": 3,
   "casos": 8,
   "COMUNA": "Aisén"
  },
  {
   "delito": "HURTOS",
   "CODCOM": 11201,
   "anio": 2024,
   "mes": 4,
   "casos": 10,
   "COMUNA": "Aisén"
  },
  {
   "delito": "HURTOS",
   "CODCOM": 11201,
   "anio": 2024,
   "mes": 5,
   "casos": 10,
   "COMUNA": "Aisén"
  },
  {
   "delito": "HURTOS",
   "CODCOM": 11201,
   "anio": 2024,
   "mes": 6,
   "casos": 11,
   "COMUNA": "Aisén"
  },
  {
   "delito": "HURTOS",
   "CODCOM": 11201,
   "anio": 2024,
   "mes": 7,
   "casos": 21,
   "COMUNA": "Aisén"
  },
  {
   "delito": "HURTOS",
   "CODCOM": 11201,
   "anio": 2024,
   "mes": 8,
   "casos": 9,
   "COMUNA": "Aisén"
  },
  {
   "delito": "HURTOS",
   "CODCOM": 11201,
   "anio": 2024,
   "mes": 9,
   "casos": 13,
   "COMUNA": "Aisén"
  },
  {
   "delito": "HURTOS",
   "CODCOM": 11201,
   "anio": 2024,
   "mes": 10,
   "casos": 11,
   "COMUNA": "Aisén"
  },
  {
   "delito": "HURTOS",
   "CODCOM": 11201,
   "anio": 2024,
   "mes": 11,
   "casos": 10,
   "COMUNA": "Aisén"
  },
  {
   "delito": "HURTOS",
   "CODCOM": 11201,
   "anio": 2024,
   "mes": 12,
   "casos": 13,
   "COMUNA": "Aisén"
  },
  {
   "delito": "HURTOS",
   "CODCOM": 11201,
   "anio": 2025,
   "mes": 1,
   "casos": 12,
   "COMUNA": "Aisén"
  },
  {
   "delito": "HURTOS",
   "CODCOM": 11201,
   "anio": 2025,
   "mes": 2,
   "casos": 6,
   "COMUNA": "Aisén"
  },
  {
   "delito": "HURTOS",
   "CODCOM": 11201,
   "anio": 2025,
   "mes": 3,
   "casos": 10,
   "COMUNA": "Aisén"
  },
  {
   "delito": "HURTOS",
   "CODCOM": 11201,
   "anio": 2025,
   "mes": 4,
   "casos": 16,
   "COMUNA": "Aisén"
  },
  {
   "delito": "HURTOS",
   "CODCOM": 11201,
   "anio": 2025,
   "mes": 5,
   "casos": 3,
   "COMUNA": "Aisén"
  },
  {
   "delito": "HURTOS",
   "CODCOM": 11201,
   "anio": 2025,
   "mes": 6,
   "casos": 14,
   "COMUNA": "Aisén"
  },
  {
   "delito": "HURTOS",
   "CODCOM": 11201,
   "anio": 2025,
   "mes": 7,
   "casos": 15,
   "COMUNA": "Aisén"
  },
  {
   "delito": "HURTOS",
   "CODCOM": 11201,
   "anio": 2025,
   "mes": 8,
   "casos": 5,
   "COMUNA": "Aisén"
  },
  {
   "delito": "HURTOS",
   "CODCOM": 11201,
   "anio": 2025,
   "mes": 9,
   "casos": 8,
   "COMUNA": "Aisén"
  },
  {
   "delito": "HURTOS",
   "CODCOM": 11201,
   "anio": 2025,
   "mes": 10,
   "casos": 5,
   "COMUNA": "Aisén"
  },
  {
   "delito": "HURTOS",
   "CODCOM": 11201,
   "anio": 2025,
   "mes": 11,
   "casos": 6,
   "COMUNA": "Aisén"
  },
  {
   "delito": "HURTOS",
   "CODCOM": 11201,
   "anio": 2025,
   "mes": 12,
   "casos": 4,
   "COMUNA": "Aisén"
  },
  {
   "delito": "INCIVILIDADES",
   "CODCOM": 11201,
   "anio": 2024,
   "mes": 1,
   "casos": 17,
   "COMUNA": "Aisén"
  },
  {
   "delito": "INCIVILIDADES",
   "CODCOM": 11201,
   "anio": 2024,
   "mes": 2,
   "casos": 11,
   "COMUNA": "Aisén"
  },
  {
   "delito": "INCIVILIDADES",
   "CODCOM": 11201,
   "anio": 2024,
   "mes": 3,
   "casos": 19,
   "COMUNA": "Aisén"
  },
  {
   "delito": "INCIVILIDADES",
   "CODCOM": 11201,
   "anio": 2024,
   "mes": 4,
   "casos": 21,
   "COMUNA": "Aisén"
  },
  {
   "delito": "INCIVILIDADES",
   "CODCOM": 11201,
   "anio": 2024,
   "mes": 5,
   "casos": 16,
   "COMUNA": "Aisén"
  },
  {
   "delito": "INCIVILIDADES",
   "CODCOM": 11201,
   "anio": 2024,
   "mes": 6,
   "casos": 15,
   "COMUNA": "Aisén"
  },
  {
   "delito": "INCIVILIDADES",
   "CODCOM": 11201,
   "anio": 2024,
   "mes": 7,
   "casos": 16,
   "COMUNA": "Aisén"
  },
  {
   "delito": "INCIVILIDADES",
   "CODCOM": 11201,
   "anio": 2024,
   "mes": 8,
   "casos": 22,
   "COMUNA": "Aisén"
  },
  {
   "delito": "INCIVILIDADES",
   "CODCOM": 11201,
   "anio": 2024,
   "mes": 9,
   "casos": 23,
   "COMUNA": "Aisén"
  },
  {
   "delito": "INCIVILIDADES",
   "CODCOM": 11201,
   "anio": 2024,
   "mes": 10,
   "casos": 12,
   "COMUNA": "Aisén"
  },
  {
   "delito": "INCIVILIDADES",
   "CODCOM": 11201,
   "anio": 2024,
   "mes": 11,
   "casos": 15,
   "COMUNA": "Aisén"
  },
  {
   "delito": "INCIVILIDADES",
   "CODCOM": 11201,
   "anio": 2024,
   "mes": 12,
   "casos": 15,
   "COMUNA": "Aisén"
  },
  {
   "delito": "INCIVILIDADES",
   "CODCOM": 11201,
   "anio": 2025,
   "mes": 1,
   "casos": 18,
   "COMUNA": "Aisén"
  },
  {
   "delito": "INCIVILIDADES",
   "CODCOM": 11201,
   "anio": 2025,
   "mes": 2,
   "casos": 14,
   "COMUNA": "Aisén"
  },
  {
   "delito": "INCIVILIDADES",
   "CODCOM": 11201,
   "anio": 2025,
   "mes": 3,
   "casos": 13,
   "COMUNA": "Aisén"
  },
  {
   "delito": "INCIVILIDADES",
   "CODCOM": 11201,
   "anio": 2025,
   "mes": 4,
   "casos": 15,
   "COMUNA": "Aisén"
  },
  {
   "delito": "INCIVILIDADES",
   "CODCOM": 11201,
   "anio": 2025,
   "mes": 5,
   "casos": 13,
   "COMUNA": "Aisén"
  },
  {
   "delito": "INCIVILIDADES",
   "CODCOM": 11201,
   "anio": 2025,
   "mes": 6,
   "casos": 16,
   "COMUNA": "Aisén"
  },
  {
   "delito": "INCIVILIDADES",
   "CODCOM": 11201,
   "anio": 2025,
   "mes": 7,
   "casos": 11,
   "COMUNA": "Aisén"
  },
  {
   "delito": "INCIVILIDADES",
   "CODCOM": 11201,
   "anio": 2025,
   "mes": 8,
   "casos": 17,
   "COMUNA": "Aisén"
  },
  {
   "delito": "INCIVILIDADES",
   "CODCOM": 11201,
   "anio": 2025,
   "mes": 9,
   "casos": 16,
   "COMUNA": "Aisén"
  },
  {
   "delito": "INCIVILIDADES",
   "CODCOM": 11201,
   "anio": 2025,
   "mes": 10,
   "casos": 18,
   "COMUNA": "Aisén"
  },
  {
   "delito": "INCIVILIDADES",
   "CODCOM": 11201,
   "anio": 2025,
   "mes": 11,
   "casos": 6,
   "COMUNA": "Aisén"
  },
  {
   "delito": "INCIVILIDADES",
   "CODCOM": 11201,
   "anio": 2025,
   "mes": 12,
   "casos": 8,
   "COMUNA": "Aisén"
  },
  {
   "delito": "LESIONES GRAVES",
   "CODCOM": 11201,
   "anio": 2024,
   "mes": 1,
   "casos": 4,
   "COMUNA": "Aisén"
  },
  {
   "delito": "LESIONES GRAVES",
   "CODCOM": 11201,
   "anio": 2024,
   "mes": 2,
   "casos": 1,
   "COMUNA": "Aisén"
  },
  {
   "delito": "LESIONES GRAVES",
   "CODCOM": 11201,
   "anio": 2024,
   "mes": 3,
   "casos": 2,
   "COMUNA": "Aisén"
  },
  {
   "delito": "LESIONES GRAVES",
   "CODCOM": 11201,
   "anio": 2024,
   "mes": 4,
   "casos": 0,
   "COMUNA": "Aisén"
  },
  {
   "delito": "LESIONES GRAVES",
   "CODCOM": 11201,
   "anio": 2024,
   "mes": 5,
   "casos": 2,
   "COMUNA": "Aisén"
  },
  {
   "delito": "LESIONES GRAVES",
   "CODCOM": 11201,
   "anio": 2024,
   "mes": 6,
   "casos": 0,
   "COMUNA": "Aisén"
  },
  {
   "delito": "LESIONES GRAVES",
   "CODCOM": 11201,
   "anio": 2024,
   "mes": 7,
   "casos": 1,
   "COMUNA": "Aisén"
  },
  {
   "delito": "LESIONES GRAVES",
   "CODCOM": 11201,
   "anio": 2024,
   "mes": 8,
   "casos": 3,
   "COMUNA": "Aisén"
  },
  {
   "delito": "LESIONES GRAVES",
   "CODCOM": 11201,
   "anio": 2024,
   "mes": 9,
   "casos": 0,
   "COMUNA": "Aisén"
  },
  {
   "delito": "LESIONES GRAVES",
   "CODCOM": 11201,
   "anio": 2024,
   "mes": 10,
   "casos": 2,
   "COMUNA": "Aisén"
  },
  {
   "delito": "LESIONES GRAVES",
   "CODCOM": 11201,
   "anio": 2024,
   "mes": 11,
   "casos": 1,
   "COMUNA": "Aisén"
  },
  {
   "delito": "LESIONES GRAVES",
   "CODCOM": 11201,
   "anio": 2024,
   "mes": 12,
   "casos": 0,
   "COMUNA": "Aisén"
  },
  {
   "delito": "LESIONES GRAVES",
   "CODCOM": 11201,
   "anio": 2025,
   "mes": 1,
   "casos": 0,
   "COMUNA": "Aisén"
  },
  {
   "delito": "LESIONES GRAVES",
   "CODCOM": 11201,
   "anio": 2025,
   "mes": 2,
   "casos": 0,
   "COMUNA": "Aisén"
  },
  {
   "delito": "LESIONES GRAVES",
   "CODCOM": 11201,
   "anio": 2025,
   "mes": 3,
   "casos": 3,
   "COMUNA": "Aisén"
  },
  {
   "delito": "LESIONES GRAVES",
   "CODCOM": 11201,
   "anio": 2025,
   "mes": 4,
   "casos": 1,
   "COMUNA": "Aisén"
  },
  {
   "delito": "LESIONES GRAVES",
   "CODCOM": 11201,
   "anio": 2025,
   "mes": 5,
   "casos": 1,
   "COMUNA": "Aisén"
  },
  {
   "delito": "LESIONES GRAVES",
   "CODCOM": 11201,
   "anio": 2025,
   "mes": 6,
   "casos": 3,
   "COMUNA": "Aisén"
  },
  {
   "delito": "LESIONES GRAVES",
   "CODCOM": 11201,
   "anio": 2025,
   "mes": 7,
   "casos": 1,
   "COMUNA": "Aisén"
  },
  {
   "delito": "LESIONES GRAVES",
   "CODCOM": 11201,
   "anio": 2025,
   "mes": 8,
   "casos": 1,
   "COMUNA": "Aisén"
  },
  {
   "delito": "LESIONES GRAVES",
   "CODCOM": 11201,
   "anio": 2025,
   "mes": 9,
   "casos": 0,
   "COMUNA": "Aisén"
  },
  {
   "delito": "LESIONES GRAVES",
   "CODCOM": 11201,
   "anio": 2025,
   "mes": 10,
   "casos": 1,
   "COMUNA": "Aisén"
  },
  {
   "delito": "LESIONES GRAVES",
   "CODCOM": 11201,
   "anio": 2025,
   "mes": 11,
   "casos": 0,
   "COMUNA": "Aisén"
  },
  {
   "delito": "LESIONES GRAVES",
   "CODCOM": 11201,
   "anio": 2025,
   "mes": 12,
   "casos": 0,
   "COMUNA": "Aisén"
  },
  {
   "delito": "LESIONES LEVES",
   "CODCOM": 11201,
   "anio": 2024,
   "mes": 1,
   "casos": 11,
   "COMUNA": "Aisén"
  },
  {
   "delito": "LESIONES LEVES",
   "CODCOM": 11201,
   "anio": 2024,
   "mes": 2,
   "casos": 3,
   "COMUNA": "Aisén"
  },
  {
   "delito": "LESIONES LEVES",
   "CODCOM": 11201,
   "anio": 2024,
   "mes": 3,
   "casos": 4,
   "COMUNA": "Aisén"
  },
  {
   "delito": "LESIONES LEVES",
   "CODCOM": 11201,
   "anio": 2024,
   "mes": 4,
   "casos": 13,
   "COMUNA": "Aisén"
  },
  {
   "delito": "LESIONES LEVES",
   "CODCOM": 11201,
   "anio": 2024,
   "mes": 5,
   "casos": 13,
   "COMUNA": "Aisén"
  },
  {
   "delito": "LESIONES LEVES",
   "CODCOM": 11201,
   "anio": 2024,
   "mes": 6,
   "casos": 10,
   "COMUNA": "Aisén"
  },
  {
   "delito": "LESIONES LEVES",
   "CODCOM": 11201,
   "anio": 2024,
   "mes": 7,
   "casos": 4,
   "COMUNA": "Aisén"
  },
  {
   "delito": "LESIONES LEVES",
   "CODCOM": 11201,
   "anio": 2024,
   "mes": 8,
   "casos": 9,
   "COMUNA": "Aisén"
  },
  {
   "delito": "LESIONES LEVES",
   "CODCOM": 11201,
   "anio": 2024,
   "mes": 9,
   "casos": 8,
   "COMUNA": "Aisén"
  },
  {
   "delito": "LESIONES LEVES",
   "CODCOM": 11201,
   "anio": 2024,
   "mes": 10,
   "casos": 15,
   "COMUNA": "Aisén"
  },
  {
   "delito": "LESIONES LEVES",
   "CODCOM": 11201,
   "anio": 2024,
   "mes": 11,
   "casos": 8,
   "COMUNA": "Aisén"
  },
  {
   "delito": "LESIONES LEVES",
   "CODCOM": 11201,
   "anio": 2024,
   "mes": 12,
   "casos": 15,
   "COMUNA": "Aisén"
  },
  {
   "delito": "LESIONES LEVES",
   "CODCOM": 11201,
   "anio": 2025,
   "mes": 1,
   "casos": 11,
   "COMUNA": "Aisén"
  },
  {
   "delito": "LESIONES LEVES",
   "CODCOM": 11201,
   "anio": 2025,
   "mes": 2,
   "casos": 3,
   "COMUNA": "Aisén"
  },
  {
   "delito": "LESIONES LEVES",
   "CODCOM": 11201,
   "anio": 2025,
   "mes": 3,
   "casos": 12,
   "COMUNA": "Aisén"
  },
  {
   "delito": "LESIONES LEVES",
   "CODCOM": 11201,
   "anio": 2025,
   "mes": 4,
   "casos": 7,
   "COMUNA": "Aisén"
  },
  {
   "delito": "LESIONES LEVES",
   "CODCOM": 11201,
   "anio": 2025,
   "mes": 5,
   "casos": 8,
   "COMUNA": "Aisén"
  },
  {
   "delito": "LESIONES LEVES",
   "CODCOM": 11201,
   "anio": 2025,
   "mes": 6,
   "casos": 9,
   "COMUNA": "Aisén"
  },
  {
   "delito": "LESIONES LEVES",
   "CODCOM": 11201,
   "anio": 2025,
   "mes": 7,
   "casos": 7,
   "COMUNA": "Aisén"
  },
  {
   "delito": "LESIONES LEVES",
   "CODCOM": 11201,
   "anio": 2025,
   "mes": 8,
   "casos": 8,
   "COMUNA": "Aisén"
  },
  {
   "delito": "LESIONES LEVES",
   "CODCOM": 11201,
   "anio": 2025,
   "mes": 9,
   "casos": 16,
   "COMUNA": "Aisén"
  },
  {
   "delito": "LESIONES LEVES",
   "CODCOM": 11201,
   "anio": 2025,
   "mes": 10,
   "casos": 7,
   "COMUNA": "Aisén"
  },
  {
   "delito": "LESIONES LEVES",
   "CODCOM": 11201,
   "anio": 2025,
   "mes": 11,
   "casos": 5,
   "COMUNA": "Aisén"
  },
  {
   "delito": "LESIONES LEVES",
   "CODCOM": 11201,
   "anio": 2025,
   "mes": 12,
   "casos": 7,
   "COMUNA": "Aisén"
  },
  {
   "delito": "LESIONES MENOS GRAVES",
   "CODCOM": 11201,
   "anio": 2024,
   "mes": 1,
   "casos": 1,
   "COMUNA": "Aisén"
  },
  {
   "delito": "LESIONES MENOS GRAVES",
   "CODCOM": 11201,
   "anio": 2024,
   "mes": 2,
   "casos": 2,
   "COMUNA": "Aisén"
  },
  {
   "delito": "LESIONES MENOS GRAVES",
   "CODCOM": 11201,
   "anio": 2024,
   "mes": 3,
   "casos": 3,
   "COMUNA": "Aisén"
  },
  {
   "delito": "LESIONES MENOS GRAVES",
   "CODCOM": 11201,
   "anio": 2024,
   "mes": 4,
   "casos": 0,
   "COMUNA": "Aisén"
  },
  {
   "delito": "LESIONES MENOS GRAVES",
   "CODCOM": 11201,
   "anio": 2024,
   "mes": 5,
   "casos": 3,
   "COMUNA": "Aisén"
  },
  {
   "delito": "LESIONES MENOS GRAVES",
   "CODCOM": 11201,
   "anio": 2024,
   "mes": 6,
   "casos": 3,
   "COMUNA": "Aisén"
  },
  {
   "delito": "LESIONES MENOS GRAVES",
   "CODCOM": 11201,
   "anio": 2024,
   "mes": 7,
   "casos": 3,
   "COMUNA": "Aisén"
  },
  {
   "delito": "LESIONES MENOS GRAVES",
   "CODCOM": 11201,
   "anio": 2024,
   "mes": 8,
   "casos": 1,
   "COMUNA": "Aisén"
  },
  {
   "delito": "LESIONES MENOS GRAVES",
   "CODCOM": 11201,
   "anio": 2024,
   "mes": 9,
   "casos": 5,
   "COMUNA": "Aisén"
  },
  {
   "delito": "LESIONES MENOS GRAVES",
   "CODCOM": 11201,
   "anio": 2024,
   "mes": 10,
   "casos": 3,
   "COMUNA": "Aisén"
  },
  {
   "delito": "LESIONES MENOS GRAVES",
   "CODCOM": 11201,
   "anio": 2024,
   "mes": 11,
   "casos": 1,
   "COMUNA": "Aisén"
  },
  {
   "delito": "LESIONES MENOS GRAVES",
   "CODCOM": 11201,
   "anio": 2024,
   "mes": 12,
   "casos": 2,
   "COMUNA": "Aisén"
  },
  {
   "delito": "LESIONES MENOS GRAVES",
   "CODCOM": 11201,
   "anio": 2025,
   "mes": 1,
   "casos": 3,
   "COMUNA": "Aisén"
  },
  {
   "delito": "LESIONES MENOS GRAVES",
   "CODCOM": 11201,
   "anio": 2025,
   "mes": 2,
   "casos": 3,
   "COMUNA": "Aisén"
  },
  {
   "delito": "LESIONES MENOS GRAVES",
   "CODCOM": 11201,
   "anio": 2025,
   "mes": 3,
   "casos": 5,
   "COMUNA": "Aisén"
  },
  {
   "delito": "LESIONES MENOS GRAVES",
   "CODCOM": 11201,
   "anio": 2025,
   "mes": 4,
   "casos": 1,
   "COMUNA": "Aisén"
  },
  {
   "delito": "LESIONES MENOS GRAVES",
   "CODCOM": 11201,
   "anio": 2025,
   "mes": 5,
   "casos": 2,
   "COMUNA": "Aisén"
  },
  {
   "delito": "LESIONES MENOS GRAVES",
   "CODCOM": 11201,
   "anio": 2025,
   "mes": 6,
   "casos": 1,
   "COMUNA": "Aisén"
  },
  {
   "delito": "LESIONES MENOS GRAVES",
   "CODCOM": 11201,
   "anio": 2025,
   "mes": 7,
   "casos": 1,
   "COMUNA": "Aisén"
  },
  {
   "delito": "LESIONES MENOS GRAVES",
   "CODCOM": 11201,
   "anio": 2025,
   "mes": 8,
   "casos": 3,
   "COMUNA": "Aisén"
  },
  {
   "delito": "LESIONES MENOS GRAVES",
   "CODCOM": 11201,
   "anio": 2025,
   "mes": 9,
   "casos": 2,
   "COMUNA": "Aisén"
  },
  {
   "delito": "LESIONES MENOS GRAVES",
   "CODCOM": 11201,
   "anio": 2025,
   "mes": 10,
   "casos": 3,
   "COMUNA": "Aisén"
  },
  {
   "delito": "LESIONES MENOS GRAVES",
   "CODCOM": 11201,
   "anio": 2025,
   "mes": 11,
   "casos": 3,
   "COMUNA": "Aisén"
  },
  {
   "delito": "LESIONES MENOS GRAVES",
   "CODCOM": 11201,
   "anio": 2025,
   "mes": 12,
   "casos": 2,
   "COMUNA": "Aisén"
  },
  {
   "delito": "LEY DE CONTROL DE ARMAS",
   "CODCOM": 11201,
   "anio": 2024,
   "mes": 1,
   "casos": 0,
   "COMUNA": "Aisén"
  },
  {
   "delito": "LEY DE CONTROL DE ARMAS",
   "CODCOM": 11201,
   "anio": 2024,
   "mes": 2,
   "casos": 1,
   "COMUNA": "Aisén"
  },
  {
   "delito": "LEY DE CONTROL DE ARMAS",
   "CODCOM": 11201,
   "anio": 2024,
   "mes": 3,
   "casos": 1,
   "COMUNA": "Aisén"
  },
  {
   "delito": "LEY DE CONTROL DE ARMAS",
   "CODCOM": 11201,
   "anio": 2024,
   "mes": 4,
   "casos": 3,
   "COMUNA": "Aisén"
  },
  {
   "delito": "LEY DE CONTROL DE ARMAS",
   "CODCOM": 11201,
   "anio": 2024,
   "mes": 5,
   "casos": 0,
   "COMUNA": "Aisén"
  },
  {
   "delito": "LEY DE CONTROL DE ARMAS",
   "CODCOM": 11201,
   "anio": 2024,
   "mes": 6,
   "casos": 2,
   "COMUNA": "Aisén"
  },
  {
   "delito": "LEY DE CONTROL DE ARMAS",
   "CODCOM": 11201,
   "anio": 2024,
   "mes": 7,
   "casos": 4,
   "COMUNA": "Aisén"
  },
  {
   "delito": "LEY DE CONTROL DE ARMAS",
   "CODCOM": 11201,
   "anio": 2024,
   "mes": 8,
   "casos": 1,
   "COMUNA": "Aisén"
  },
  {
   "delito": "LEY DE CONTROL DE ARMAS",
   "CODCOM": 11201,
   "anio": 2024,
   "mes": 9,
   "casos": 3,
   "COMUNA": "Aisén"
  },
  {
   "delito": "LEY DE CONTROL DE ARMAS",
   "CODCOM": 11201,
   "anio": 2024,
   "mes": 10,
   "casos": 1,
   "COMUNA": "Aisén"
  },
  {
   "delito": "LEY DE CONTROL DE ARMAS",
   "CODCOM": 11201,
   "anio": 2024,
   "mes": 11,
   "casos": 1,
   "COMUNA": "Aisén"
  },
  {
   "delito": "LEY DE CONTROL DE ARMAS",
   "CODCOM": 11201,
   "anio": 2024,
   "mes": 12,
   "casos": 3,
   "COMUNA": "Aisén"
  },
  {
   "delito": "LEY DE CONTROL DE ARMAS",
   "CODCOM": 11201,
   "anio": 2025,
   "mes": 1,
   "casos": 2,
   "COMUNA": "Aisén"
  },
  {
   "delito": "LEY DE CONTROL DE ARMAS",
   "CODCOM": 11201,
   "anio": 2025,
   "mes": 2,
   "casos": 4,
   "COMUNA": "Aisén"
  },
  {
   "delito": "LEY DE CONTROL DE ARMAS",
   "CODCOM": 11201,
   "anio": 2025,
   "mes": 3,
   "casos": 3,
   "COMUNA": "Aisén"
  },
  {
   "delito": "LEY DE CONTROL DE ARMAS",
   "CODCOM": 11201,
   "anio": 2025,
   "mes": 4,
   "casos": 3,
   "COMUNA": "Aisén"
  },
  {
   "delito": "LEY DE CONTROL DE ARMAS",
   "CODCOM": 11201,
   "anio": 2025,
   "mes": 5,
   "casos": 2,
   "COMUNA": "Aisén"
  },
  {
   "delito": "LEY DE CONTROL DE ARMAS",
   "CODCOM": 11201,
   "anio": 2025,
   "mes": 6,
   "casos": 2,
   "COMUNA": "Aisén"
  },
  {
   "delito": "LEY DE CONTROL DE ARMAS",
   "CODCOM": 11201,
   "anio": 2025,
   "mes": 7,
   "casos": 1,
   "COMUNA": "Aisén"
  },
  {
   "delito": "LEY DE CONTROL DE ARMAS",
   "CODCOM": 11201,
   "anio": 2025,
   "mes": 8,
   "casos": 3,
   "COMUNA": "Aisén"
  },
  {
   "delito": "LEY DE CONTROL DE ARMAS",
   "CODCOM": 11201,
   "anio": 2025,
   "mes": 9,
   "casos": 2,
   "COMUNA": "Aisén"
  },
  {
   "delito": "LEY DE CONTROL DE ARMAS",
   "CODCOM": 11201,
   "anio": 2025,
   "mes": 10,
   "casos": 2,
   "COMUNA": "Aisén"
  },
  {
   "delito": "LEY DE CONTROL DE ARMAS",
   "CODCOM": 11201,
   "anio": 2025,
   "mes": 11,
   "casos": 1,
   "COMUNA": "Aisén"
  },
  {
   "delito": "LEY DE CONTROL DE ARMAS",
   "CODCOM": 11201,
   "anio": 2025,
   "mes": 12,
   "casos": 2,
   "COMUNA": "Aisén"
  },
  {
   "delito": "LEY DE DROGAS",
   "CODCOM": 11201,
   "anio": 2024,
   "mes": 1,
   "casos": 1,
   "COMUNA": "Aisén"
  },
  {
   "delito": "LEY DE DROGAS",
   "CODCOM": 11201,
   "anio": 2024,
   "mes": 2,
   "casos": 2,
   "COMUNA": "Aisén"
  },
  {
   "delito": "LEY DE DROGAS",
   "CODCOM": 11201,
   "anio": 2024,
   "mes": 3,
   "casos": 2,
   "COMUNA": "Aisén"
  },
  {
   "delito": "LEY DE DROGAS",
   "CODCOM": 11201,
   "anio": 2024,
   "mes": 4,
   "casos": 1,
   "COMUNA": "Aisén"
  },
  {
   "delito": "LEY DE DROGAS",
   "CODCOM": 11201,
   "anio": 2024,
   "mes": 5,
   "casos": 1,
   "COMUNA": "Aisén"
  },
  {
   "delito": "LEY DE DROGAS",
   "CODCOM": 11201,
   "anio": 2024,
   "mes": 6,
   "casos": 0,
   "COMUNA": "Aisén"
  },
  {
   "delito": "LEY DE DROGAS",
   "CODCOM": 11201,
   "anio": 2024,
   "mes": 7,
   "casos": 0,
   "COMUNA": "Aisén"
  },
  {
   "delito": "LEY DE DROGAS",
   "CODCOM": 11201,
   "anio": 2024,
   "mes": 8,
   "casos": 2,
   "COMUNA": "Aisén"
  },
  {
   "delito": "LEY DE DROGAS",
   "CODCOM": 11201,
   "anio": 2024,
   "mes": 9,
   "casos": 3,
   "COMUNA": "Aisén"
  },
  {
   "delito": "LEY DE DROGAS",
   "CODCOM": 11201,
   "anio": 2024,
   "mes": 10,
   "casos": 0,
   "COMUNA": "Aisén"
  },
  {
   "delito": "LEY DE DROGAS",
   "CODCOM": 11201,
   "anio": 2024,
   "mes": 11,
   "casos": 1,
   "COMUNA": "Aisén"
  },
  {
   "delito": "LEY DE DROGAS",
   "CODCOM": 11201,
   "anio": 2024,
   "mes": 12,
   "casos": 0,
   "COMUNA": "Aisén"
  },
  {
   "delito": "LEY DE DROGAS",
   "CODCOM": 11201,
   "anio": 2025,
   "mes": 1,
   "casos": 0,
   "COMUNA": "Aisén"
  },
  {
   "delito": "LEY DE DROGAS",
   "CODCOM": 11201,
   "anio": 2025,
   "mes": 2,
   "casos": 1,
   "COMUNA": "Aisén"
  },
  {
   "delito": "LEY DE DROGAS",
   "CODCOM": 11201,
   "anio": 2025,
   "mes": 3,
   "casos": 7,
   "COMUNA": "Aisén"
  },
  {
   "delito": "LEY DE DROGAS",
   "CODCOM": 11201,
   "anio": 2025,
   "mes": 4,
   "casos": 3,
   "COMUNA": "Aisén"
  },
  {
   "delito": "LEY DE DROGAS",
   "CODCOM": 11201,
   "anio": 2025,
   "mes": 5,
   "casos": 2,
   "COMUNA": "Aisén"
  },
  {
   "delito": "LEY DE DROGAS",
   "CODCOM": 11201,
   "anio": 2025,
   "mes": 6,
   "casos": 6,
   "COMUNA": "Aisén"
  },
  {
   "delito": "LEY DE DROGAS",
   "CODCOM": 11201,
   "anio": 2025,
   "mes": 7,
   "casos": 1,
   "COMUNA": "Aisén"
  },
  {
   "delito": "LEY DE DROGAS",
   "CODCOM": 11201,
   "anio": 2025,
   "mes": 8,
   "casos": 2,
   "COMUNA": "Aisén"
  },
  {
   "delito": "LEY DE DROGAS",
   "CODCOM": 11201,
   "anio": 2025,
   "mes": 9,
   "casos": 1,
   "COMUNA": "Aisén"
  },
  {
   "delito": "LEY DE DROGAS",
   "CODCOM": 11201,
   "anio": 2025,
   "mes": 10,
   "casos": 1,
   "COMUNA": "Aisén"
  },
  {
   "delito": "LEY DE DROGAS",
   "CODCOM": 11201,
   "anio": 2025,
   "mes": 11,
   "casos": 1,
   "COMUNA": "Aisén"
  },
  {
   "delito": "LEY DE DROGAS",
   "CODCOM": 11201,
   "anio": 2025,
   "mes": 12,
   "casos": 2,
   "COMUNA": "Aisén"
  },
  {
   "delito": "OTROS DESÓRDENES PÚBLICOS",
   "CODCOM": 11201,
   "anio": 2024,
   "mes": 1,
   "casos": 0,
   "COMUNA": "Aisén"
  },
  {
   "delito": "OTROS DESÓRDENES PÚBLICOS",
   "CODCOM": 11201,
   "anio": 2024,
   "mes": 2,
   "casos": 0,
   "COMUNA": "Aisén"
  },
  {
   "delito": "OTROS DESÓRDENES PÚBLICOS",
   "CODCOM": 11201,
   "anio": 2024,
   "mes": 3,
   "casos": 0,
   "COMUNA": "Aisén"
  },
  {
   "delito": "OTROS DESÓRDENES PÚBLICOS",
   "CODCOM": 11201,
   "anio": 2024,
   "mes": 4,
   "casos": 2,
   "COMUNA": "Aisén"
  },
  {
   "delito": "OTROS DESÓRDENES PÚBLICOS",
   "CODCOM": 11201,
   "anio": 2024,
   "mes": 5,
   "casos": 0,
   "COMUNA": "Aisén"
  },
  {
   "delito": "OTROS DESÓRDENES PÚBLICOS",
   "CODCOM": 11201,
   "anio": 2024,
   "mes": 6,
   "casos": 0,
   "COMUNA": "Aisén"
  },
  {
   "delito": "OTROS DESÓRDENES PÚBLICOS",
   "CODCOM": 11201,
   "anio": 2024,
   "mes": 7,
   "casos": 1,
   "COMUNA": "Aisén"
  },
  {
   "delito": "OTROS DESÓRDENES PÚBLICOS",
   "CODCOM": 11201,
   "anio": 2024,
   "mes": 8,
   "casos": 0,
   "COMUNA": "Aisén"
  },
  {
   "delito": "OTROS DESÓRDENES PÚBLICOS",
   "CODCOM": 11201,
   "anio": 2024,
   "mes": 9,
   "casos": 0,
   "COMUNA": "Aisén"
  },
  {
   "delito": "OTROS DESÓRDENES PÚBLICOS",
   "CODCOM": 11201,
   "anio": 2024,
   "mes": 10,
   "casos": 1,
   "COMUNA": "Aisén"
  },
  {
   "delito": "OTROS DESÓRDENES PÚBLICOS",
   "CODCOM": 11201,
   "anio": 2024,
   "mes": 11,
   "casos": 0,
   "COMUNA": "Aisén"
  },
  {
   "delito": "OTROS DESÓRDENES PÚBLICOS",
   "CODCOM": 11201,
   "anio": 2024,
   "mes": 12,
   "casos": 1,
   "COMUNA": "Aisén"
  },
  {
   "delito": "OTROS DESÓRDENES PÚBLICOS",
   "CODCOM": 11201,
   "anio": 2025,
   "mes": 1,
   "casos": 0,
   "COMUNA": "Aisén"
  },
  {
   "delito": "OTROS DESÓRDENES PÚBLICOS",
   "CODCOM": 11201,
   "anio": 2025,
   "mes": 2,
   "casos": 1,
   "COMUNA": "Aisén"
  },
  {
   "delito": "OTROS DESÓRDENES PÚBLICOS",
   "CODCOM": 11201,
   "anio": 2025,
   "mes": 3,
   "casos": 0,
   "COMUNA": "Aisén"
  },
  {
   "delito": "OTROS DESÓRDENES PÚBLICOS",
   "CODCOM": 11201,
   "anio": 2025,
   "mes": 4,
   "casos": 0,
   "COMUNA": "Aisén"
  },
  {
   "delito": "OTROS DESÓRDENES PÚBLICOS",
   "CODCOM": 11201,
   "anio": 2025,
   "mes": 5,
   "casos": 0,
   "COMUNA": "Aisén"
  },
  {
   "delito": "OTROS DESÓRDENES PÚBLICOS",
   "CODCOM": 11201,
   "anio": 2025,
   "mes": 6,
   "casos": 2,
   "COMUNA": "Aisén"
  },
  {
   "delito": "OTROS DESÓRDENES PÚBLICOS",
   "CODCOM": 11201,
   "anio": 2025,
   "mes": 7,
   "casos": 0,
   "COMUNA": "Aisén"
  },
  {
   "delito": "OTROS DESÓRDENES PÚBLICOS",
   "CODCOM": 11201,
   "anio": 2025,
   "mes": 8,
   "casos": 1,
   "COMUNA": "Aisén"
  },
  {
   "delito": "OTROS DESÓRDENES PÚBLICOS",
   "CODCOM": 11201,
   "anio": 2025,
   "mes": 9,
   "casos": 0,
   "COMUNA": "Aisén"
  },
  {
   "delito": "OTROS DESÓRDENES PÚBLICOS",
   "CODCOM": 11201,
   "anio": 2025,
   "mes": 10,
   "casos": 0,
   "COMUNA": "Aisén"
  },
  {
   "delito": "OTROS DESÓRDENES PÚBLICOS",
   "CODCOM": 11201,
   "anio": 2025,
   "mes": 11,
   "casos": 0,
   "COMUNA": "Aisén"
  },
  {
   "delito": "OTROS DESÓRDENES PÚBLICOS",
   "CODCOM": 11201,
   "anio": 2025,
   "mes": 12,
   "casos": 0,
   "COMUNA": "Aisén"
  },
  {
   "delito": "OTROS ROBOS CON FUERZA EN LAS COSAS",
   "CODCOM": 11201,
   "anio": 2024,
   "mes": 1,
   "casos": 0,
   "COMUNA": "Aisén"
  },
  {
   "delito": "OTROS ROBOS CON FUERZA EN LAS COSAS",
   "CODCOM": 11201,
   "anio": 2024,
   "mes": 2,
   "casos": 0,
   "COMUNA": "Aisén"
  },
  {
   "delito": "OTROS ROBOS CON FUERZA EN LAS COSAS",
   "CODCOM": 11201,
   "anio": 2024,
   "mes": 3,
   "casos": 0,
   "COMUNA": "Aisén"
  },
  {
   "delito": "OTROS ROBOS CON FUERZA EN LAS COSAS",
   "CODCOM": 11201,
   "anio": 2024,
   "mes": 4,
   "casos": 0,
   "COMUNA": "Aisén"
  },
  {
   "delito": "OTROS ROBOS CON FUERZA EN LAS COSAS",
   "CODCOM": 11201,
   "anio": 2024,
   "mes": 5,
   "casos": 1,
   "COMUNA": "Aisén"
  },
  {
   "delito": "OTROS ROBOS CON FUERZA EN LAS COSAS",
   "CODCOM": 11201,
   "anio": 2024,
   "mes": 6,
   "casos": 0,
   "COMUNA": "Aisén"
  },
  {
   "delito": "OTROS ROBOS CON FUERZA EN LAS COSAS",
   "CODCOM": 11201,
   "anio": 2024,
   "mes": 7,
   "casos": 0,
   "COMUNA": "Aisén"
  },
  {
   "delito": "OTROS ROBOS CON FUERZA EN LAS COSAS",
   "CODCOM": 11201,
   "anio": 2024,
   "mes": 8,
   "casos": 0,
   "COMUNA": "Aisén"
  },
  {
   "delito": "OTROS ROBOS CON FUERZA EN LAS COSAS",
   "CODCOM": 11201,
   "anio": 2024,
   "mes": 9,
   "casos": 1,
   "COMUNA": "Aisén"
  },
  {
   "delito": "OTROS ROBOS CON FUERZA EN LAS COSAS",
   "CODCOM": 11201,
   "anio": 2024,
   "mes": 10,
   "casos": 0,
   "COMUNA": "Aisén"
  },
  {
   "delito": "OTROS ROBOS CON FUERZA EN LAS COSAS",
   "CODCOM": 11201,
   "anio": 2024,
   "mes": 11,
   "casos": 0,
   "COMUNA": "Aisén"
  },
  {
   "delito": "OTROS ROBOS CON FUERZA EN LAS COSAS",
   "CODCOM": 11201,
   "anio": 2024,
   "mes": 12,
   "casos": 0,
   "COMUNA": "Aisén"
  },
  {
   "delito": "OTROS ROBOS CON FUERZA EN LAS COSAS",
   "CODCOM": 11201,
   "anio": 2025,
   "mes": 1,
   "casos": 1,
   "COMUNA": "Aisén"
  },
  {
   "delito": "OTROS ROBOS CON FUERZA EN LAS COSAS",
   "CODCOM": 11201,
   "anio": 2025,
   "mes": 2,
   "casos": 2,
   "COMUNA": "Aisén"
  },
  {
   "delito": "OTROS ROBOS CON FUERZA EN LAS COSAS",
   "CODCOM": 11201,
   "anio": 2025,
   "mes": 3,
   "casos": 1,
   "COMUNA": "Aisén"
  },
  {
   "delito": "OTROS ROBOS CON FUERZA EN LAS COSAS",
   "CODCOM": 11201,
   "anio": 2025,
   "mes": 4,
   "casos": 0,
   "COMUNA": "Aisén"
  },
  {
   "delito": "OTROS ROBOS CON FUERZA EN LAS COSAS",
   "CODCOM": 11201,
   "anio": 2025,
   "mes": 5,
   "casos": 0,
   "COMUNA": "Aisén"
  },
  {
   "delito": "OTROS ROBOS CON FUERZA EN LAS COSAS",
   "CODCOM": 11201,
   "anio": 2025,
   "mes": 6,
   "casos": 2,
   "COMUNA": "Aisén"
  },
  {
   "delito": "OTROS ROBOS CON FUERZA EN LAS COSAS",
   "CODCOM": 11201,
   "anio": 2025,
   "mes": 7,
   "casos": 1,
   "COMUNA": "Aisén"
  },
  {
   "delito": "OTROS ROBOS CON FUERZA EN LAS COSAS",
   "CODCOM": 11201,
   "anio": 2025,
   "mes": 8,
   "casos": 1,
   "COMUNA": "Aisén"
  },
  {
   "delito": "OTROS ROBOS CON FUERZA EN LAS COSAS",
   "CODCOM": 11201,
   "anio": 2025,
   "mes": 9,
   "casos": 0,
   "COMUNA": "Aisén"
  },
  {
   "delito": "OTROS ROBOS CON FUERZA EN LAS COSAS",
   "CODCOM": 11201,
   "anio": 2025,
   "mes": 10,
   "casos": 1,
   "COMUNA": "Aisén"
  },
  {
   "delito": "OTROS ROBOS CON FUERZA EN LAS COSAS",
   "CODCOM": 11201,
   "anio": 2025,
   "mes": 11,
   "casos": 0,
   "COMUNA": "Aisén"
  },
  {
   "delito": "OTROS ROBOS CON FUERZA EN LAS COSAS",
   "CODCOM": 11201,
   "anio": 2025,
   "mes": 12,
   "casos": 0,
   "COMUNA": "Aisén"
  },
  {
   "delito": "RECEPTACIÓN",
   "CODCOM": 11201,
   "anio": 2024,
   "mes": 1,
   "casos": 1,
   "COMUNA": "Aisén"
  },
  {
   "delito": "RECEPTACIÓN",
   "CODCOM": 11201,
   "anio": 2024,
   "mes": 2,
   "casos": 0,
   "COMUNA": "Aisén"
  },
  {
   "delito": "RECEPTACIÓN",
   "CODCOM": 11201,
   "anio": 2024,
   "mes": 3,
   "casos": 1,
   "COMUNA": "Aisén"
  },
  {
   "delito": "RECEPTACIÓN",
   "CODCOM": 11201,
   "anio": 2024,
   "mes": 4,
   "casos": 3,
   "COMUNA": "Aisén"
  },
  {
   "delito": "RECEPTACIÓN",
   "CODCOM": 11201,
   "anio": 2024,
   "mes": 5,
   "casos": 0,
   "COMUNA": "Aisén"
  },
  {
   "delito": "RECEPTACIÓN",
   "CODCOM": 11201,
   "anio": 2024,
   "mes": 6,
   "casos": 2,
   "COMUNA": "Aisén"
  },
  {
   "delito": "RECEPTACIÓN",
   "CODCOM": 11201,
   "anio": 2024,
   "mes": 7,
   "casos": 1,
   "COMUNA": "Aisén"
  },
  {
   "delito": "RECEPTACIÓN",
   "CODCOM": 11201,
   "anio": 2024,
   "mes": 8,
   "casos": 1,
   "COMUNA": "Aisén"
  },
  {
   "delito": "RECEPTACIÓN",
   "CODCOM": 11201,
   "anio": 2024,
   "mes": 9,
   "casos": 0,
   "COMUNA": "Aisén"
  },
  {
   "delito": "RECEPTACIÓN",
   "CODCOM": 11201,
   "anio": 2024,
   "mes": 10,
   "casos": 3,
   "COMUNA": "Aisén"
  },
  {
   "delito": "RECEPTACIÓN",
   "CODCOM": 11201,
   "anio": 2024,
   "mes": 11,
   "casos": 0,
   "COMUNA": "Aisén"
  },
  {
   "delito": "RECEPTACIÓN",
   "CODCOM": 11201,
   "anio": 2024,
   "mes": 12,
   "casos": 0,
   "COMUNA": "Aisén"
  },
  {
   "delito": "RECEPTACIÓN",
   "CODCOM": 11201,
   "anio": 2025,
   "mes": 1,
   "casos": 2,
   "COMUNA": "Aisén"
  },
  {
   "delito": "RECEPTACIÓN",
   "CODCOM": 11201,
   "anio": 2025,
   "mes": 2,
   "casos": 1,
   "COMUNA": "Aisén"
  },
  {
   "delito": "RECEPTACIÓN",
   "CODCOM": 11201,
   "anio": 2025,
   "mes": 3,
   "casos": 2,
   "COMUNA": "Aisén"
  },
  {
   "delito": "RECEPTACIÓN",
   "CODCOM": 11201,
   "anio": 2025,
   "mes": 4,
   "casos": 1,
   "COMUNA": "Aisén"
  },
  {
   "delito": "RECEPTACIÓN",
   "CODCOM": 11201,
   "anio": 2025,
   "mes": 5,
   "casos": 0,
   "COMUNA": "Aisén"
  },
  {
   "delito": "RECEPTACIÓN",
   "CODCOM": 11201,
   "anio": 2025,
   "mes": 6,
   "casos": 0,
   "COMUNA": "Aisén"
  },
  {
   "delito": "RECEPTACIÓN",
   "CODCOM": 11201,
   "anio": 2025,
   "mes": 7,
   "casos": 1,
   "COMUNA": "Aisén"
  },
  {
   "delito": "RECEPTACIÓN",
   "CODCOM": 11201,
   "anio": 2025,
   "mes": 8,
   "casos": 1,
   "COMUNA": "Aisén"
  },
  {
   "delito": "RECEPTACIÓN",
   "CODCOM": 11201,
   "anio": 2025,
   "mes": 9,
   "casos": 0,
   "COMUNA": "Aisén"
  },
  {
   "delito": "RECEPTACIÓN",
   "CODCOM": 11201,
   "anio": 2025,
   "mes": 10,
   "casos": 0,
   "COMUNA": "Aisén"
  },
  {
   "delito": "RECEPTACIÓN",
   "CODCOM": 11201,
   "anio": 2025,
   "mes": 11,
   "casos": 0,
   "COMUNA": "Aisén"
  },
  {
   "delito": "RECEPTACIÓN",
   "CODCOM": 11201,
   "anio": 2025,
   "mes": 12,
   "casos": 2,
   "COMUNA": "Aisén"
  },
  {
   "delito": "ROBOS CON VIOLENCIA E INTIMIDACIÓN",
   "CODCOM": 11201,
   "anio": 2024,
   "mes": 1,
   "casos": 4,
   "COMUNA": "Aisén"
  },
  {
   "delito": "ROBOS CON VIOLENCIA E INTIMIDACIÓN",
   "CODCOM": 11201,
   "anio": 2024,
   "mes": 2,
   "casos": 2,
   "COMUNA": "Aisén"
  },
  {
   "delito": "ROBOS CON VIOLENCIA E INTIMIDACIÓN",
   "CODCOM": 11201,
   "anio": 2024,
   "mes": 3,
   "casos": 1,
   "COMUNA": "Aisén"
  },
  {
   "delito": "ROBOS CON VIOLENCIA E INTIMIDACIÓN",
   "CODCOM": 11201,
   "anio": 2024,
   "mes": 4,
   "casos": 2,
   "COMUNA": "Aisén"
  },
  {
   "delito": "ROBOS CON VIOLENCIA E INTIMIDACIÓN",
   "CODCOM": 11201,
   "anio": 2024,
   "mes": 5,
   "casos": 3,
   "COMUNA": "Aisén"
  },
  {
   "delito": "ROBOS CON VIOLENCIA E INTIMIDACIÓN",
   "CODCOM": 11201,
   "anio": 2024,
   "mes": 6,
   "casos": 1,
   "COMUNA": "Aisén"
  },
  {
   "delito": "ROBOS CON VIOLENCIA E INTIMIDACIÓN",
   "CODCOM": 11201,
   "anio": 2024,
   "mes": 7,
   "casos": 3,
   "COMUNA": "Aisén"
  },
  {
   "delito": "ROBOS CON VIOLENCIA E INTIMIDACIÓN",
   "CODCOM": 11201,
   "anio": 2024,
   "mes": 8,
   "casos": 1,
   "COMUNA": "Aisén"
  },
  {
   "delito": "ROBOS CON VIOLENCIA E INTIMIDACIÓN",
   "CODCOM": 11201,
   "anio": 2024,
   "mes": 9,
   "casos": 1,
   "COMUNA": "Aisén"
  },
  {
   "delito": "ROBOS CON VIOLENCIA E INTIMIDACIÓN",
   "CODCOM": 11201,
   "anio": 2024,
   "mes": 10,
   "casos": 1,
   "COMUNA": "Aisén"
  },
  {
   "delito": "ROBOS CON VIOLENCIA E INTIMIDACIÓN",
   "CODCOM": 11201,
   "anio": 2024,
   "mes": 11,
   "casos": 3,
   "COMUNA": "Aisén"
  },
  {
   "delito": "ROBOS CON VIOLENCIA E INTIMIDACIÓN",
   "CODCOM": 11201,
   "anio": 2024,
   "mes": 12,
   "casos": 0,
   "COMUNA": "Aisén"
  },
  {
   "delito": "ROBOS CON VIOLENCIA E INTIMIDACIÓN",
   "CODCOM": 11201,
   "anio": 2025,
   "mes": 1,
   "casos": 4,
   "COMUNA": "Aisén"
  },
  {
   "delito": "ROBOS CON VIOLENCIA E INTIMIDACIÓN",
   "CODCOM": 11201,
   "anio": 2025,
   "mes": 2,
   "casos": 0,
   "COMUNA": "Aisén"
  },
  {
   "delito": "ROBOS CON VIOLENCIA E INTIMIDACIÓN",
   "CODCOM": 11201,
   "anio": 2025,
   "mes": 3,
   "casos": 1,
   "COMUNA": "Aisén"
  },
  {
   "delito": "ROBOS CON VIOLENCIA E INTIMIDACIÓN",
   "CODCOM": 11201,
   "anio": 2025,
   "mes": 4,
   "casos": 0,
   "COMUNA": "Aisén"
  },
  {
   "delito": "ROBOS CON VIOLENCIA E INTIMIDACIÓN",
   "CODCOM": 11201,
   "anio": 2025,
   "mes": 5,
   "casos": 1,
   "COMUNA": "Aisén"
  },
  {
   "delito": "ROBOS CON VIOLENCIA E INTIMIDACIÓN",
   "CODCOM": 11201,
   "anio": 2025,
   "mes": 6,
   "casos": 2,
   "COMUNA": "Aisén"
  },
  {
   "delito": "ROBOS CON VIOLENCIA E INTIMIDACIÓN",
   "CODCOM": 11201,
   "anio": 2025,
   "mes": 7,
   "casos": 2,
   "COMUNA": "Aisén"
  },
  {
   "delito": "ROBOS CON VIOLENCIA E INTIMIDACIÓN",
   "CODCOM": 11201,
   "anio": 2025,
   "mes": 8,
   "casos": 5,
   "COMUNA": "Aisén"
  },
  {
   "delito": "ROBOS CON VIOLENCIA E INTIMIDACIÓN",
   "CODCOM": 11201,
   "anio": 2025,
   "mes": 9,
   "casos": 1,
   "COMUNA": "Aisén"
  },
  {
   "delito": "ROBOS CON VIOLENCIA E INTIMIDACIÓN",
   "CODCOM": 11201,
   "anio": 2025,
   "mes": 10,
   "casos": 1,
   "COMUNA": "Aisén"
  },
  {
   "delito": "ROBOS CON VIOLENCIA E INTIMIDACIÓN",
   "CODCOM": 11201,
   "anio": 2025,
   "mes": 11,
   "casos": 1,
   "COMUNA": "Aisén"
  },
  {
   "delito": "ROBOS CON VIOLENCIA E INTIMIDACIÓN",
   "CODCOM": 11201,
   "anio": 2025,
   "mes": 12,
   "casos": 1,
   "COMUNA": "Aisén"
  },
  {
   "delito": "ROBOS DE VEHÍCULOS Y SUS ACCESORIOS",
   "CODCOM": 11201,
   "anio": 2024,
   "mes": 1,
   "casos": 2,
   "COMUNA": "Aisén"
  },
  {
   "delito": "ROBOS DE VEHÍCULOS Y SUS ACCESORIOS",
   "CODCOM": 11201,
   "anio": 2024,
   "mes": 2,
   "casos": 2,
   "COMUNA": "Aisén"
  },
  {
   "delito": "ROBOS DE VEHÍCULOS Y SUS ACCESORIOS",
   "CODCOM": 11201,
   "anio": 2024,
   "mes": 3,
   "casos": 0,
   "COMUNA": "Aisén"
  },
  {
   "delito": "ROBOS DE VEHÍCULOS Y SUS ACCESORIOS",
   "CODCOM": 11201,
   "anio": 2024,
   "mes": 4,
   "casos": 3,
   "COMUNA": "Aisén"
  },
  {
   "delito": "ROBOS DE VEHÍCULOS Y SUS ACCESORIOS",
   "CODCOM": 11201,
   "anio": 2024,
   "mes": 5,
   "casos": 2,
   "COMUNA": "Aisén"
  },
  {
   "delito": "ROBOS DE VEHÍCULOS Y SUS ACCESORIOS",
   "CODCOM": 11201,
   "anio": 2024,
   "mes": 6,
   "casos": 1,
   "COMUNA": "Aisén"
  },
  {
   "delito": "ROBOS DE VEHÍCULOS Y SUS ACCESORIOS",
   "CODCOM": 11201,
   "anio": 2024,
   "mes": 7,
   "casos": 3,
   "COMUNA": "Aisén"
  },
  {
   "delito": "ROBOS DE VEHÍCULOS Y SUS ACCESORIOS",
   "CODCOM": 11201,
   "anio": 2024,
   "mes": 8,
   "casos": 0,
   "COMUNA": "Aisén"
  },
  {
   "delito": "ROBOS DE VEHÍCULOS Y SUS ACCESORIOS",
   "CODCOM": 11201,
   "anio": 2024,
   "mes": 9,
   "casos": 1,
   "COMUNA": "Aisén"
  },
  {
   "delito": "ROBOS DE VEHÍCULOS Y SUS ACCESORIOS",
   "CODCOM": 11201,
   "anio": 2024,
   "mes": 10,
   "casos": 0,
   "COMUNA": "Aisén"
  },
  {
   "delito": "ROBOS DE VEHÍCULOS Y SUS ACCESORIOS",
   "CODCOM": 11201,
   "anio": 2024,
   "mes": 11,
   "casos": 2,
   "COMUNA": "Aisén"
  },
  {
   "delito": "ROBOS DE VEHÍCULOS Y SUS ACCESORIOS",
   "CODCOM": 11201,
   "anio": 2024,
   "mes": 12,
   "casos": 4,
   "COMUNA": "Aisén"
  },
  {
   "delito": "ROBOS DE VEHÍCULOS Y SUS ACCESORIOS",
   "CODCOM": 11201,
   "anio": 2025,
   "mes": 1,
   "casos": 3,
   "COMUNA": "Aisén"
  },
  {
   "delito": "ROBOS DE VEHÍCULOS Y SUS ACCESORIOS",
   "CODCOM": 11201,
   "anio": 2025,
   "mes": 2,
   "casos": 8,
   "COMUNA": "Aisén"
  },
  {
   "delito": "ROBOS DE VEHÍCULOS Y SUS ACCESORIOS",
   "CODCOM": 11201,
   "anio": 2025,
   "mes": 3,
   "casos": 1,
   "COMUNA": "Aisén"
  },
  {
   "delito": "ROBOS DE VEHÍCULOS Y SUS ACCESORIOS",
   "CODCOM": 11201,
   "anio": 2025,
   "mes": 4,
   "casos": 0,
   "COMUNA": "Aisén"
  },
  {
   "delito": "ROBOS DE VEHÍCULOS Y SUS ACCESORIOS",
   "CODCOM": 11201,
   "anio": 2025,
   "mes": 5,
   "casos": 1,
   "COMUNA": "Aisén"
  },
  {
   "delito": "ROBOS DE VEHÍCULOS Y SUS ACCESORIOS",
   "CODCOM": 11201,
   "anio": 2025,
   "mes": 6,
   "casos": 2,
   "COMUNA": "Aisén"
  },
  {
   "delito": "ROBOS DE VEHÍCULOS Y SUS ACCESORIOS",
   "CODCOM": 11201,
   "anio": 2025,
   "mes": 7,
   "casos": 0,
   "COMUNA": "Aisén"
  },
  {
   "delito": "ROBOS DE VEHÍCULOS Y SUS ACCESORIOS",
   "CODCOM": 11201,
   "anio": 2025,
   "mes": 8,
   "casos": 0,
   "COMUNA": "Aisén"
  },
  {
   "delito": "ROBOS DE VEHÍCULOS Y SUS ACCESORIOS",
   "CODCOM": 11201,
   "anio": 2025,
   "mes": 9,
   "casos": 3,
   "COMUNA": "Aisén"
  },
  {
   "delito": "ROBOS DE VEHÍCULOS Y SUS ACCESORIOS",
   "CODCOM": 11201,
   "anio": 2025,
   "mes": 10,
   "casos": 4,
   "COMUNA": "Aisén"
  },
  {
   "delito": "ROBOS DE VEHÍCULOS Y SUS ACCESORIOS",
   "CODCOM": 11201,
   "anio": 2025,
   "mes": 11,
   "casos": 0,
   "COMUNA": "Aisén"
  },
  {
   "delito": "ROBOS DE VEHÍCULOS Y SUS ACCESORIOS",
   "CODCOM": 11201,
   "anio": 2025,
   "mes": 12,
   "casos": 1,
   "COMUNA": "Aisén"
  },
  {
   "delito": "ROBOS EN LUGARES HABITADOS Y NO HABITADOS",
   "CODCOM": 11201,
   "anio": 2024,
   "mes": 1,
   "casos": 4,
   "COMUNA": "Aisén"
  },
  {
   "delito": "ROBOS EN LUGARES HABITADOS Y NO HABITADOS",
   "CODCOM": 11201,
   "anio": 2024,
   "mes": 2,
   "casos": 7,
   "COMUNA": "Aisén"
  },
  {
   "delito": "ROBOS EN LUGARES HABITADOS Y NO HABITADOS",
   "CODCOM": 11201,
   "anio": 2024,
   "mes": 3,
   "casos": 2,
   "COMUNA": "Aisén"
  },
  {
   "delito": "ROBOS EN LUGARES HABITADOS Y NO HABITADOS",
   "CODCOM": 11201,
   "anio": 2024,
   "mes": 4,
   "casos": 8,
   "COMUNA": "Aisén"
  },
  {
   "delito": "ROBOS EN LUGARES HABITADOS Y NO HABITADOS",
   "CODCOM": 11201,
   "anio": 2024,
   "mes": 5,
   "casos": 13,
   "COMUNA": "Aisén"
  },
  {
   "delito": "ROBOS EN LUGARES HABITADOS Y NO HABITADOS",
   "CODCOM": 11201,
   "anio": 2024,
   "mes": 6,
   "casos": 10,
   "COMUNA": "Aisén"
  },
  {
   "delito": "ROBOS EN LUGARES HABITADOS Y NO HABITADOS",
   "CODCOM": 11201,
   "anio": 2024,
   "mes": 7,
   "casos": 7,
   "COMUNA": "Aisén"
  },
  {
   "delito": "ROBOS EN LUGARES HABITADOS Y NO HABITADOS",
   "CODCOM": 11201,
   "anio": 2024,
   "mes": 8,
   "casos": 13,
   "COMUNA": "Aisén"
  },
  {
   "delito": "ROBOS EN LUGARES HABITADOS Y NO HABITADOS",
   "CODCOM": 11201,
   "anio": 2024,
   "mes": 9,
   "casos": 9,
   "COMUNA": "Aisén"
  },
  {
   "delito": "ROBOS EN LUGARES HABITADOS Y NO HABITADOS",
   "CODCOM": 11201,
   "anio": 2024,
   "mes": 10,
   "casos": 4,
   "COMUNA": "Aisén"
  },
  {
   "delito": "ROBOS EN LUGARES HABITADOS Y NO HABITADOS",
   "CODCOM": 11201,
   "anio": 2024,
   "mes": 11,
   "casos": 8,
   "COMUNA": "Aisén"
  },
  {
   "delito": "ROBOS EN LUGARES HABITADOS Y NO HABITADOS",
   "CODCOM": 11201,
   "anio": 2024,
   "mes": 12,
   "casos": 7,
   "COMUNA": "Aisén"
  },
  {
   "delito": "ROBOS EN LUGARES HABITADOS Y NO HABITADOS",
   "CODCOM": 11201,
   "anio": 2025,
   "mes": 1,
   "casos": 11,
   "COMUNA": "Aisén"
  },
  {
   "delito": "ROBOS EN LUGARES HABITADOS Y NO HABITADOS",
   "CODCOM": 11201,
   "anio": 2025,
   "mes": 2,
   "casos": 2,
   "COMUNA": "Aisén"
  },
  {
   "delito": "ROBOS EN LUGARES HABITADOS Y NO HABITADOS",
   "CODCOM": 11201,
   "anio": 2025,
   "mes": 3,
   "casos": 5,
   "COMUNA": "Aisén"
  },
  {
   "delito": "ROBOS EN LUGARES HABITADOS Y NO HABITADOS",
   "CODCOM": 11201,
   "anio": 2025,
   "mes": 4,
   "casos": 8,
   "COMUNA": "Aisén"
  },
  {
   "delito": "ROBOS EN LUGARES HABITADOS Y NO HABITADOS",
   "CODCOM": 11201,
   "anio": 2025,
   "mes": 5,
   "casos": 5,
   "COMUNA": "Aisén"
  },
  {
   "delito": "ROBOS EN LUGARES HABITADOS Y NO HABITADOS",
   "CODCOM": 11201,
   "anio": 2025,
   "mes": 6,
   "casos": 4,
   "COMUNA": "Aisén"
  },
  {
   "delito": "ROBOS EN LUGARES HABITADOS Y NO HABITADOS",
   "CODCOM": 11201,
   "anio": 2025,
   "mes": 7,
   "casos": 8,
   "COMUNA": "Aisén"
  },
  {
   "delito": "ROBOS EN LUGARES HABITADOS Y NO HABITADOS",
   "CODCOM": 11201,
   "anio": 2025,
   "mes": 8,
   "casos": 3,
   "COMUNA": "Aisén"
  },
  {
   "delito": "ROBOS EN LUGARES HABITADOS Y NO HABITADOS",
   "CODCOM": 11201,
   "anio": 2025,
   "mes": 9,
   "casos": 3,
   "COMUNA": "Aisén"
  },
  {
   "delito": "ROBOS EN LUGARES HABITADOS Y NO HABITADOS",
   "CODCOM": 11201,
   "anio": 2025,
   "mes": 10,
   "casos": 5,
   "COMUNA": "Aisén"
  },
  {
   "delito": "ROBOS EN LUGARES HABITADOS Y NO HABITADOS",
   "CODCOM": 11201,
   "anio": 2025,
   "mes": 11,
   "casos": 2,
   "COMUNA": "Aisén"
  },
  {
   "delito": "ROBOS EN LUGARES HABITADOS Y NO HABITADOS",
   "CODCOM": 11201,
   "anio": 2025,
   "mes": 12,
   "casos": 2,
   "COMUNA": "Aisén"
  },
  {
   "delito": "ROBOS POR SORPRESA",
   "CODCOM": 11201,
   "anio": 2024,
   "mes": 1,
   "casos": 0,
   "COMUNA": "Aisén"
  },
  {
   "delito": "ROBOS POR SORPRESA",
   "CODCOM": 11201,
   "anio": 2024,
   "mes": 2,
   "casos": 1,
   "COMUNA": "Aisén"
  },
  {
   "delito": "ROBOS POR SORPRESA",
   "CODCOM": 11201,
   "anio": 2024,
   "mes": 3,
   "casos": 0,
   "COMUNA": "Aisén"
  },
  {
   "delito": "ROBOS POR SORPRESA",
   "CODCOM": 11201,
   "anio": 2024,
   "mes": 4,
   "casos": 0,
   "COMUNA": "Aisén"
  },
  {
   "delito": "ROBOS POR SORPRESA",
   "CODCOM": 11201,
   "anio": 2024,
   "mes": 5,
   "casos": 0,
   "COMUNA": "Aisén"
  },
  {
   "delito": "ROBOS POR SORPRESA",
   "CODCOM": 11201,
   "anio": 2024,
   "mes": 6,
   "casos": 0,
   "COMUNA": "Aisén"
  },
  {
   "delito": "ROBOS POR SORPRESA",
   "CODCOM": 11201,
   "anio": 2024,
   "mes": 7,
   "casos": 0,
   "COMUNA": "Aisén"
  },
  {
   "delito": "ROBOS POR SORPRESA",
   "CODCOM": 11201,
   "anio": 2024,
   "mes": 8,
   "casos": 1,
   "COMUNA": "Aisén"
  },
  {
   "delito": "ROBOS POR SORPRESA",
   "CODCOM": 11201,
   "anio": 2024,
   "mes": 9,
   "casos": 0,
   "COMUNA": "Aisén"
  },
  {
   "delito": "ROBOS POR SORPRESA",
   "CODCOM": 11201,
   "anio": 2024,
   "mes": 10,
   "casos": 0,
   "COMUNA": "Aisén"
  },
  {
   "delito": "ROBOS POR SORPRESA",
   "CODCOM": 11201,
   "anio": 2024,
   "mes": 11,
   "casos": 0,
   "COMUNA": "Aisén"
  },
  {
   "delito": "ROBOS POR SORPRESA",
   "CODCOM": 11201,
   "anio": 2024,
   "mes": 12,
   "casos": 0,
   "COMUNA": "Aisén"
  },
  {
   "delito": "ROBOS POR SORPRESA",
   "CODCOM": 11201,
   "anio": 2025,
   "mes": 1,
   "casos": 3,
   "COMUNA": "Aisén"
  },
  {
   "delito": "ROBOS POR SORPRESA",
   "CODCOM": 11201,
   "anio": 2025,
   "mes": 2,
   "casos": 0,
   "COMUNA": "Aisén"
  },
  {
   "delito": "ROBOS POR SORPRESA",
   "CODCOM": 11201,
   "anio": 2025,
   "mes": 3,
   "casos": 0,
   "COMUNA": "Aisén"
  },
  {
   "delito": "ROBOS POR SORPRESA",
   "CODCOM": 11201,
   "anio": 2025,
   "mes": 4,
   "casos": 1,
   "COMUNA": "Aisén"
  },
  {
   "delito": "ROBOS POR SORPRESA",
   "CODCOM": 11201,
   "anio": 2025,
   "mes": 5,
   "casos": 1,
   "COMUNA": "Aisén"
  },
  {
   "delito": "ROBOS POR SORPRESA",
   "CODCOM": 11201,
   "anio": 2025,
   "mes": 6,
   "casos": 0,
   "COMUNA": "Aisén"
  },
  {
   "delito": "ROBOS POR SORPRESA",
   "CODCOM": 11201,
   "anio": 2025,
   "mes": 7,
   "casos": 0,
   "COMUNA": "Aisén"
  },
  {
   "delito": "ROBOS POR SORPRESA",
   "CODCOM": 11201,
   "anio": 2025,
   "mes": 8,
   "casos": 0,
   "COMUNA": "Aisén"
  },
  {
   "delito": "ROBOS POR SORPRESA",
   "CODCOM": 11201,
   "anio": 2025,
   "mes": 9,
   "casos": 0,
   "COMUNA": "Aisén"
  },
  {
   "delito": "ROBOS POR SORPRESA",
   "CODCOM": 11201,
   "anio": 2025,
   "mes": 10,
   "casos": 0,
   "COMUNA": "Aisén"
  },
  {
   "delito": "ROBOS POR SORPRESA",
   "CODCOM": 11201,
   "anio": 2025,
   "mes": 11,
   "casos": 0,
   "COMUNA": "Aisén"
  },
  {
   "delito": "ROBOS POR SORPRESA",
   "CODCOM": 11201,
   "anio": 2025,
   "mes": 12,
   "casos": 0,
   "COMUNA": "Aisén"
  },
  {
   "delito": "VIOLACIONES Y DELITOS SEXUALES",
   "CODCOM": 11201,
   "anio": 2024,
   "mes": 1,
   "casos": 0,
   "COMUNA": "Aisén"
  },
  {
   "delito": "VIOLACIONES Y DELITOS SEXUALES",
   "CODCOM": 11201,
   "anio": 2024,
   "mes": 2,
   "casos": 0,
   "COMUNA": "Aisén"
  },
  {
   "delito": "VIOLACIONES Y DELITOS SEXUALES",
   "CODCOM": 11201,
   "anio": 2024,
   "mes": 3,
   "casos": 2,
   "COMUNA": "Aisén"
  },
  {
   "delito": "VIOLACIONES Y DELITOS SEXUALES",
   "CODCOM": 11201,
   "anio": 2024,
   "mes": 4,
   "casos": 2,
   "COMUNA": "Aisén"
  },
  {
   "delito": "VIOLACIONES Y DELITOS SEXUALES",
   "CODCOM": 11201,
   "anio": 2024,
   "mes": 5,
   "casos": 3,
   "COMUNA": "Aisén"
  },
  {
   "delito": "VIOLACIONES Y DELITOS SEXUALES",
   "CODCOM": 11201,
   "anio": 2024,
   "mes": 6,
   "casos": 2,
   "COMUNA": "Aisén"
  },
  {
   "delito": "VIOLACIONES Y DELITOS SEXUALES",
   "CODCOM": 11201,
   "anio": 2024,
   "mes": 7,
   "casos": 4,
   "COMUNA": "Aisén"
  },
  {
   "delito": "VIOLACIONES Y DELITOS SEXUALES",
   "CODCOM": 11201,
   "anio": 2024,
   "mes": 8,
   "casos": 2,
   "COMUNA": "Aisén"
  },
  {
   "delito": "VIOLACIONES Y DELITOS SEXUALES",
   "CODCOM": 11201,
   "anio": 2024,
   "mes": 9,
   "casos": 2,
   "COMUNA": "Aisén"
  },
  {
   "delito": "VIOLACIONES Y DELITOS SEXUALES",
   "CODCOM": 11201,
   "anio": 2024,
   "mes": 10,
   "casos": 1,
   "COMUNA": "Aisén"
  },
  {
   "delito": "VIOLACIONES Y DELITOS SEXUALES",
   "CODCOM": 11201,
   "anio": 2024,
   "mes": 11,
   "casos": 1,
   "COMUNA": "Aisén"
  },
  {
   "delito": "VIOLACIONES Y DELITOS SEXUALES",
   "CODCOM": 11201,
   "anio": 2024,
   "mes": 12,
   "casos": 0,
   "COMUNA": "Aisén"
  },
  {
   "delito": "VIOLACIONES Y DELITOS SEXUALES",
   "CODCOM": 11201,
   "anio": 2025,
   "mes": 1,
   "casos": 3,
   "COMUNA": "Aisén"
  },
  {
   "delito": "VIOLACIONES Y DELITOS SEXUALES",
   "CODCOM": 11201,
   "anio": 2025,
   "mes": 2,
   "casos": 2,
   "COMUNA": "Aisén"
  },
  {
   "delito": "VIOLACIONES Y DELITOS SEXUALES",
   "CODCOM": 11201,
   "anio": 2025,
   "mes": 3,
   "casos": 1,
   "COMUNA": "Aisén"
  },
  {
   "delito": "VIOLACIONES Y DELITOS SEXUALES",
   "CODCOM": 11201,
   "anio": 2025,
   "mes": 4,
   "casos": 1,
   "COMUNA": "Aisén"
  },
  {
   "delito": "VIOLACIONES Y DELITOS SEXUALES",
   "CODCOM": 11201,
   "anio": 2025,
   "mes": 5,
   "casos": 0,
   "COMUNA": "Aisén"
  },
  {
   "delito": "VIOLACIONES Y DELITOS SEXUALES",
   "CODCOM": 11201,
   "anio": 2025,
   "mes": 6,
   "casos": 2,
   "COMUNA": "Aisén"
  },
  {
   "delito": "VIOLACIONES Y DELITOS SEXUALES",
   "CODCOM": 11201,
   "anio": 2025,
   "mes": 7,
   "casos": 0,
   "COMUNA": "Aisén"
  },
  {
   "delito": "VIOLACIONES Y DELITOS SEXUALES",
   "CODCOM": 11201,
   "anio": 2025,
   "mes": 8,
   "casos": 3,
   "COMUNA": "Aisén"
  },
  {
   "delito": "VIOLACIONES Y DELITOS SEXUALES",
   "CODCOM": 11201,
   "anio": 2025,
   "mes": 9,
   "casos": 5,
   "COMUNA": "Aisén"
  },
  {
   "delito": "VIOLACIONES Y DELITOS SEXUALES",
   "CODCOM": 11201,
   "anio": 2025,
   "mes": 10,
   "casos": 1,
   "COMUNA": "Aisén"
  },
  {
   "delito": "VIOLACIONES Y DELITOS SEXUALES",
   "CODCOM": 11201,
   "anio": 2025,
   "mes": 11,
   "casos": 1,
   "COMUNA": "Aisén"
  },
  {
   "delito": "VIOLACIONES Y DELITOS SEXUALES",
   "CODCOM": 11201,
   "anio": 2025,
   "mes": 12,
   "casos": 1,
   "COMUNA": "Aisén"
  }
 ],
 "info": [
  {
   "informacion": "Casos",
   "CODCOM": 11201,
   "delito": "AMENAZAS CON ARMAS",
   "2023": 17,
   "2024": 16,
   "2025": 10,
   "COMUNA": "Aisén"
  },
  {
   "informacion": "Casos",
   "CODCOM": 11201,
   "delito": "AMENAZAS Y RIÑAS",
   "2023": 175,
   "2024": 190,
   "2025": 223,
   "COMUNA": "Aisén"
  },
  {
   "informacion": "Casos",
   "CODCOM": 11201,
   "delito": "CONSUMO DE ALCOHOL Y DE DROGAS EN LA VÍA PÚBLICA",
   "2023": 341,
   "2024": 582,
   "2025": 580,
   "COMUNA": "Aisén"
  },
  {
   "informacion": "Casos",
   "CODCOM": 11201,
   "delito": "DAÑOS",
   "2023": 233,
   "2024": 205,
   "2025": 152,
   "COMUNA": "Aisén"
  },
  {
   "informacion": "Casos",
   "CODCOM": 11201,
   "delito": "DELITOS EN CONTEXTO DE VIOLENCIA INTRAFAMILIAR",
   "2023": 321,
   "2024": 392,
   "2025": 295,
   "COMUNA": "Aisén"
  },
  {
   "informacion": "Casos",
   "CODCOM": 11201,
   "delito": "HOMICIDIOS Y FEMICIDIOS",
   "2023": 0,
   "2024": 2,
   "2025": 1,
   "COMUNA": "Aisén"
  },
  {
   "informacion": "Casos",
   "CODCOM": 11201,
   "delito": "HURTOS",
   "2023": 120,
   "2024": 137,
   "2025": 104,
   "COMUNA": "Aisén"
  },
  {
   "informacion": "Casos",
   "CODCOM": 11201,
   "delito": "INCIVILIDADES",
   "2023": 125,
   "2024": 194,
   "2025": 165,
   "COMUNA": "Aisén"
  },
  {
   "informacion": "Casos",
   "CODCOM": 11201,
   "delito": "LESIONES GRAVES",
   "2023": 17,
   "2024": 16,
   "2025": 11,
   "COMUNA": "Aisén"
  },
  {
   "informacion": "Casos",
   "CODCOM": 11201,
   "delito": "LESIONES LEVES",
   "2023": 118,
   "2024": 108,
   "2025": 100,
   "COMUNA": "Aisén"
  },
  {
   "informacion": "Casos",
   "CODCOM": 11201,
   "delito": "LESIONES MENOS GRAVES",
   "2023": 30,
   "2024": 26,
   "2025": 29,
   "COMUNA": "Aisén"
  },
  {
   "informacion": "Casos",
   "CODCOM": 11201,
   "delito": "LEY DE CONTROL DE ARMAS",
   "2023": 20,
   "2024": 18,
   "2025": 27,
   "COMUNA": "Aisén"
  },
  {
   "informacion": "Casos",
   "CODCOM": 11201,
   "delito": "LEY DE DROGAS",
   "2023": 11,
   "2024": 13,
   "2025": 27,
   "COMUNA": "Aisén"
  },
  {
   "informacion": "Casos",
   "CODCOM": 11201,
   "delito": "OTROS DESÓRDENES PÚBLICOS",
   "2023": 15,
   "2024": 5,
   "2025": 4,
   "COMUNA": "Aisén"
  },
  {
   "informacion": "Casos",
   "CODCOM": 11201,
   "delito": "OTROS ROBOS CON FUERZA EN LAS COSAS",
   "2023": 2,
   "2024": 2,
   "2025": 9,
   "COMUNA": "Aisén"
  },
  {
   "informacion": "Casos",
   "CODCOM": 11201,
   "delito": "RECEPTACIÓN",
   "2023": 12,
   "2024": 12,
   "2025": 10,
   "COMUNA": "Aisén"
  },
  {
   "informacion": "Casos",
   "CODCOM": 11201,
   "delito": "ROBOS CON VIOLENCIA E INTIMIDACIÓN",
   "2023": 18,
   "2024": 22,
   "2025": 19,
   "COMUNA": "Aisén"
  },
  {
   "informacion": "Casos",
   "CODCOM": 11201,
   "delito": "ROBOS DE VEHÍCULOS Y SUS ACCESORIOS",
   "2023": 9,
   "2024": 20,
   "2025": 23,
   "COMUNA": "Aisén"
  },
  {
   "informacion": "Casos",
   "CODCOM": 11201,
   "delito": "ROBOS EN LUGARES HABITADOS Y NO HABITADOS",
   "2023": 59,
   "2024": 89,
   "2025": 58,
   "COMUNA": "Aisén"
  },
  {
   "informacion": "Casos",
   "CODCOM": 11201,
   "delito": "ROBOS POR SORPRESA",
   "2023": 0,
   "2024": 2,
   "2025": 5,
   "COMUNA": "Aisén"
  },
  {
   "informacion": "Casos",
   "CODCOM": 11201,
   "delito": "VIOLACIONES Y DELITOS SEXUALES",
   "2023": 21,
   "2024": 19,
   "2025": 20,
   "COMUNA": "Aisén"
  }
 ],
 "meta": {
  "semana_id": "SEMANA 51/2025 (del 15/12/2025 al 21/12/2025)",
  "region": "Aysén"
 }
}