{
 "resumen": [
  {
   "delito": "AMENAZAS CON ARMAS",
   "CODCOM": 13116,
   "2024": 24,
   "2025": 16,
   "variacion": -33,
   "situación": "Disminución de Casos",
   "COMUNA": "Lo Espejo"
  },
  {
   "delito": "AMENAZAS Y RIÑAS",
   "CODCOM": 13116,
   "2024": 784,
   "2025": 828,
   "variacion": 6,
   "situación": "Aumento de Casos",
   "COMUNA": "Lo Espejo"
  },
  {
   "delito": "CONSUMO DE ALCOHOL Y DE DROGAS EN LA VÍA PÚBLICA",
   "CODCOM": 13116,
   "2024": 213,
   "2025": 116,
   "variacion": -46,
   "situación": "Disminución de Casos",
   "COMUNA": "Lo Espejo"
  },
  {
   "delito": "DAÑOS",
   "CODCOM": 13116,
   "2024": 377,
   "2025": 365,
   "variacion": -3,
   "situación": "Disminución de Casos",
   "COMUNA": "Lo Espejo"
  },
  {
   "delito": "DELITOS EN CONTEXTO DE VIOLENCIA INTRAFAMILIAR",
   "CODCOM": 13116,
   "2024": 519,
   "2025": 486,
   "variacion": -6,
   "situación": "Disminución de Casos",
   "COMUNA": "Lo Espejo"
  },
  {
   "delito": "HOMICIDIOS Y FEMICIDIOS",
   "CODCOM": 13116,
   "2024": 3,
   "2025": 10,
   "variacion": 233,
   "situación": "Aumento de Casos",
   "COMUNA": "Lo Espejo"
  },
  {
   "delito": "HURTOS",
   "CODCOM": 13116,
   "2024": 145,
   "2025": 153,
   "variacion": 6,
   "situación": "Aumento de Casos",
   "COMUNA": "Lo Espejo"
  },
  {
   "delito": "INCIVILIDADES",
   "CODCOM": 13116,
   "2024": 53,
   "2025": 48,
   "variacion": -9,
   "situación": "Disminución de Casos",
   "COMUNA": "Lo Espejo"
  },
  {
   "delito": "LESIONES GRAVES",
   "CODCOM": 13116,
   "2024": 55,
   "2025": 35,
   "variacion": -36,
   "situación": "Disminución de Casos",
   "COMUNA": "Lo Espejo"
  },
  {
   "delito": "LESIONES LEVES",
   "CODCOM": 13116,
   "2024": 267,
   "2025": 258,
   "variacion": -3,
   "situación": "Disminución de Casos",
   "COMUNA": "Lo Espejo"
  },
  {
   "delito": "LESIONES MENOS GRAVES",
   "CODCOM": 13116,
   "2024": 57,
   "2025": 55,
   "variacion": -4,
   "situación": "Disminución de Casos",
   "COMUNA": "Lo Espejo"
  },
  {
   "delito": "LEY DE CONTROL DE ARMAS",
   "CODCOM": 13116,
   "2024": 155,
   "2025": 239,
   "variacion": 54,
   "situación": "Aumento de Casos",
   "COMUNA": "Lo Espejo"
  },
  {
   "delito": "LEY DE DROGAS",
   "CODCOM": 13116,
   "2024": 53,
   "2025": 98,
   "variacion": 85,
   "situación": "Aumento de Casos",
   "COMUNA": "Lo Espejo"
  },
  {
   "delito": "OTROS DESÓRDENES PÚBLICOS",
   "CODCOM": 13116,
   "2024": 7,
   "2025": 4,
   "variacion": -43,
   "situación": "Disminución de Casos",
   "COMUNA": "Lo Espejo"
  },
  {
   "delito": "OTROS ROBOS CON FUERZA EN LAS COSAS",
   "CODCOM": 13116,
   "2024": 18,
   "2025": 34,
   "variacion": 89,
   "situación": "Aumento de Casos",
   "COMUNA": "Lo Espejo"
  },
  {
   "delito": "RECEPTACIÓN",
   "CODCOM": 13116,
   "2024": 43,
   "2025": 69,
   "variacion": 60,
   "situación": "Aumento de Casos",
   "COMUNA": "Lo Espejo"
  },
  {
   "delito": "ROBOS CON VIOLENCIA E INTIMIDACIÓN",
   "CODCOM": 13116,
   "2024": 579,
   "2025": 493,
   "variacion": -15,
   "situación": "Disminución de Casos",
   "COMUNA": "Lo Espejo"
  },
  {
   "delito": "ROBOS DE VEHÍCULOS Y SUS ACCESORIOS",
   "CODCOM": 13116,
   "2024": 256,
   "2025": 288,
   "variacion": 12,
   "situación": "Aumento de Casos",
   "COMUNA": "Lo Espejo"
  },
  {
   "delito": "ROBOS EN LUGARES HABITADOS Y NO HABITADOS",
   "CODCOM": 13116,
   "2024": 159,
   "2025": 153,
   "variacion": -4,
   "situación": "Disminución de Casos",
   "COMUNA": "Lo Espejo"
  },
  {
   "delito": "ROBOS POR SORPRESA",
   "CODCOM": 13116,
   "2024": 248,
   "2025": 199,
   "variacion": -20,
   "situación": "Disminución de Casos",
   "COMUNA": "Lo Espejo"
  },
  {
   "delito": "VIOLACIONES Y DELITOS SEXUALES",
   "CODCOM": 13116,
   "2024": 59,
   "2025": 39,
   "variacion": -34,
   "situación": "Disminución de Casos",
   "COMUNA": "Lo Espejo"
  }
 ],
 "mensual": [
  {
   "delito": "AMENAZAS CON ARMAS",
   "CODCOM": 13116,
   "anio": 2024,
   "mes": 1,
   "casos": 1,
   "COMUNA": "Lo Espejo"
  },
  {
   "delito": "AMENAZAS CON ARMAS",
   "CODCOM": 13116,
   "anio": 2024,
   "mes": 2,
   "casos": 1,
   "COMUNA": "Lo Espejo"
  },
  {
   "delito": "AMENAZAS CON ARMAS",
   "CODCOM": 13116,
   "anio": 2024,
   "mes": 3,
   "casos": 2,
   "COMUNA": "Lo Espejo"
  },
  {
   "delito": "AMENAZAS CON ARMAS",
   "CODCOM": 13116,
   "anio": 2024,
   "mes": 4,
   "casos": 3,
   "COMUNA": "Lo Espejo"
  },
  {
   "delito": "AMENAZAS CON ARMAS",
   "CODCOM": 13116,
   "anio": 2024,
   "mes": 5,
   "casos": 2,
   "COMUNA": "Lo Espejo"
  },
  {
   "delito": "AMENAZAS CON ARMAS",
   "CODCOM": 13116,
   "anio": 2024,
   "mes": 6,
   "casos": 2,
   "COMUNA": "Lo Espejo"
  },
  {
   "delito": "AMENAZAS CON ARMAS",
   "CODCOM": 13116,
   "anio": 2024,
   "mes": 7,
   "casos": 3,
   "COMUNA": "Lo Espejo"
  },
  {
   "delito": "AMENAZAS CON ARMAS",
   "CODCOM": 13116,
   "anio": 2024,
   "mes": 8,
   "casos": 3,
   "COMUNA": "Lo Espejo"
  },
  {
   "delito": "AMENAZAS CON ARMAS",
   "CODCOM": 13116,
   "anio": 2024,
   "mes": 9,
   "casos": 3,
   "COMUNA": "Lo Espejo"
  },
  {
   "delito": "AMENAZAS CON ARMAS",
   "CODCOM": 13116,
   "anio": 2024,
   "mes": 10,
   "casos": 4,
   "COMUNA": "Lo Espejo"
  },
  {
   "delito": "AMENAZAS CON ARMAS",
   "CODCOM": 13116,
   "anio": 2024,
   "mes": 11,
   "casos": 0,
   "COMUNA": "Lo Espejo"
  },
  {
   "delito": "AMENAZAS CON ARMAS",
   "CODCOM": 13116,
   "anio": 2024,
   "mes": 12,
   "casos": 0,
   "COMUNA": "Lo Espejo"
  },
  {
   "delito": "AMENAZAS CON ARMAS",
   "CODCOM": 13116,
   "anio": 2025,
   "mes": 1,
   "casos": 2,
   "COMUNA": "Lo Espejo"
  },
  {
   "delito": "AMENAZAS CON ARMAS",
   "CODCOM": 13116,
   "anio": 2025,
   "mes": 2,
   "casos": 4,
   "COMUNA": "Lo Espejo"
  },
  {
   "delito": "AMENAZAS CON ARMAS",
   "CODCOM": 13116,
   "anio": 2025,
   "mes": 3,
   "casos": 3,
   "COMUNA": "Lo Espejo"
  },
  {
   "delito": "AMENAZAS CON ARMAS",
   "CODCOM": 13116,
   "anio": 2025,
   "mes": 4,
   "casos": 0,
   "COMUNA": "Lo Espejo"
  },
  {
   "delito": "AMENAZAS CON ARMAS",
   "CODCOM": 13116,
   "anio": 2025,
   "mes": 5,
   "casos": 1,
   "COMUNA": "Lo Espejo"
  },
  {
   "delito": "AMENAZAS CON ARMAS",
   "CODCOM": 13116,
   "anio": 2025,
   "mes": 6,
   "casos": 0,
   "COMUNA": "Lo Espejo"
  },
  {
   "delito": "AMENAZAS CON ARMAS",
   "CODCOM": 13116,
   "anio": 2025,
   "mes": 7,
   "casos": 1,
   "COMUNA": "Lo Espejo"
  },
  {
   "delito": "AMENAZAS CON ARMAS",
   "CODCOM": 13116,
   "anio": 2025,
   "mes": 8,
   "casos": 2,
   "COMUNA": "Lo Espejo"
  },
  {
   "delito": "AMENAZAS CON ARMAS",
   "CODCOM": 13116,
   "anio": 2025,
   "mes": 9,
   "casos": 3,
   "COMUNA": "Lo Espejo"
  },
  {
   "delito": "AMENAZAS CON ARMAS",
   "CODCOM": 13116,
   "anio": 2025,
   "mes": 10,
   "casos": 0,
   "COMUNA": "Lo Espejo"
  },
  {
   "delito": "AMENAZAS CON ARMAS",
   "CODCOM": 13116,
   "anio": 2025,
   "mes": 11,
   "casos": 0,
   "COMUNA": "Lo Espejo"
  },
  {
   "delito": "AMENAZAS Y RIÑAS",
   "CODCOM": 13116,
   "anio": 2024,
   "mes": 1,
   "casos": 83,
   "COMUNA": "Lo Espejo"
  },
  {
   "delito": "AMENAZAS Y RIÑAS",
   "CODCOM": 13116,
   "anio": 2024,
   "mes": 2,
   "casos": 77,
   "COMUNA": "Lo Espejo"
  },
  {
   "delito": "AMENAZAS Y RIÑAS",
   "CODCOM": 13116,
   "anio": 2024,
   "mes": 3,
   "casos": 75,
   "COMUNA": "Lo Espejo"
  },
  {
   "delito": "AMENAZAS Y RIÑAS",
   "CODCOM": 13116,
   "anio": 2024,
   "mes": 4,
   "casos": 79,
   "COMUNA": "Lo Espejo"
  },
  {
   "delito": "AMENAZAS Y RIÑAS",
   "CODCOM": 13116,
   "anio": 2024,
   "mes": 5,
   "casos": 64,
   "COMUNA": "Lo Espejo"
  },
  {
   "delito": "AMENAZAS Y RIÑAS",
   "CODCOM": 13116,
   "anio": 2024,
   "mes": 6,
   "casos": 62,
   "COMUNA": "Lo Espejo"
  },
  {
   "delito": "AMENAZAS Y RIÑAS",
   "CODCOM": 13116,
   "anio": 2024,
   "mes": 7,
   "casos": 85,
   "COMUNA": "Lo Espejo"
  },
  {
   "delito": "AMENAZAS Y RIÑAS",
   "CODCOM": 13116,
   "anio": 2024,
   "mes": 8,
   "casos": 55,
   "COMUNA": "Lo Espejo"
  },
  {
   "delito": "AMENAZAS Y RIÑAS",
   "CODCOM": 13116,
   "anio": 2024,
   "mes": 9,
   "casos": 94,
   "COMUNA": "Lo Espejo"
  },
  {
   "delito": "AMENAZAS Y RIÑAS",
   "CODCOM": 13116,
   "anio": 2024,
   "mes": 10,
   "casos": 82,
   "COMUNA": "Lo Espejo"
  },
  {
   "delito": "AMENAZAS Y RIÑAS",
   "CODCOM": 13116,
   "anio": 2024,
   "mes": 11,
   "casos": 72,
   "COMUNA": "Lo Espejo"
  },
  {
   "delito": "AMENAZAS Y RIÑAS",
   "CODCOM": 13116,
   "anio": 2024,
   "mes": 12,
   "casos": 77,
   "COMUNA": "Lo Espejo"
  },
  {
   "delito": "AMENAZAS Y RIÑAS",
   "CODCOM": 13116,
   "anio": 2025,
   "mes": 1,
   "casos": 79,
   "COMUNA": "Lo Espejo"
  },
  {
   "delito": "AMENAZAS Y RIÑAS",
   "CODCOM": 13116,
   "anio": 2025,
   "mes": 2,
   "casos": 82,
   "COMUNA": "Lo Espejo"
  },
  {
   "delito": "AMENAZAS Y RIÑAS",
   "CODCOM": 13116,
   "anio": 2025,
   "mes": 3,
   "casos": 94,
   "COMUNA": "Lo Espejo"
  },
  {
   "delito": "AMENAZAS Y RIÑAS",
   "CODCOM": 13116,
   "anio": 2025,
   "mes": 4,
   "casos": 60,
   "COMUNA": "Lo Espejo"
  },
  {
   "delito": "AMENAZAS Y RIÑAS",
   "CODCOM": 13116,
   "anio": 2025,
   "mes": 5,
   "casos": 67,
   "COMUNA": "Lo Espejo"
  },
  {
   "delito": "AMENAZAS Y RIÑAS",
   "CODCOM": 13116,
   "anio": 2025,
   "mes": 6,
   "casos": 90,
   "COMUNA": "Lo Espejo"
  },
  {
   "delito": "AMENAZAS Y RIÑAS",
   "CODCOM": 13116,
   "anio": 2025,
   "mes": 7,
   "casos": 72,
   "COMUNA": "Lo Espejo"
  },
  {
   "delito": "AMENAZAS Y RIÑAS",
   "CODCOM": 13116,
   "anio": 2025,
   "mes": 8,
   "casos": 79,
   "COMUNA": "Lo Espejo"
  },
  {
   "delito": "AMENAZAS Y RIÑAS",
   "CODCOM": 13116,
   "anio": 2025,
   "mes": 9,
   "casos": 101,
   "COMUNA": "Lo Espejo"
  },
  {
   "delito": "AMENAZAS Y RIÑAS",
   "CODCOM": 13116,
   "anio": 2025,
   "mes": 10,
   "casos": 81,
   "COMUNA": "Lo Espejo"
  },
  {
   "delito": "AMENAZAS Y RIÑAS",
   "CODCOM": 13116,
   "anio": 2025,
   "mes": 11,
   "casos": 23,
   "COMUNA": "Lo Espejo"
  },
  {
   "delito": "CONSUMO DE ALCOHOL Y DE DROGAS EN LA VÍA PÚBLICA",
   "CODCOM": 13116,
   "anio": 2024,
   "mes": 1,
   "casos": 28,
   "COMUNA": "Lo Espejo"
  },
  {
   "delito": "CONSUMO DE ALCOHOL Y DE DROGAS EN LA VÍA PÚBLICA",
   "CODCOM": 13116,
   "anio": 2024,
   "mes": 2,
   "casos": 31,
   "COMUNA": "Lo Espejo"
  },
  {
   "delito": "CONSUMO DE ALCOHOL Y DE DROGAS EN LA VÍA PÚBLICA",
   "CODCOM": 13116,
   "anio": 2024,
   "mes": 3,
   "casos": 13,
   "COMUNA": "Lo Espejo"
  },
  {
   "delito": "CONSUMO DE ALCOHOL Y DE DROGAS EN LA VÍA PÚBLICA",
   "CODCOM": 13116,
   "anio": 2024,
   "mes": 4,
   "casos": 39,
   "COMUNA": "Lo Espejo"
  },
  {
   "delito": "CONSUMO DE ALCOHOL Y DE DROGAS EN LA VÍA PÚBLICA",
   "CODCOM": 13116,
   "anio": 2024,
   "mes": 5,
   "casos": 9,
   "COMUNA": "Lo Espejo"
  },
  {
   "delito": "CONSUMO DE ALCOHOL Y DE DROGAS EN LA VÍA PÚBLICA",
   "CODCOM": 13116,
   "anio": 2024,
   "mes": 6,
   "casos": 9,
   "COMUNA": "Lo Espejo"
  },
  {
   "delito": "CONSUMO DE ALCOHOL Y DE DROGAS EN LA VÍA PÚBLICA",
   "CODCOM": 13116,
   "anio": 2024,
   "mes": 7,
   "casos": 48,
   "COMUNA": "Lo Espejo"
  },
  {
   "delito": "CONSUMO DE ALCOHOL Y DE DROGAS EN LA VÍA PÚBLICA",
   "CODCOM": 13116,
   "anio": 2024,
   "mes": 8,
   "casos": 3,
   "COMUNA": "Lo Espejo"
  },
  {
   "delito": "CONSUMO DE ALCOHOL Y DE DROGAS EN LA VÍA PÚBLICA",
   "CODCOM": 13116,
   "anio": 2024,
   "mes": 9,
   "casos": 17,
   "COMUNA": "Lo Espejo"
  },
  {
   "delito": "CONSUMO DE ALCOHOL Y DE DROGAS EN LA VÍA PÚBLICA",
   "CODCOM": 13116,
   "anio": 2024,
   "mes": 10,
   "casos": 16,
   "COMUNA": "Lo Espejo"
  },
  {
   "delito": "CONSUMO DE ALCOHOL Y DE DROGAS EN LA VÍA PÚBLICA",
   "CODCOM": 13116,
   "anio": 2024,
   "mes": 11,
   "casos": 0,
   "COMUNA": "Lo Espejo"
  },
  {
   "delito": "CONSUMO DE ALCOHOL Y DE DROGAS EN LA VÍA PÚBLICA",
   "CODCOM": 13116,
   "anio": 2024,
   "mes": 12,
   "casos": 1,
   "COMUNA": "Lo Espejo"
  },
  {
   "delito": "CONSUMO DE ALCOHOL Y DE DROGAS EN LA VÍA PÚBLICA",
   "CODCOM": 13116,
   "anio": 2025,
   "mes": 1,
   "casos": 9,
   "COMUNA": "Lo Espejo"
  },
  {
   "delito": "CONSUMO DE ALCOHOL Y DE DROGAS EN LA VÍA PÚBLICA",
   "CODCOM": 13116,
   "anio": 2025,
   "mes": 2,
   "casos": 10,
   "COMUNA": "Lo Espejo"
  },
  {
   "delito": "CONSUMO DE ALCOHOL Y DE DROGAS EN LA VÍA PÚBLICA",
   "CODCOM": 13116,
   "anio": 2025,
   "mes": 3,
   "casos": 5,
   "COMUNA": "Lo Espejo"
  },
  {
   "delito": "CONSUMO DE ALCOHOL Y DE DROGAS EN LA VÍA PÚBLICA",
   "CODCOM": 13116,
   "anio": 2025,
   "mes": 4,
   "casos": 11,
   "COMUNA": "Lo Espejo"
  },
  {
   "delito": "CONSUMO DE ALCOHOL Y DE DROGAS EN LA VÍA PÚBLICA",
   "CODCOM": 13116,
   "anio": 2025,
   "mes": 5,
   "casos": 18,
   "COMUNA": "Lo Espejo"
  },
  {
   "delito": "CONSUMO DE ALCOHOL Y DE DROGAS EN LA VÍA PÚBLICA",
   "CODCOM": 13116,
   "anio": 2025,
   "mes": 6,
   "casos": 14,
   "COMUNA": "Lo Espejo"
  },
  {
   "delito": "CONSUMO DE ALCOHOL Y DE DROGAS EN LA VÍA PÚBLICA",
   "CODCOM": 13116,
   "anio": 2025,
   "mes": 7,
   "casos": 14,
   "COMUNA": "Lo Espejo"
  },
  {
   "delito": "CONSUMO DE ALCOHOL Y DE DROGAS EN LA VÍA PÚBLICA",
   "CODCOM": 13116,
   "anio": 2025,
   "mes": 8,
   "casos": 9,
   "COMUNA": "Lo Espejo"
  },
  {
   "delito": "CONSUMO DE ALCOHOL Y DE DROGAS EN LA VÍA PÚBLICA",
   "CODCOM": 13116,
   "anio": 2025,
   "mes": 9,
   "casos": 7,
   "COMUNA": "Lo Espejo"
  },
  {
   "delito": "CONSUMO DE ALCOHOL Y DE DROGAS EN LA VÍA PÚBLICA",
   "CODCOM": 13116,
   "anio": 2025,
   "mes": 10,
   "casos": 4,
   "COMUNA": "Lo Espejo"
  },
  {
   "delito": "CONSUMO DE ALCOHOL Y DE DROGAS EN LA VÍA PÚBLICA",
   "CODCOM": 13116,
   "anio": 2025,
   "mes": 11,
   "casos": 15,
   "COMUNA": "Lo Espejo"
  },
  {
   "delito": "DAÑOS",
   "CODCOM": 13116,
   "anio": 2024,
   "mes": 1,
   "casos": 35,
   "COMUNA": "Lo Espejo"
  },
  {
   "delito": "DAÑOS",
   "CODCOM": 13116,
   "anio": 2024,
   "mes": 2,
   "casos": 31,
   "COMUNA": "Lo Espejo"
  },
  {
   "delito": "DAÑOS",
   "CODCOM": 13116,
   "anio": 2024,
   "mes": 3,
   "casos": 28,
   "COMUNA": "Lo Espejo"
  },
  {
   "delito": "DAÑOS",
   "CODCOM": 13116,
   "anio": 2024,
   "mes": 4,
   "casos": 43,
   "COMUNA": "Lo Espejo"
  },
  {
   "delito": "DAÑOS",
   "CODCOM": 13116,
   "anio": 2024,
   "mes": 5,
   "casos": 29,
   "COMUNA": "Lo Espejo"
  },
  {
   "delito": "DAÑOS",
   "CODCOM": 13116,
   "anio": 2024,
   "mes": 6,
   "casos": 28,
   "COMUNA": "Lo Espejo"
  },
  {
   "delito": "DAÑOS",
   "CODCOM": 13116,
   "anio": 2024,
   "mes": 7,
   "casos": 47,
   "COMUNA": "Lo Espejo"
  },
  {
   "delito": "DAÑOS",
   "CODCOM": 13116,
   "anio": 2024,
   "mes": 8,
   "casos": 34,
   "COMUNA": "Lo Espejo"
  },
  {
   "delito": "DAÑOS",
   "CODCOM": 13116,
   "anio": 2024,
   "mes": 9,
   "casos": 44,
   "COMUNA": "Lo Espejo"
  },
  {
   "delito": "DAÑOS",
   "CODCOM": 13116,
   "anio": 2024,
   "mes": 10,
   "casos": 47,
   "COMUNA": "Lo Espejo"
  },
  {
   "delito": "DAÑOS",
   "CODCOM": 13116,
   "anio": 2024,
   "mes": 11,
   "casos": 46,
   "COMUNA": "Lo Espejo"
  },
  {
   "delito": "DAÑOS",
   "CODCOM": 13116,
   "anio": 2024,
   "mes": 12,
   "casos": 32,
   "COMUNA": "Lo Espejo"
  },
  {
   "delito": "DAÑOS",
   "CODCOM": 13116,
   "anio": 2025,
   "mes": 1,
   "casos": 29,
   "COMUNA": "Lo Espejo"
  },
  {
   "delito": "DAÑOS",
   "CODCOM": 13116,
   "anio": 2025,
   "mes": 2,
   "casos": 37,
   "COMUNA": "Lo Espejo"
  },
  {
   "delito": "DAÑOS",
   "CODCOM": 13116,
   "anio": 2025,
   "mes": 3,
   "casos": 33,
   "COMUNA": "Lo Espejo"
  },
  {
   "delito": "DAÑOS",
   "CODCOM": 13116,
   "anio": 2025,
   "mes": 4,
   "casos": 30,
   "COMUNA": "Lo Espejo"
  },
  {
   "delito": "DAÑOS",
   "CODCOM": 13116,
   "anio": 2025,
   "mes": 5,
   "casos": 40,
   "COMUNA": "Lo Espejo"
  },
  {
   "delito": "DAÑOS",
   "CODCOM": 13116,
   "anio": 2025,
   "mes": 6,
   "casos": 37,
   "COMUNA": "Lo Espejo"
  },
  {
   "delito": "DAÑOS",
   "CODCOM": 13116,
   "anio": 2025,
   "mes": 7,
   "casos": 39,
   "COMUNA": "Lo Espejo"
  },
  {
   "delito": "DAÑOS",
   "CODCOM": 13116,
   "anio": 2025,
   "mes": 8,
   "casos": 42,
   "COMUNA": "Lo Espejo"
  },
  {
   "delito": "DAÑOS",
   "CODCOM": 13116,
   "anio": 2025,
   "mes": 9,
   "casos": 37,
   "COMUNA": "Lo Espejo"
  },
  {
   "delito": "DAÑOS",
   "CODCOM": 13116,
   "anio": 2025,
   "mes": 10,
   "casos": 34,
   "COMUNA": "Lo Espejo"
  },
  {
   "delito": "DAÑOS",
   "CODCOM": 13116,
   "anio": 2025,
   "mes": 11,
   "casos": 7,
   "COMUNA": "Lo Espejo"
  },
  {
   "delito": "DELITOS EN CONTEXTO DE VIOLENCIA INTRAFAMILIAR",
   "CODCOM": 13116,
   "anio": 2024,
   "mes": 1,
   "casos": 57,
   "COMUNA": "Lo Espejo"
  },
  {
   "delito": "DELITOS EN CONTEXTO DE VIOLENCIA INTRAFAMILIAR",
   "CODCOM": 13116,
   "anio": 2024,
   "mes": 2,
   "casos": 58,
   "COMUNA": "Lo Espejo"
  },
  {
   "delito": "DELITOS EN CONTEXTO DE VIOLENCIA INTRAFAMILIAR",
   "CODCOM": 13116,
   "anio": 2024,
   "mes": 3,
   "casos": 50,
   "COMUNA": "Lo Espejo"
  },
  {
   "delito": "DELITOS EN CONTEXTO DE VIOLENCIA INTRAFAMILIAR",
   "CODCOM": 13116,
   "anio": 2024,
   "mes": 4,
   "casos": 56,
   "COMUNA": "Lo Espejo"
  },
  {
   "delito": "DELITOS EN CONTEXTO DE VIOLENCIA INTRAFAMILIAR",
   "CODCOM": 13116,
   "anio": 2024,
   "mes": 5,
   "casos": 33,
   "COMUNA": "Lo Espejo"
  },
  {
   "delito": "DELITOS EN CONTEXTO DE VIOLENCIA INTRAFAMILIAR",
   "CODCOM": 13116,
   "anio": 2024,
   "mes": 6,
   "casos": 31,
   "COMUNA": "Lo Espejo"
  },
  {
   "delito": "DELITOS EN CONTEXTO DE VIOLENCIA INTRAFAMILIAR",
   "CODCOM": 13116,
   "anio": 2024,
   "mes": 7,
   "casos": 31,
   "COMUNA": "Lo Espejo"
  },
  {
   "delito": "DELITOS EN CONTEXTO DE VIOLENCIA INTRAFAMILIAR",
   "CODCOM": 13116,
   "anio": 2024,
   "mes": 8,
   "casos": 52,
   "COMUNA": "Lo Espejo"
  },
  {
   "delito": "DELITOS EN CONTEXTO DE VIOLENCIA INTRAFAMILIAR",
   "CODCOM": 13116,
   "anio": 2024,
   "mes": 9,
   "casos": 81,
   "COMUNA": "Lo Espejo"
  },
  {
   "delito": "DELITOS EN CONTEXTO DE VIOLENCIA INTRAFAMILIAR",
   "CODCOM": 13116,
   "anio": 2024,
   "mes": 10,
   "casos": 56,
   "COMUNA": "Lo Espejo"
  },
  {
   "delito": "DELITOS EN CONTEXTO DE VIOLENCIA INTRAFAMILIAR",
   "CODCOM": 13116,
   "anio": 2024,
   "mes": 11,
   "casos": 55,
   "COMUNA": "Lo Espejo"
  },
  {
   "delito": "DELITOS EN CONTEXTO DE VIOLENCIA INTRAFAMILIAR",
   "CODCOM": 13116,
   "anio": 2024,
   "mes": 12,
   "casos": 47,
   "COMUNA": "Lo Espejo"
  },
  {
   "delito": "DELITOS EN CONTEXTO DE VIOLENCIA INTRAFAMILIAR",
   "CODCOM": 13116,
   "anio": 2025,
   "mes": 1,
   "casos": 64,
   "COMUNA": "Lo Espejo"
  },
  {
   "delito": "DELITOS EN CONTEXTO DE VIOLENCIA INTRAFAMILIAR",
   "CODCOM": 13116,
   "anio": 2025,
   "mes": 2,
   "casos": 47,
   "COMUNA": "Lo Espejo"
  },
  {
   "delito": "DELITOS EN CONTEXTO DE VIOLENCIA INTRAFAMILIAR",
   "CODCOM": 13116,
   "anio": 2025,
   "mes": 3,
   "casos": 39,
   "COMUNA": "Lo Espejo"
  },
  {
   "delito": "DELITOS EN CONTEXTO DE VIOLENCIA INTRAFAMILIAR",
   "CODCOM": 13116,
   "anio": 2025,
   "mes": 4,
   "casos": 56,
   "COMUNA": "Lo Espejo"
  },
  {
   "delito": "DELITOS EN CONTEXTO DE VIOLENCIA INTRAFAMILIAR",
   "CODCOM": 13116,
   "anio": 2025,
   "mes": 5,
   "casos": 37,
   "COMUNA": "Lo Espejo"
  },
  {
   "delito": "DELITOS EN CONTEXTO DE VIOLENCIA INTRAFAMILIAR",
   "CODCOM": 13116,
   "anio": 2025,
   "mes": 6,
   "casos": 41,
   "COMUNA": "Lo Espejo"
  },
  {
   "delito": "DELITOS EN CONTEXTO DE VIOLENCIA INTRAFAMILIAR",
   "CODCOM": 13116,
   "anio": 2025,
   "mes": 7,
   "casos": 52,
   "COMUNA": "Lo Espejo"
  },
  {
   "delito": "DELITOS EN CONTEXTO DE VIOLENCIA INTRAFAMILIAR",
   "CODCOM": 13116,
   "anio": 2025,
   "mes": 8,
   "casos": 38,
   "COMUNA": "Lo Espejo"
  },
  {
   "delito": "DELITOS EN CONTEXTO DE VIOLENCIA INTRAFAMILIAR",
   "CODCOM": 13116,
   "anio": 2025,
   "mes": 9,
   "casos": 58,
   "COMUNA": "Lo Espejo"
  },
  {
   "delito": "DELITOS EN CONTEXTO DE VIOLENCIA INTRAFAMILIAR",
   "CODCOM": 13116,
   "anio": 2025,
   "mes": 10,
   "casos": 40,
   "COMUNA": "Lo Espejo"
  },
  {
   "delito": "DELITOS EN CONTEXTO DE VIOLENCIA INTRAFAMILIAR",
   "CODCOM": 13116,
   "anio": 2025,
   "mes": 11,
   "casos": 14,
   "COMUNA": "Lo Espejo"
  },
  {
   "delito": "HOMICIDIOS Y FEMICIDIOS",
   "CODCOM": 13116,
   "anio": 2024,
   "mes": 1,
   "casos": 0,
   "COMUNA": "Lo Espejo"
  },
  {
   "delito": "HOMICIDIOS Y FEMICIDIOS",
   "CODCOM": 13116,
   "anio": 2024,
   "mes": 2,
   "casos": 1,
   "COMUNA": "Lo Espejo"
  },
  {
   "delito": "HOMICIDIOS Y FEMICIDIOS",
   "CODCOM": 13116,
   "anio": 2024,
   "mes": 3,
   "casos": 0,
   "COMUNA": "Lo Espejo"
  },
  {
   "delito": "HOMICIDIOS Y FEMICIDIOS",
   "CODCOM": 13116,
   "anio": 2024,
   "mes": 4,
   "casos": 0,
   "COMUNA": "Lo Espejo"
  },
  {
   "delito": "HOMICIDIOS Y FEMICIDIOS",
   "CODCOM": 13116,
   "anio": 2024,
   "mes": 5,
   "casos": 1,
   "COMUNA": "Lo Espejo"
  },
  {
   "delito": "HOMICIDIOS Y FEMICIDIOS",
   "CODCOM": 13116,
   "anio": 2024,
   "mes": 6,
   "casos": 0,
   "COMUNA": "Lo Espejo"
  },
  {
   "delito": "HOMICIDIOS Y FEMICIDIOS",
   "CODCOM": 13116,
   "anio": 2024,
   "mes": 7,
   "casos": 0,
   "COMUNA": "Lo Espejo"
  },
  {
   "delito": "HOMICIDIOS Y FEMICIDIOS",
   "CODCOM": 13116,
   "anio": 2024,
   "mes": 8,
   "casos": 0,
   "COMUNA": "Lo Espejo"
  },
  {
   "delito": "HOMICIDIOS Y FEMICIDIOS",
   "CODCOM": 13116,
   "anio": 2024,
   "mes": 9,
   "casos": 0,
   "COMUNA": "Lo Espejo"
  },
  {
   "delito": "HOMICIDIOS Y FEMICIDIOS",
   "CODCOM": 13116,
   "anio": 2024,
   "mes": 10,
   "casos": 1,
   "COMUNA": "Lo Espejo"
  },
  {
   "delito": "HOMICIDIOS Y FEMICIDIOS",
   "CODCOM": 13116,
   "anio": 2024,
   "mes": 11,
   "casos": 0,
   "COMUNA": "Lo Espejo"
  },
  {
   "delito": "HOMICIDIOS Y FEMICIDIOS",
   "CODCOM": 13116,
   "anio": 2024,
   "mes": 12,
   "casos": 1,
   "COMUNA": "Lo Espejo"
  },
  {
   "delito": "HOMICIDIOS Y FEMICIDIOS",
   "CODCOM": 13116,
   "anio": 2025,
   "mes": 1,
   "casos": 3,
   "COMUNA": "Lo Espejo"
  },
  {
   "delito": "HOMICIDIOS Y FEMICIDIOS",
   "CODCOM": 13116,
   "anio": 2025,
   "mes": 2,
   "casos": 1,
   "COMUNA": "Lo Espejo"
  },
  {
   "delito": "HOMICIDIOS Y FEMICIDIOS",
   "CODCOM": 13116,
   "anio": 2025,
   "mes": 3,
   "casos": 0,
   "COMUNA": "Lo Espejo"
  },
  {
   "delito": "HOMICIDIOS Y FEMICIDIOS",
   "CODCOM": 13116,
   "anio": 2025,
   "mes": 4,
   "casos": 1,
   "COMUNA": "Lo Espejo"
  },
  {
   "delito": "HOMICIDIOS Y FEMICIDIOS",
   "CODCOM": 13116,
   "anio": 2025,
   "mes": 5,
   "casos": 0,
   "COMUNA": "Lo Espejo"
  },
  {
   "delito": "HOMICIDIOS Y FEMICIDIOS",
   "CODCOM": 13116,
   "anio": 2025,
   "mes": 6,
   "casos": 1,
   "COMUNA": "Lo Espejo"
  },
  {
   "delito": "HOMICIDIOS Y FEMICIDIOS",
   "CODCOM": 13116,
   "anio": 2025,
   "mes": 7,
   "casos": 2,
   "COMUNA": "Lo Espejo"
  },
  {
   "delito": "HOMICIDIOS Y FEMICIDIOS",
   "CODCOM": 13116,
   "anio": 2025,
   "mes": 8,
   "casos": 1,
   "COMUNA": "Lo Espejo"
  },
  {
   "delito": "HOMICIDIOS Y FEMICIDIOS",
   "CODCOM": 13116,
   "anio": 2025,
   "mes": 9,
   "casos": 1,
   "COMUNA": "Lo Espejo"
  },
  {
   "delito": "HOMICIDIOS Y FEMICIDIOS",
   "CODCOM": 13116,
   "anio": 2025,
   "mes": 10,
   "casos": 0,
   "COMUNA": "Lo Espejo"
  },
  {
   "delito": "HOMICIDIOS Y FEMICIDIOS",
   "CODCOM": 13116,
   "anio": 2025,
   "mes": 11,
   "casos": 0,
   "COMUNA": "Lo Espejo"
  },
  {
   "delito": "HURTOS",
   "CODCOM": 13116,
   "anio": 2024,
   "mes": 1,
   "casos": 14,
   "COMUNA": "Lo Espejo"
  },
  {
   "delito": "HURTOS",
   "CODCOM": 13116,
   "anio": 2024,
   "mes": 2,
   "casos": 9,
   "COMUNA": "Lo Espejo"
  },
  {
   "delito": "HURTOS",
   "CODCOM": 13116,
   "anio": 2024,
   "mes": 3,
   "casos": 10,
   "COMUNA": "Lo Espejo"
  },
  {
   "delito": "HURTOS",
   "CODCOM": 13116,
   "anio": 2024,
   "mes": 4,
   "casos": 18,
   "COMUNA": "Lo Espejo"
  },
  {
   "delito": "HURTOS",
   "CODCOM": 13116,
   "anio": 2024,
   "mes": 5,
   "casos": 11,
   "COMUNA": "Lo Espejo"
  },
  {
   "delito": "HURTOS",
   "CODCOM": 13116,
   "anio": 2024,
   "mes": 6,
   "casos": 15,
   "COMUNA": "Lo Espejo"
  },
  {
   "delito": "HURTOS",
   "CODCOM": 13116,
   "anio": 2024,
   "mes": 7,
   "casos": 18,
   "COMUNA": "Lo Espejo"
  },
  {
   "delito": "HURTOS",
   "CODCOM": 13116,
   "anio": 2024,
   "mes": 8,
   "casos": 13,
   "COMUNA": "Lo Espejo"
  },
  {
   "delito": "HURTOS",
   "CODCOM": 13116,
   "anio": 2024,
   "mes": 9,
   "casos": 18,
   "COMUNA": "Lo Espejo"
  },
  {
   "delito": "HURTOS",
   "CODCOM": 13116,
   "anio": 2024,
   "mes": 10,
   "casos": 13,
   "COMUNA": "Lo Espejo"
  },
  {
   "delito": "HURTOS",
   "CODCOM": 13116,
   "anio": 2024,
   "mes": 11,
   "casos": 18,
   "COMUNA": "Lo Espejo"
  },
  {
   "delito": "HURTOS",
   "CODCOM": 13116,
   "anio": 2024,
   "mes": 12,
   "casos": 17,
   "COMUNA": "Lo Espejo"
  },
  {
   "delito": "HURTOS",
   "CODCOM": 13116,
   "anio": 2025,
   "mes": 1,
   "casos": 12,
   "COMUNA": "Lo Espejo"
  },
  {
   "delito": "HURTOS",
   "CODCOM": 13116,
   "anio": 2025,
   "mes": 2,
   "casos": 13,
   "COMUNA": "Lo Espejo"
  },
  {
   "delito": "HURTOS",
   "CODCOM": 13116,
   "anio": 2025,
   "mes": 3,
   "casos": 24,
   "COMUNA": "Lo Espejo"
  },
  {
   "delito": "HURTOS",
   "CODCOM": 13116,
   "anio": 2025,
   "mes": 4,
   "casos": 10,
   "COMUNA": "Lo Espejo"
  },
  {
   "delito": "HURTOS",
   "CODCOM": 13116,
   "anio": 2025,
   "mes": 5,
   "casos": 10,
   "COMUNA": "Lo Espejo"
  },
  {
   "delito": "HURTOS",
   "CODCOM": 13116,
   "anio": 2025,
   "mes": 6,
   "casos": 16,
   "COMUNA": "Lo Espejo"
  },
  {
   "delito": "HURTOS",
   "CODCOM": 13116,
   "anio": 2025,
   "mes": 7,
   "casos": 15,
   "COMUNA": "Lo Espejo"
  },
  {
   "delito": "HURTOS",
   "CODCOM": 13116,
   "anio": 2025,
   "mes": 8,
   "casos": 11,
   "COMUNA": "Lo Espejo"
  },
  {
   "delito": "HURTOS",
   "CODCOM": 13116,
   "anio": 2025,
   "mes": 9,
   "casos": 18,
   "COMUNA": "Lo Espejo"
  },
  {
   "delito": "HURTOS",
   "CODCOM": 13116,
   "anio": 2025,
   "mes": 10,
   "casos": 22,
   "COMUNA": "Lo Espejo"
  },
  {
   "delito": "HURTOS",
   "CODCOM": 13116,
   "anio": 2025,
   "mes": 11,
   "casos": 2,
   "COMUNA": "Lo Espejo"
  },
  {
   "delito": "INCIVILIDADES",
   "CODCOM": 13116,
   "anio": 2024,
   "mes": 1,
   "casos": 2,
   "COMUNA": "Lo Espejo"
  },
  {
   "delito": "INCIVILIDADES",
   "CODCOM": 13116,
   "anio": 2024,
   "mes": 2,
   "casos": 3,
   "COMUNA": "Lo Espejo"
  },
  {
   "delito": "INCIVILIDADES",
   "CODCOM": 13116,
   "anio": 2024,
   "mes": 3,
   "casos": 3,
   "COMUNA": "Lo Espejo"
  },
  {
   "delito": "INCIVILIDADES",
   "CODCOM": 13116,
   "anio": 2024,
   "mes": 4,
   "casos": 5,
   "COMUNA": "Lo Espejo"
  },
  {
   "delito": "INCIVILIDADES",
   "CODCOM": 13116,
   "anio": 2024,
   "mes": 5,
   "casos": 5,
   "COMUNA": "Lo Espejo"
  },
  {
   "delito": "INCIVILIDADES",
   "CODCOM": 13116,
   "anio": 2024,
   "mes": 6,
   "casos": 6,
   "COMUNA": "Lo Espejo"
  },
  {
   "delito": "INCIVILIDADES",
   "CODCOM": 13116,
   "anio": 2024,
   "mes": 7,
   "casos": 5,
   "COMUNA": "Lo Espejo"
  },
  {
   "delito": "INCIVILIDADES",
   "CODCOM": 13116,
   "anio": 2024,
   "mes": 8,
   "casos": 5,
   "COMUNA": "Lo Espejo"
  },
  {
   "delito": "INCIVILIDADES",
   "CODCOM": 13116,
   "anio": 2024,
   "mes": 9,
   "casos": 14,
   "COMUNA": "Lo Espejo"
  },
  {
   "delito": "INCIVILIDADES",
   "CODCOM": 13116,
   "anio": 2024,
   "mes": 10,
   "casos": 5,
   "COMUNA": "Lo Espejo"
  },
  {
   "delito": "INCIVILIDADES",
   "CODCOM": 13116,
   "anio": 2024,
   "mes": 11,
   "casos": 2,
   "COMUNA": "Lo Espejo"
  },
  {
   "delito": "INCIVILIDADES",
   "CODCOM": 13116,
   "anio": 2024,
   "mes": 12,
   "casos": 3,
   "COMUNA": "Lo Espejo"
  },
  {
   "delito": "INCIVILIDADES",
   "CODCOM": 13116,
   "anio": 2025,
   "mes": 1,
   "casos": 5,
   "COMUNA": "Lo Espejo"
  },
  {
   "delito": "INCIVILIDADES",
   "CODCOM": 13116,
   "anio": 2025,
   "mes": 2,
   "casos": 3,
   "COMUNA": "Lo Espejo"
  },
  {
   "delito": "INCIVILIDADES",
   "CODCOM": 13116,
   "anio": 2025,
   "mes": 3,
   "casos": 4,
   "COMUNA": "Lo Espejo"
  },
  {
   "delito": "INCIVILIDADES",
   "CODCOM": 13116,
   "anio": 2025,
   "mes": 4,
   "casos": 3,
   "COMUNA": "Lo Espejo"
  },
  {
   "delito": "INCIVILIDADES",
   "CODCOM": 13116,
   "anio": 2025,
   "mes": 5,
   "casos": 4,
   "COMUNA": "Lo Espejo"
  },
  {
   "delito": "INCIVILIDADES",
   "CODCOM": 13116,
   "anio": 2025,
   "mes": 6,
   "casos": 8,
   "COMUNA": "Lo Espejo"
  },
  {
   "delito": "INCIVILIDADES",
   "CODCOM": 13116,
   "anio": 2025,
   "mes": 7,
   "casos": 5,
   "COMUNA": "Lo Espejo"
  },
  {
   "delito": "INCIVILIDADES",
   "CODCOM": 13116,
   "anio": 2025,
   "mes": 8,
   "casos": 5,
   "COMUNA": "Lo Espejo"
  },
  {
   "delito": "INCIVILIDADES",
   "CODCOM": 13116,
   "anio": 2025,
   "mes": 9,
   "casos": 5,
   "COMUNA": "Lo Espejo"
  },
  {
   "delito": "INCIVILIDADES",
   "CODCOM": 13116,
   "anio": 2025,
   "mes": 10,
   "casos": 6,
   "COMUNA": "Lo Espejo"
  },
  {
   "delito": "INCIVILIDADES",
   "CODCOM": 13116,
   "anio": 2025,
   "mes": 11,
   "casos": 0,
   "COMUNA": "Lo Espejo"
  },
  {
   "delito": "LESIONES GRAVES",
   "CODCOM": 13116,
   "anio": 2024,
   "mes": 1,
   "casos": 2,
   "COMUNA": "Lo Espejo"
  },
  {
   "delito": "LESIONES GRAVES",
   "CODCOM": 13116,
   "anio": 2024,
   "mes": 2,
   "casos": 12,
   "COMUNA": "Lo Espejo"
  },
  {
   "delito": "LESIONES GRAVES",
   "CODCOM": 13116,
   "anio": 2024,
   "mes": 3,
   "casos": 5,
   "COMUNA": "Lo Espejo"
  },
  {
   "delito": "LESIONES GRAVES",
   "CODCOM": 13116,
   "anio": 2024,
   "mes": 4,
   "casos": 3,
   "COMUNA": "Lo Espejo"
  },
  {
   "delito": "LESIONES GRAVES",
   "CODCOM": 13116,
   "anio": 2024,
   "mes": 5,
   "casos": 1,
   "COMUNA": "Lo Espejo"
  },
  {
   "delito": "LESIONES GRAVES",
   "CODCOM": 13116,
   "anio": 2024,
   "mes": 6,
   "casos": 2,
   "COMUNA": "Lo Espejo"
  },
  {
   "delito": "LESIONES GRAVES",
   "CODCOM": 13116,
   "anio": 2024,
   "mes": 7,
   "casos": 6,
   "COMUNA": "Lo Espejo"
  },
  {
   "delito": "LESIONES GRAVES",
   "CODCOM": 13116,
   "anio": 2024,
   "mes": 8,
   "casos": 5,
   "COMUNA": "Lo Espejo"
  },
  {
   "delito": "LESIONES GRAVES",
   "CODCOM": 13116,
   "anio": 2024,
   "mes": 9,
   "casos": 9,
   "COMUNA": "Lo Espejo"
  },
  {
   "delito": "LESIONES GRAVES",
   "CODCOM": 13116,
   "anio": 2024,
   "mes": 10,
   "casos": 10,
   "COMUNA": "Lo Espejo"
  },
  {
   "delito": "LESIONES GRAVES",
   "CODCOM": 13116,
   "anio": 2024,
   "mes": 11,
   "casos": 3,
   "COMUNA": "Lo Espejo"
  },
  {
   "delito": "LESIONES GRAVES",
   "CODCOM": 13116,
   "anio": 2024,
   "mes": 12,
   "casos": 10,
   "COMUNA": "Lo Espejo"
  },
  {
   "delito": "LESIONES GRAVES",
   "CODCOM": 13116,
   "anio": 2025,
   "mes": 1,
   "casos": 3,
   "COMUNA": "Lo Espejo"
  },
  {
   "delito": "LESIONES GRAVES",
   "CODCOM": 13116,
   "anio": 2025,
   "mes": 2,
   "casos": 2,
   "COMUNA": "Lo Espejo"
  },
  {
   "delito": "LESIONES GRAVES",
   "CODCOM": 13116,
   "anio": 2025,
   "mes": 3,
   "casos": 4,
   "COMUNA": "Lo Espejo"
  },
  {
   "delito": "LESIONES GRAVES",
   "CODCOM": 13116,
   "anio": 2025,
   "mes": 4,
   "casos": 3,
   "COMUNA": "Lo Espejo"
  },
  {
   "delito": "LESIONES GRAVES",
   "CODCOM": 13116,
   "anio": 2025,
   "mes": 5,
   "casos": 4,
   "COMUNA": "Lo Espejo"
  },
  {
   "delito": "LESIONES GRAVES",
   "CODCOM": 13116,
   "anio": 2025,
   "mes": 6,
   "casos": 5,
   "COMUNA": "Lo Espejo"
  },
  {
   "delito": "LESIONES GRAVES",
   "CODCOM": 13116,
   "anio": 2025,
   "mes": 7,
   "casos": 3,
   "COMUNA": "Lo Espejo"
  },
  {
   "delito": "LESIONES GRAVES",
   "CODCOM": 13116,
   "anio": 2025,
   "mes": 8,
   "casos": 2,
   "COMUNA": "Lo Espejo"
  },
  {
   "delito": "LESIONES GRAVES",
   "CODCOM": 13116,
   "anio": 2025,
   "mes": 9,
   "casos": 3,
   "COMUNA": "Lo Espejo"
  },
  {
   "delito": "LESIONES GRAVES",
   "CODCOM": 13116,
   "anio": 2025,
   "mes": 10,
   "casos": 3,
   "COMUNA": "Lo Espejo"
  },
  {
   "delito": "LESIONES GRAVES",
   "CODCOM": 13116,
   "anio": 2025,
   "mes": 11,
   "casos": 3,
   "COMUNA": "Lo Espejo"
  },
  {
   "delito": "LESIONES LEVES",
   "CODCOM": 13116,
   "anio": 2024,
   "mes": 1,
   "casos": 35,
   "COMUNA": "Lo Espejo"
  },
  {
   "delito": "LESIONES LEVES",
   "CODCOM": 13116,
   "anio": 2024,
   "mes": 2,
   "casos": 22,
   "COMUNA": "Lo Espejo"
  },
  {
   "delito": "LESIONES LEVES",
   "CODCOM": 13116,
   "anio": 2024,
   "mes": 3,
   "casos": 31,
   "COMUNA": "Lo Espejo"
  },
  {
   "delito": "LESIONES LEVES",
   "CODCOM": 13116,
   "anio": 2024,
   "mes": 4,
   "casos": 21,
   "COMUNA": "Lo Espejo"
  },
  {
   "delito": "LESIONES LEVES",
   "CODCOM": 13116,
   "anio": 2024,
   "mes": 5,
   "casos": 16,
   "COMUNA": "Lo Espejo"
  },
  {
   "delito": "LESIONES LEVES",
   "CODCOM": 13116,
   "anio": 2024,
   "mes": 6,
   "casos": 18,
   "COMUNA": "Lo Espejo"
  },
  {
   "delito": "LESIONES LEVES",
   "CODCOM": 13116,
   "anio": 2024,
   "mes": 7,
   "casos": 28,
   "COMUNA": "Lo Espejo"
  },
  {
   "delito": "LESIONES LEVES",
   "CODCOM": 13116,
   "anio": 2024,
   "mes": 8,
   "casos": 32,
   "COMUNA": "Lo Espejo"
  },
  {
   "delito": "LESIONES LEVES",
   "CODCOM": 13116,
   "anio": 2024,
   "mes": 9,
   "casos": 38,
   "COMUNA": "Lo Espejo"
  },
  {
   "delito": "LESIONES LEVES",
   "CODCOM": 13116,
   "anio": 2024,
   "mes": 10,
   "casos": 22,
   "COMUNA": "Lo Espejo"
  },
  {
   "delito": "LESIONES LEVES",
   "CODCOM": 13116,
   "anio": 2024,
   "mes": 11,
   "casos": 31,
   "COMUNA": "Lo Espejo"
  },
  {
   "delito": "LESIONES LEVES",
   "CODCOM": 13116,
   "anio": 2024,
   "mes": 12,
   "casos": 41,
   "COMUNA": "Lo Espejo"
  },
  {
   "delito": "LESIONES LEVES",
   "CODCOM": 13116,
   "anio": 2025,
   "mes": 1,
   "casos": 35,
   "COMUNA": "Lo Espejo"
  },
  {
   "delito": "LESIONES LEVES",
   "CODCOM": 13116,
   "anio": 2025,
   "mes": 2,
   "casos": 24,
   "COMUNA": "Lo Espejo"
  },
  {
   "delito": "LESIONES LEVES",
   "CODCOM": 13116,
   "anio": 2025,
   "mes": 3,
   "casos": 35,
   "COMUNA": "Lo Espejo"
  },
  {
   "delito": "LESIONES LEVES",
   "CODCOM": 13116,
   "anio": 2025,
   "mes": 4,
   "casos": 19,
   "COMUNA": "Lo Espejo"
  },
  {
   "delito": "LESIONES LEVES",
   "CODCOM": 13116,
   "anio": 2025,
   "mes": 5,
   "casos": 22,
   "COMUNA": "Lo Espejo"
  },
  {
   "delito": "LESIONES LEVES",
   "CODCOM": 13116,
   "anio": 2025,
   "mes": 6,
   "casos": 23,
   "COMUNA": "Lo Espejo"
  },
  {
   "delito": "LESIONES LEVES",
   "CODCOM": 13116,
   "anio": 2025,
   "mes": 7,
   "casos": 24,
   "COMUNA": "Lo Espejo"
  },
  {
   "delito": "LESIONES LEVES",
   "CODCOM": 13116,
   "anio": 2025,
   "mes": 8,
   "casos": 26,
   "COMUNA": "Lo Espejo"
  },
  {
   "delito": "LESIONES LEVES",
   "CODCOM": 13116,
   "anio": 2025,
   "mes": 9,
   "casos": 22,
   "COMUNA": "Lo Espejo"
  },
  {
   "delito": "LESIONES LEVES",
   "CODCOM": 13116,
   "anio": 2025,
   "mes": 10,
   "casos": 23,
   "COMUNA": "Lo Espejo"
  },
  {
   "delito": "LESIONES LEVES",
   "CODCOM": 13116,
   "anio": 2025,
   "mes": 11,
   "casos": 5,
   "COMUNA": "Lo Espejo"
  },
  {
   "delito": "LESIONES MENOS GRAVES",
   "CODCOM": 13116,
   "anio": 2024,
   "mes": 1,
   "casos": 5,
   "COMUNA": "Lo Espejo"
  },
  {
   "delito": "LESIONES MENOS GRAVES",
   "CODCOM": 13116,
   "anio": 2024,
   "mes": 2,
   "casos": 9,
   "COMUNA": "Lo Espejo"
  },
  {
   "delito": "LESIONES MENOS GRAVES",
   "CODCOM": 13116,
   "anio": 2024,
   "mes": 3,
   "casos": 4,
   "COMUNA": "Lo Espejo"
  },
  {
   "delito": "LESIONES MENOS GRAVES",
   "CODCOM": 13116,
   "anio": 2024,
   "mes": 4,
   "casos": 7,
   "COMUNA": "Lo Espejo"
  },
  {
   "delito": "LESIONES MENOS GRAVES",
   "CODCOM": 13116,
   "anio": 2024,
   "mes": 5,
   "casos": 7,
   "COMUNA": "Lo Espejo"
  },
  {
   "delito": "LESIONES MENOS GRAVES",
   "CODCOM": 13116,
   "anio": 2024,
   "mes": 6,
   "casos": 5,
   "COMUNA": "Lo Espejo"
  },
  {
   "delito": "LESIONES MENOS GRAVES",
   "CODCOM": 13116,
   "anio": 2024,
   "mes": 7,
   "casos": 5,
   "COMUNA": "Lo Espejo"
  },
  {
   "delito": "LESIONES MENOS GRAVES",
   "CODCOM": 13116,
   "anio": 2024,
   "mes": 8,
   "casos": 6,
   "COMUNA": "Lo Espejo"
  },
  {
   "delito": "LESIONES MENOS GRAVES",
   "CODCOM": 13116,
   "anio": 2024,
   "mes": 9,
   "casos": 4,
   "COMUNA": "Lo Espejo"
  },
  {
   "delito": "LESIONES MENOS GRAVES",
   "CODCOM": 13116,
   "anio": 2024,
   "mes": 10,
   "casos": 3,
   "COMUNA": "Lo Espejo"
  },
  {
   "delito": "LESIONES MENOS GRAVES",
   "CODCOM": 13116,
   "anio": 2024,
   "mes": 11,
   "casos": 8,
   "COMUNA": "Lo Espejo"
  },
  {
   "delito": "LESIONES MENOS GRAVES",
   "CODCOM": 13116,
   "anio": 2024,
   "mes": 12,
   "casos": 4,
   "COMUNA": "Lo Espejo"
  },
  {
   "delito": "LESIONES MENOS GRAVES",
   "CODCOM": 13116,
   "anio": 2025,
   "mes": 1,
   "casos": 7,
   "COMUNA": "Lo Espejo"
  },
  {
   "delito": "LESIONES MENOS GRAVES",
   "CODCOM": 13116,
   "anio": 2025,
   "mes": 2,
   "casos": 4,
   "COMUNA": "Lo Espejo"
  },
  {
   "delito": "LESIONES MENOS GRAVES",
   "CODCOM": 13116,
   "anio": 2025,
   "mes": 3,
   "casos": 2,
   "COMUNA": "Lo Espejo"
  },
  {
   "delito": "LESIONES MENOS GRAVES",
   "CODCOM": 13116,
   "anio": 2025,
   "mes": 4,
   "casos": 6,
   "COMUNA": "Lo Espejo"
  },
  {
   "delito": "LESIONES MENOS GRAVES",
   "CODCOM": 13116,
   "anio": 2025,
   "mes": 5,
   "casos": 2,
   "COMUNA": "Lo Espejo"
  },
  {
   "delito": "LESIONES MENOS GRAVES",
   "CODCOM": 13116,
   "anio": 2025,
   "mes": 6,
   "casos": 7,
   "COMUNA": "Lo Espejo"
  },
  {
   "delito": "LESIONES MENOS GRAVES",
   "CODCOM": 13116,
   "anio": 2025,
   "mes": 7,
   "casos": 6,
   "COMUNA": "Lo Espejo"
  },
  {
   "delito": "LESIONES MENOS GRAVES",
   "CODCOM": 13116,
   "anio": 2025,
   "mes": 8,
   "casos": 4,
   "COMUNA": "Lo Espejo"
  },
  {
   "delito": "LESIONES MENOS GRAVES",
   "CODCOM": 13116,
   "anio": 2025,
   "mes": 9,
   "casos": 7,
   "COMUNA": "Lo Espejo"
  },
  {
   "delito": "LESIONES MENOS GRAVES",
   "CODCOM": 13116,
   "anio": 2025,
   "mes": 10,
   "casos": 8,
   "COMUNA": "Lo Espejo"
  },
  {
   "delito": "LESIONES MENOS GRAVES",
   "CODCOM": 13116,
   "anio": 2025,
   "mes": 11,
   "casos": 2,
   "COMUNA": "Lo Espejo"
  },
  {
   "delito": "LEY DE CONTROL DE ARMAS",
   "CODCOM": 13116,
   "anio": 2024,
   "mes": 1,
   "casos": 10,
   "COMUNA": "Lo Espejo"
  },
  {
   "delito": "LEY DE CONTROL DE ARMAS",
   "CODCOM": 13116,
   "anio": 2024,
   "mes": 2,
   "casos": 4,
   "COMUNA": "Lo Espejo"
  },
  {
   "delito": "LEY DE CONTROL DE ARMAS",
   "CODCOM": 13116,
   "anio": 2024,
   "mes": 3,
   "casos": 9,
   "COMUNA": "Lo Espejo"
  },
  {
   "delito": "LEY DE CONTROL DE ARMAS",
   "CODCOM": 13116,
   "anio": 2024,
   "mes": 4,
   "casos": 14,
   "COMUNA": "Lo Espejo"
  },
  {
   "delito": "LEY DE CONTROL DE ARMAS",
   "CODCOM": 13116,
   "anio": 2024,
   "mes": 5,
   "casos": 8,
   "COMUNA": "Lo Espejo"
  },
  {
   "delito": "LEY DE CONTROL DE ARMAS",
   "CODCOM": 13116,
   "anio": 2024,
   "mes": 6,
   "casos": 18,
   "COMUNA": "Lo Espejo"
  },
  {
   "delito": "LEY DE CONTROL DE ARMAS",
   "CODCOM": 13116,
   "anio": 2024,
   "mes": 7,
   "casos": 19,
   "COMUNA": "Lo Espejo"
  },
  {
   "delito": "LEY DE CONTROL DE ARMAS",
   "CODCOM": 13116,
   "anio": 2024,
   "mes": 8,
   "casos": 20,
   "COMUNA": "Lo Espejo"
  },
  {
   "delito": "LEY DE CONTROL DE ARMAS",
   "CODCOM": 13116,
   "anio": 2024,
   "mes": 9,
   "casos": 22,
   "COMUNA": "Lo Espejo"
  },
  {
   "delito": "LEY DE CONTROL DE ARMAS",
   "CODCOM": 13116,
   "anio": 2024,
   "mes": 10,
   "casos": 25,
   "COMUNA": "Lo Espejo"
  },
  {
   "delito": "LEY DE CONTROL DE ARMAS",
   "CODCOM": 13116,
   "anio": 2024,
   "mes": 11,
   "casos": 21,
   "COMUNA": "Lo Espejo"
  },
  {
   "delito": "LEY DE CONTROL DE ARMAS",
   "CODCOM": 13116,
   "anio": 2024,
   "mes": 12,
   "casos": 20,
   "COMUNA": "Lo Espejo"
  },
  {
   "delito": "LEY DE CONTROL DE ARMAS",
   "CODCOM": 13116,
   "anio": 2025,
   "mes": 1,
   "casos": 12,
   "COMUNA": "Lo Espejo"
  },
  {
   "delito": "LEY DE CONTROL DE ARMAS",
   "CODCOM": 13116,
   "anio": 2025,
   "mes": 2,
   "casos": 4,
   "COMUNA": "Lo Espejo"
  },
  {
   "delito": "LEY DE CONTROL DE ARMAS",
   "CODCOM": 13116,
   "anio": 2025,
   "mes": 3,
   "casos": 18,
   "COMUNA": "Lo Espejo"
  },
  {
   "delito": "LEY DE CONTROL DE ARMAS",
   "CODCOM": 13116,
   "anio": 2025,
   "mes": 4,
   "casos": 24,
   "COMUNA": "Lo Espejo"
  },
  {
   "delito": "LEY DE CONTROL DE ARMAS",
   "CODCOM": 13116,
   "anio": 2025,
   "mes": 5,
   "casos": 32,
   "COMUNA": "Lo Espejo"
  },
  {
   "delito": "LEY DE CONTROL DE ARMAS",
   "CODCOM": 13116,
   "anio": 2025,
   "mes": 6,
   "casos": 47,
   "COMUNA": "Lo Espejo"
  },
  {
   "delito": "LEY DE CONTROL DE ARMAS",
   "CODCOM": 13116,
   "anio": 2025,
   "mes": 7,
   "casos": 16,
   "COMUNA": "Lo Espejo"
  },
  {
   "delito": "LEY DE CONTROL DE ARMAS",
   "CODCOM": 13116,
   "anio": 2025,
   "mes": 8,
   "casos": 28,
   "COMUNA": "Lo Espejo"
  },
  {
   "delito": "LEY DE CONTROL DE ARMAS",
   "CODCOM": 13116,
   "anio": 2025,
   "mes": 9,
   "casos": 24,
   "COMUNA": "Lo Espejo"
  },
  {
   "delito": "LEY DE CONTROL DE ARMAS",
   "CODCOM": 13116,
   "anio": 2025,
   "mes": 10,
   "casos": 28,
   "COMUNA": "Lo Espejo"
  },
  {
   "delito": "LEY DE CONTROL DE ARMAS",
   "CODCOM": 13116,
   "anio": 2025,
   "mes": 11,
   "casos": 6,
   "COMUNA": "Lo Espejo"
  },
  {
   "delito": "LEY DE DROGAS",
   "CODCOM": 13116,
   "anio": 2024,
   "mes": 1,
   "casos": 4,
   "COMUNA": "Lo Espejo"
  },
  {
   "delito": "LEY DE DROGAS",
   "CODCOM": 13116,
   "anio": 2024,
   "mes": 2,
   "casos": 6,
   "COMUNA": "Lo Espejo"
  },
  {
   "delito": "LEY DE DROGAS",
   "CODCOM": 13116,
   "anio": 2024,
   "mes": 3,
   "casos": 2,
   "COMUNA": "Lo Espejo"
  },
  {
   "delito": "LEY DE DROGAS",
   "CODCOM": 13116,
   "anio": 2024,
   "mes": 4,
   "casos": 5,
   "COMUNA": "Lo Espejo"
  },
  {
   "delito": "LEY DE DROGAS",
   "CODCOM": 13116,
   "anio": 2024,
   "mes": 5,
   "casos": 9,
   "COMUNA": "Lo Espejo"
  },
  {
   "delito": "LEY DE DROGAS",
   "CODCOM": 13116,
   "anio": 2024,
   "mes": 6,
   "casos": 2,
   "COMUNA": "Lo Espejo"
  },
  {
   "delito": "LEY DE DROGAS",
   "CODCOM": 13116,
   "anio": 2024,
   "mes": 7,
   "casos": 4,
   "COMUNA": "Lo Espejo"
  },
  {
   "delito": "LEY DE DROGAS",
   "CODCOM": 13116,
   "anio": 2024,
   "mes": 8,
   "casos": 7,
   "COMUNA": "Lo Espejo"
  },
  {
   "delito": "LEY DE DROGAS",
   "CODCOM": 13116,
   "anio": 2024,
   "mes": 9,
   "casos": 8,
   "COMUNA": "Lo Espejo"
  },
  {
   "delito": "LEY DE DROGAS",
   "CODCOM": 13116,
   "anio": 2024,
   "mes": 10,
   "casos": 4,
   "COMUNA": "Lo Espejo"
  },
  {
   "delito": "LEY DE DROGAS",
   "CODCOM": 13116,
   "anio": 2024,
   "mes": 11,
   "casos": 3,
   "COMUNA": "Lo Espejo"
  },
  {
   "delito": "LEY DE DROGAS",
   "CODCOM": 13116,
   "anio": 2024,
   "mes": 12,
   "casos": 4,
   "COMUNA": "Lo Espejo"
  },
  {
   "delito": "LEY DE DROGAS",
   "CODCOM": 13116,
   "anio": 2025,
   "mes": 1,
   "casos": 9,
   "COMUNA": "Lo Espejo"
  },
  {
   "delito": "LEY DE DROGAS",
   "CODCOM": 13116,
   "anio": 2025,
   "mes": 2,
   "casos": 4,
   "COMUNA": "Lo Espejo"
  },
  {
   "delito": "LEY DE DROGAS",
   "CODCOM": 13116,
   "anio": 2025,
   "mes": 3,
   "casos": 14,
   "COMUNA": "Lo Espejo"
  },
  {
   "delito": "LEY DE DROGAS",
   "CODCOM": 13116,
   "anio": 2025,
   "mes": 4,
   "casos": 3,
   "COMUNA": "Lo Espejo"
  },
  {
   "delito": "LEY DE DROGAS",
   "CODCOM": 13116,
   "anio": 2025,
   "mes": 5,
   "casos": 4,
   "COMUNA": "Lo Espejo"
  },
  {
   "delito": "LEY DE DROGAS",
   "CODCOM": 13116,
   "anio": 2025,
   "mes": 6,
   "casos": 10,
   "COMUNA": "Lo Espejo"
  },
  {
   "delito": "LEY DE DROGAS",
   "CODCOM": 13116,
   "anio": 2025,
   "mes": 7,
   "casos": 8,
   "COMUNA": "Lo Espejo"
  },
  {
   "delito": "LEY DE DROGAS",
   "CODCOM": 13116,
   "anio": 2025,
   "mes": 8,
   "casos": 15,
   "COMUNA": "Lo Espejo"
  },
  {
   "delito": "LEY DE DROGAS",
   "CODCOM": 13116,
   "anio": 2025,
   "mes": 9,
   "casos": 19,
   "COMUNA": "Lo Espejo"
  },
  {
   "delito": "LEY DE DROGAS",
   "CODCOM": 13116,
   "anio": 2025,
   "mes": 10,
   "casos": 10,
   "COMUNA": "Lo Espejo"
  },
  {
   "delito": "LEY DE DROGAS",
   "CODCOM": 13116,
   "anio": 2025,
   "mes": 11,
   "casos": 2,
   "COMUNA": "Lo Espejo"
  },
  {
   "delito": "OTROS DESÓRDENES PÚBLICOS",
   "CODCOM": 13116,
   "anio": 2024,
   "mes": 1,
   "casos": 1,
   "COMUNA": "Lo Espejo"
  },
  {
   "delito": "OTROS DESÓRDENES PÚBLICOS",
   "CODCOM": 13116,
   "anio": 2024,
   "mes": 2,
   "casos": 0,
   "COMUNA": "Lo Espejo"
  },
  {
   "delito": "OTROS DESÓRDENES PÚBLICOS",
   "CODCOM": 13116,
   "anio": 2024,
   "mes": 3,
   "casos": 2,
   "COMUNA": "Lo Espejo"
  },
  {
   "delito": "OTROS DESÓRDENES PÚBLICOS",
   "CODCOM": 13116,
   "anio": 2024,
   "mes": 4,
   "casos": 0,
   "COMUNA": "Lo Espejo"
  },
  {
   "delito": "OTROS DESÓRDENES PÚBLICOS",
   "CODCOM": 13116,
   "anio": 2024,
   "mes": 5,
   "casos": 0,
   "COMUNA": "Lo Espejo"
  },
  {
   "delito": "OTROS DESÓRDENES PÚBLICOS",
   "CODCOM": 13116,
   "anio": 2024,
   "mes": 6,
   "casos": 0,
   "COMUNA": "Lo Espejo"
  },
  {
   "delito": "OTROS DESÓRDENES PÚBLICOS",
   "CODCOM": 13116,
   "anio": 2024,
   "mes": 7,
   "casos": 0,
   "COMUNA": "Lo Espejo"
  },
  {
   "delito": "OTROS DESÓRDENES PÚBLICOS",
   "CODCOM": 13116,
   "anio": 2024,
   "mes": 8,
   "casos": 0,
   "COMUNA": "Lo Espejo"
  },
  {
   "delito": "OTROS DESÓRDENES PÚBLICOS",
   "CODCOM": 13116,
   "anio": 2024,
   "mes": 9,
   "casos": 2,
   "COMUNA": "Lo Espejo"
  },
  {
   "delito": "OTROS DESÓRDENES PÚBLICOS",
   "CODCOM": 13116,
   "anio": 2024,
   "mes": 10,
   "casos": 1,
   "COMUNA": "Lo Espejo"
  },
  {
   "delito": "OTROS DESÓRDENES PÚBLICOS",
   "CODCOM": 13116,
   "anio": 2024,
   "mes": 11,
   "casos": 2,
   "COMUNA": "Lo Espejo"
  },
  {
   "delito": "OTROS DESÓRDENES PÚBLICOS",
   "CODCOM": 13116,
   "anio": 2024,
   "mes": 12,
   "casos": 0,
   "COMUNA": "Lo Espejo"
  },
  {
   "delito": "OTROS DESÓRDENES PÚBLICOS",
   "CODCOM": 13116,
   "anio": 2025,
   "mes": 1,
   "casos": 0,
   "COMUNA": "Lo Espejo"
  },
  {
   "delito": "OTROS DESÓRDENES PÚBLICOS",
   "CODCOM": 13116,
   "anio": 2025,
   "mes": 2,
   "casos": 0,
   "COMUNA": "Lo Espejo"
  },
  {
   "delito": "OTROS DESÓRDENES PÚBLICOS",
   "CODCOM": 13116,
   "anio": 2025,
   "mes": 3,
   "casos": 0,
   "COMUNA": "Lo Espejo"
  },
  {
   "delito": "OTROS DESÓRDENES PÚBLICOS",
   "CODCOM": 13116,
   "anio": 2025,
   "mes": 4,
   "casos": 0,
   "COMUNA": "Lo Espejo"
  },
  {
   "delito": "OTROS DESÓRDENES PÚBLICOS",
   "CODCOM": 13116,
   "anio": 2025,
   "mes": 5,
   "casos": 1,
   "COMUNA": "Lo Espejo"
  },
  {
   "delito": "OTROS DESÓRDENES PÚBLICOS",
   "CODCOM": 13116,
   "anio": 2025,
   "mes": 6,
   "casos": 0,
   "COMUNA": "Lo Espejo"
  },
  {
   "delito": "OTROS DESÓRDENES PÚBLICOS",
   "CODCOM": 13116,
   "anio": 2025,
   "mes": 7,
   "casos": 0,
   "COMUNA": "Lo Espejo"
  },
  {
   "delito": "OTROS DESÓRDENES PÚBLICOS",
   "CODCOM": 13116,
   "anio": 2025,
   "mes": 8,
   "casos": 1,
   "COMUNA": "Lo Espejo"
  },
  {
   "delito": "OTROS DESÓRDENES PÚBLICOS",
   "CODCOM": 13116,
   "anio": 2025,
   "mes": 9,
   "casos": 1,
   "COMUNA": "Lo Espejo"
  },
  {
   "delito": "OTROS DESÓRDENES PÚBLICOS",
   "CODCOM": 13116,
   "anio": 2025,
   "mes": 10,
   "casos": 1,
   "COMUNA": "Lo Espejo"
  },
  {
   "delito": "OTROS DESÓRDENES PÚBLICOS",
   "CODCOM": 13116,
   "anio": 2025,
   "mes": 11,
   "casos": 0,
   "COMUNA": "Lo Espejo"
  },
  {
   "delito": "OTROS ROBOS CON FUERZA EN LAS COSAS",
   "CODCOM": 13116,
   "anio": 2024,
   "mes": 1,
   "casos": 6,
   "COMUNA": "Lo Espejo"
  },
  {
   "delito": "OTROS ROBOS CON FUERZA EN LAS COSAS",
   "CODCOM": 13116,
   "anio": 2024,
   "mes": 2,
   "casos": 2,
   "COMUNA": "Lo Espejo"
  },
  {
   "delito": "OTROS ROBOS CON FUERZA EN LAS COSAS",
   "CODCOM": 13116,
   "anio": 2024,
   "mes": 3,
   "casos": 1,
   "COMUNA": "Lo Espejo"
  },
  {
   "delito": "OTROS ROBOS CON FUERZA EN LAS COSAS",
   "CODCOM": 13116,
   "anio": 2024,
   "mes": 4,
   "casos": 0,
   "COMUNA": "Lo Espejo"
  },
  {
   "delito": "OTROS ROBOS CON FUERZA EN LAS COSAS",
   "CODCOM": 13116,
   "anio": 2024,
   "mes": 5,
   "casos": 3,
   "COMUNA": "Lo Espejo"
  },
  {
   "delito": "OTROS ROBOS CON FUERZA EN LAS COSAS",
   "CODCOM": 13116,
   "anio": 2024,
   "mes": 6,
   "casos": 1,
   "COMUNA": "Lo Espejo"
  },
  {
   "delito": "OTROS ROBOS CON FUERZA EN LAS COSAS",
   "CODCOM": 13116,
   "anio": 2024,
   "mes": 7,
   "casos": 1,
   "COMUNA": "Lo Espejo"
  },
  {
   "delito": "OTROS ROBOS CON FUERZA EN LAS COSAS",
   "CODCOM": 13116,
   "anio": 2024,
   "mes": 8,
   "casos": 0,
   "COMUNA": "Lo Espejo"
  },
  {
   "delito": "OTROS ROBOS CON FUERZA EN LAS COSAS",
   "CODCOM": 13116,
   "anio": 2024,
   "mes": 9,
   "casos": 3,
   "COMUNA": "Lo Espejo"
  },
  {
   "delito": "OTROS ROBOS CON FUERZA EN LAS COSAS",
   "CODCOM": 13116,
   "anio": 2024,
   "mes": 10,
   "casos": 1,
   "COMUNA": "Lo Espejo"
  },
  {
   "delito": "OTROS ROBOS CON FUERZA EN LAS COSAS",
   "CODCOM": 13116,
   "anio": 2024,
   "mes": 11,
   "casos": 1,
   "COMUNA": "Lo Espejo"
  },
  {
   "delito": "OTROS ROBOS CON FUERZA EN LAS COSAS",
   "CODCOM": 13116,
   "anio": 2024,
   "mes": 12,
   "casos": 1,
   "COMUNA": "Lo Espejo"
  },
  {
   "delito": "OTROS ROBOS CON FUERZA EN LAS COSAS",
   "CODCOM": 13116,
   "anio": 2025,
   "mes": 1,
   "casos": 4,
   "COMUNA": "Lo Espejo"
  },
  {
   "delito": "OTROS ROBOS CON FUERZA EN LAS COSAS",
   "CODCOM": 13116,
   "anio": 2025,
   "mes": 2,
   "casos": 2,
   "COMUNA": "Lo Espejo"
  },
  {
   "delito": "OTROS ROBOS CON FUERZA EN LAS COSAS",
   "CODCOM": 13116,
   "anio": 2025,
   "mes": 3,
   "casos": 8,
   "COMUNA": "Lo Espejo"
  },
  {
   "delito": "OTROS ROBOS CON FUERZA EN LAS COSAS",
   "CODCOM": 13116,
   "anio": 2025,
   "mes": 4,
   "casos": 1,
   "COMUNA": "Lo Espejo"
  },
  {
   "delito": "OTROS ROBOS CON FUERZA EN LAS COSAS",
   "CODCOM": 13116,
   "anio": 2025,
   "mes": 5,
   "casos": 2,
   "COMUNA": "Lo Espejo"
  },
  {
   "delito": "OTROS ROBOS CON FUERZA EN LAS COSAS",
   "CODCOM": 13116,
   "anio": 2025,
   "mes": 6,
   "casos": 4,
   "COMUNA": "Lo Espejo"
  },
  {
   "delito": "OTROS ROBOS CON FUERZA EN LAS COSAS",
   "CODCOM": 13116,
   "anio": 2025,
   "mes": 7,
   "casos": 3,
   "COMUNA": "Lo Espejo"
  },
  {
   "delito": "OTROS ROBOS CON FUERZA EN LAS COSAS",
   "CODCOM": 13116,
   "anio": 2025,
   "mes": 8,
   "casos": 4,
   "COMUNA": "Lo Espejo"
  },
  {
   "delito": "OTROS ROBOS CON FUERZA EN LAS COSAS",
   "CODCOM": 13116,
   "anio": 2025,
   "mes": 9,
   "casos": 4,
   "COMUNA": "Lo Espejo"
  },
  {
   "delito": "OTROS ROBOS CON FUERZA EN LAS COSAS",
   "CODCOM": 13116,
   "anio": 2025,
   "mes": 10,
   "casos": 1,
   "COMUNA": "Lo Espejo"
  },
  {
   "delito": "OTROS ROBOS CON FUERZA EN LAS COSAS",
   "CODCOM": 13116,
   "anio": 2025,
   "mes": 11,
   "casos": 1,
   "COMUNA": "Lo Espejo"
  },
  {
   "delito": "RECEPTACIÓN",
   "CODCOM": 13116,
   "anio": 2024,
   "mes": 1,
   "casos": 9,
   "COMUNA": "Lo Espejo"
  },
  {
   "delito": "RECEPTACIÓN",
   "CODCOM": 13116,
   "anio": 2024,
   "mes": 2,
   "casos": 4,
   "COMUNA": "Lo Espejo"
  },
  {
   "delito": "RECEPTACIÓN",
   "CODCOM": 13116,
   "anio": 2024,
   "mes": 3,
   "casos": 5,
   "COMUNA": "Lo Espejo"
  },
  {
   "delito": "RECEPTACIÓN",
   "CODCOM": 13116,
   "anio": 2024,
   "mes": 4,
   "casos": 3,
   "COMUNA": "Lo Espejo"
  },
  {
   "delito": "RECEPTACIÓN",
   "CODCOM": 13116,
   "anio": 2024,
   "mes": 5,
   "casos": 3,
   "COMUNA": "Lo Espejo"
  },
  {
   "delito": "RECEPTACIÓN",
   "CODCOM": 13116,
   "anio": 2024,
   "mes": 6,
   "casos": 5,
   "COMUNA": "Lo Espejo"
  },
  {
   "delito": "RECEPTACIÓN",
   "CODCOM": 13116,
   "anio": 2024,
   "mes": 7,
   "casos": 2,
   "COMUNA": "Lo Espejo"
  },
  {
   "delito": "RECEPTACIÓN",
   "CODCOM": 13116,
   "anio": 2024,
   "mes": 8,
   "casos": 2,
   "COMUNA": "Lo Espejo"
  },
  {
   "delito": "RECEPTACIÓN",
   "CODCOM": 13116,
   "anio": 2024,
   "mes": 9,
   "casos": 5,
   "COMUNA": "Lo Espejo"
  },
  {
   "delito": "RECEPTACIÓN",
   "CODCOM": 13116,
   "anio": 2024,
   "mes": 10,
   "casos": 5,
   "COMUNA": "Lo Espejo"
  },
  {
   "delito": "RECEPTACIÓN",
   "CODCOM": 13116,
   "anio": 2024,
   "mes": 11,
   "casos": 4,
   "COMUNA": "Lo Espejo"
  },
  {
   "delito": "RECEPTACIÓN",
   "CODCOM": 13116,
   "anio": 2024,
   "mes": 12,
   "casos": 3,
   "COMUNA": "Lo Espejo"
  },
  {
   "delito": "RECEPTACIÓN",
   "CODCOM": 13116,
   "anio": 2025,
   "mes": 1,
   "casos": 9,
   "COMUNA": "Lo Espejo"
  },
  {
   "delito": "RECEPTACIÓN",
   "CODCOM": 13116,
   "anio": 2025,
   "mes": 2,
   "casos": 4,
   "COMUNA": "Lo Espejo"
  },
  {
   "delito": "RECEPTACIÓN",
   "CODCOM": 13116,
   "anio": 2025,
   "mes": 3,
   "casos": 2,
   "COMUNA": "Lo Espejo"
  },
  {
   "delito": "RECEPTACIÓN",
   "CODCOM": 13116,
   "anio": 2025,
   "mes": 4,
   "casos": 2,
   "COMUNA": "Lo Espejo"
  },
  {
   "delito": "RECEPTACIÓN",
   "CODCOM": 13116,
   "anio": 2025,
   "mes": 5,
   "casos": 5,
   "COMUNA": "Lo Espejo"
  },
  {
   "delito": "RECEPTACIÓN",
   "CODCOM": 13116,
   "anio": 2025,
   "mes": 6,
   "casos": 15,
   "COMUNA": "Lo Espejo"
  },
  {
   "delito": "RECEPTACIÓN",
   "CODCOM": 13116,
   "anio": 2025,
   "mes": 7,
   "casos": 9,
   "COMUNA": "Lo Espejo"
  },
  {
   "delito": "RECEPTACIÓN",
   "CODCOM": 13116,
   "anio": 2025,
   "mes": 8,
   "casos": 6,
   "COMUNA": "Lo Espejo"
  },
  {
   "delito": "RECEPTACIÓN",
   "CODCOM": 13116,
   "anio": 2025,
   "mes": 9,
   "casos": 3,
   "COMUNA": "Lo Espejo"
  },
  {
   "delito": "RECEPTACIÓN",
   "CODCOM": 13116,
   "anio": 2025,
   "mes": 10,
   "casos": 12,
   "COMUNA": "Lo Espejo"
  },
  {
   "delito": "RECEPTACIÓN",
   "CODCOM": 13116,
   "anio": 2025,
   "mes": 11,
   "casos": 2,
   "COMUNA": "Lo Espejo"
  },
  {
   "delito": "ROBOS CON VIOLENCIA E INTIMIDACIÓN",
   "CODCOM": 13116,
   "anio": 2024,
   "mes": 1,
   "casos": 92,
   "COMUNA": "Lo Espejo"
  },
  {
   "delito": "ROBOS CON VIOLENCIA E INTIMIDACIÓN",
   "CODCOM": 13116,
   "anio": 2024,
   "mes": 2,
   "casos": 67,
   "COMUNA": "Lo Espejo"
  },
  {
   "delito": "ROBOS CON VIOLENCIA E INTIMIDACIÓN",
   "CODCOM": 13116,
   "anio": 2024,
   "mes": 3,
   "casos": 52,
   "COMUNA": "Lo Espejo"
  },
  {
   "delito": "ROBOS CON VIOLENCIA E INTIMIDACIÓN",
   "CODCOM": 13116,
   "anio": 2024,
   "mes": 4,
   "casos": 56,
   "COMUNA": "Lo Espejo"
  },
  {
   "delito": "ROBOS CON VIOLENCIA E INTIMIDACIÓN",
   "CODCOM": 13116,
   "anio": 2024,
   "mes": 5,
   "casos": 49,
   "COMUNA": "Lo Espejo"
  },
  {
   "delito": "ROBOS CON VIOLENCIA E INTIMIDACIÓN",
   "CODCOM": 13116,
   "anio": 2024,
   "mes": 6,
   "casos": 48,
   "COMUNA": "Lo Espejo"
  },
  {
   "delito": "ROBOS CON VIOLENCIA E INTIMIDACIÓN",
   "CODCOM": 13116,
   "anio": 2024,
   "mes": 7,
   "casos": 53,
   "COMUNA": "Lo Espejo"
  },
  {
   "delito": "ROBOS CON VIOLENCIA E INTIMIDACIÓN",
   "CODCOM": 13116,
   "anio": 2024,
   "mes": 8,
   "casos": 31,
   "COMUNA": "Lo Espejo"
  },
  {
   "delito": "ROBOS CON VIOLENCIA E INTIMIDACIÓN",
   "CODCOM": 13116,
   "anio": 2024,
   "mes": 9,
   "casos": 64,
   "COMUNA": "Lo Espejo"
  },
  {
   "delito": "ROBOS CON VIOLENCIA E INTIMIDACIÓN",
   "CODCOM": 13116,
   "anio": 2024,
   "mes": 10,
   "casos": 54,
   "COMUNA": "Lo Espejo"
  },
  {
   "delito": "ROBOS CON VIOLENCIA E INTIMIDACIÓN",
   "CODCOM": 13116,
   "anio": 2024,
   "mes": 11,
   "casos": 52,
   "COMUNA": "Lo Espejo"
  },
  {
   "delito": "ROBOS CON VIOLENCIA E INTIMIDACIÓN",
   "CODCOM": 13116,
   "anio": 2024,
   "mes": 12,
   "casos": 61,
   "COMUNA": "Lo Espejo"
  },
  {
   "delito": "ROBOS CON VIOLENCIA E INTIMIDACIÓN",
   "CODCOM": 13116,
   "anio": 2025,
   "mes": 1,
   "casos": 50,
   "COMUNA": "Lo Espejo"
  },
  {
   "delito": "ROBOS CON VIOLENCIA E INTIMIDACIÓN",
   "CODCOM": 13116,
   "anio": 2025,
   "mes": 2,
   "casos": 37,
   "COMUNA": "Lo Espejo"
  },
  {
   "delito": "ROBOS CON VIOLENCIA E INTIMIDACIÓN",
   "CODCOM": 13116,
   "anio": 2025,
   "mes": 3,
   "casos": 55,
   "COMUNA": "Lo Espejo"
  },
  {
   "delito": "ROBOS CON VIOLENCIA E INTIMIDACIÓN",
   "CODCOM": 13116,
   "anio": 2025,
   "mes": 4,
   "casos": 36,
   "COMUNA": "Lo Espejo"
  },
  {
   "delito": "ROBOS CON VIOLENCIA E INTIMIDACIÓN",
   "CODCOM": 13116,
   "anio": 2025,
   "mes": 5,
   "casos": 46,
   "COMUNA": "Lo Espejo"
  },
  {
   "delito": "ROBOS CON VIOLENCIA E INTIMIDACIÓN",
   "CODCOM": 13116,
   "anio": 2025,
   "mes": 6,
   "casos": 60,
   "COMUNA": "Lo Espejo"
  },
  {
   "delito": "ROBOS CON VIOLENCIA E INTIMIDACIÓN",
   "CODCOM": 13116,
   "anio": 2025,
   "mes": 7,
   "casos": 45,
   "COMUNA": "Lo Espejo"
  },
  {
   "delito": "ROBOS CON VIOLENCIA E INTIMIDACIÓN",
   "CODCOM": 13116,
   "anio": 2025,
   "mes": 8,
   "casos": 54,
   "COMUNA": "Lo Espejo"
  },
  {
   "delito": "ROBOS CON VIOLENCIA E INTIMIDACIÓN",
   "CODCOM": 13116,
   "anio": 2025,
   "mes": 9,
   "casos": 59,
   "COMUNA": "Lo Espejo"
  },
  {
   "delito": "ROBOS CON VIOLENCIA E INTIMIDACIÓN",
   "CODCOM": 13116,
   "anio": 2025,
   "mes": 10,
   "casos": 44,
   "COMUNA": "Lo Espejo"
  },
  {
   "delito": "ROBOS CON VIOLENCIA E INTIMIDACIÓN",
   "CODCOM": 13116,
   "anio": 2025,
   "mes": 11,
   "casos": 7,
   "COMUNA": "Lo Espejo"
  },
  {
   "delito": "ROBOS DE VEHÍCULOS Y SUS ACCESORIOS",
   "CODCOM": 13116,
   "anio": 2024,
   "mes": 1,
   "casos": 33,
   "COMUNA": "Lo Espejo"
  },
  {
   "delito": "ROBOS DE VEHÍCULOS Y SUS ACCESORIOS",
   "CODCOM": 13116,
   "anio": 2024,
   "mes": 2,
   "casos": 34,
   "COMUNA": "Lo Espejo"
  },
  {
   "delito": "ROBOS DE VEHÍCULOS Y SUS ACCESORIOS",
   "CODCOM": 13116,
   "anio": 2024,
   "mes": 3,
   "casos": 22,
   "COMUNA": "Lo Espejo"
  },
  {
   "delito": "ROBOS DE VEHÍCULOS Y SUS ACCESORIOS",
   "CODCOM": 13116,
   "anio": 2024,
   "mes": 4,
   "casos": 26,
   "COMUNA": "Lo Espejo"
  },
  {
   "delito": "ROBOS DE VEHÍCULOS Y SUS ACCESORIOS",
   "CODCOM": 13116,
   "anio": 2024,
   "mes": 5,
   "casos": 31,
   "COMUNA": "Lo Espejo"
  },
  {
   "delito": "ROBOS DE VEHÍCULOS Y SUS ACCESORIOS",
   "CODCOM": 13116,
   "anio": 2024,
   "mes": 6,
   "casos": 20,
   "COMUNA": "Lo Espejo"
  },
  {
   "delito": "ROBOS DE VEHÍCULOS Y SUS ACCESORIOS",
   "CODCOM": 13116,
   "anio": 2024,
   "mes": 7,
   "casos": 19,
   "COMUNA": "Lo Espejo"
  },
  {
   "delito": "ROBOS DE VEHÍCULOS Y SUS ACCESORIOS",
   "CODCOM": 13116,
   "anio": 2024,
   "mes": 8,
   "casos": 23,
   "COMUNA": "Lo Espejo"
  },
  {
   "delito": "ROBOS DE VEHÍCULOS Y SUS ACCESORIOS",
   "CODCOM": 13116,
   "anio": 2024,
   "mes": 9,
   "casos": 17,
   "COMUNA": "Lo Espejo"
  },
  {
   "delito": "ROBOS DE VEHÍCULOS Y SUS ACCESORIOS",
   "CODCOM": 13116,
   "anio": 2024,
   "mes": 10,
   "casos": 26,
   "COMUNA": "Lo Espejo"
  },
  {
   "delito": "ROBOS DE VEHÍCULOS Y SUS ACCESORIOS",
   "CODCOM": 13116,
   "anio": 2024,
   "mes": 11,
   "casos": 25,
   "COMUNA": "Lo Espejo"
  },
  {
   "delito": "ROBOS DE VEHÍCULOS Y SUS ACCESORIOS",
   "CODCOM": 13116,
   "anio": 2024,
   "mes": 12,
   "casos": 30,
   "COMUNA": "Lo Espejo"
  },
  {
   "delito": "ROBOS DE VEHÍCULOS Y SUS ACCESORIOS",
   "CODCOM": 13116,
   "anio": 2025,
   "mes": 1,
   "casos": 26,
   "COMUNA": "Lo Espejo"
  },
  {
   "delito": "ROBOS DE VEHÍCULOS Y SUS ACCESORIOS",
   "CODCOM": 13116,
   "anio": 2025,
   "mes": 2,
   "casos": 23,
   "COMUNA": "Lo Espejo"
  },
  {
   "delito": "ROBOS DE VEHÍCULOS Y SUS ACCESORIOS",
   "CODCOM": 13116,
   "anio": 2025,
   "mes": 3,
   "casos": 36,
   "COMUNA": "Lo Espejo"
  },
  {
   "delito": "ROBOS DE VEHÍCULOS Y SUS ACCESORIOS",
   "CODCOM": 13116,
   "anio": 2025,
   "mes": 4,
   "casos": 21,
   "COMUNA": "Lo Espejo"
  },
  {
   "delito": "ROBOS DE VEHÍCULOS Y SUS ACCESORIOS",
   "CODCOM": 13116,
   "anio": 2025,
   "mes": 5,
   "casos": 23,
   "COMUNA": "Lo Espejo"
  },
  {
   "delito": "ROBOS DE VEHÍCULOS Y SUS ACCESORIOS",
   "CODCOM": 13116,
   "anio": 2025,
   "mes": 6,
   "casos": 35,
   "COMUNA": "Lo Espejo"
  },
  {
   "delito": "ROBOS DE VEHÍCULOS Y SUS ACCESORIOS",
   "CODCOM": 13116,
   "anio": 2025,
   "mes": 7,
   "casos": 24,
   "COMUNA": "Lo Espejo"
  },
  {
   "delito": "ROBOS DE VEHÍCULOS Y SUS ACCESORIOS",
   "CODCOM": 13116,
   "anio": 2025,
   "mes": 8,
   "casos": 37,
   "COMUNA": "Lo Espejo"
  },
  {
   "delito": "ROBOS DE VEHÍCULOS Y SUS ACCESORIOS",
   "CODCOM": 13116,
   "anio": 2025,
   "mes": 9,
   "casos": 35,
   "COMUNA": "Lo Espejo"
  },
  {
   "delito": "ROBOS DE VEHÍCULOS Y SUS ACCESORIOS",
   "CODCOM": 13116,
   "anio": 2025,
   "mes": 10,
   "casos": 20,
   "COMUNA": "Lo Espejo"
  },
  {
   "delito": "ROBOS DE VEHÍCULOS Y SUS ACCESORIOS",
   "CODCOM": 13116,
   "anio": 2025,
   "mes": 11,
   "casos": 8,
   "COMUNA": "Lo Espejo"
  },
  {
   "delito": "ROBOS EN LUGARES HABITADOS Y NO HABITADOS",
   "CODCOM": 13116,
   "anio": 2024,
   "mes": 1,
   "casos": 14,
   "COMUNA": "Lo Espejo"
  },
  {
   "delito": "ROBOS EN LUGARES HABITADOS Y NO HABITADOS",
   "CODCOM": 13116,
   "anio": 2024,
   "mes": 2,
   "casos": 8,
   "COMUNA": "Lo Espejo"
  },
  {
   "delito": "ROBOS EN LUGARES HABITADOS Y NO HABITADOS",
   "CODCOM": 13116,
   "anio": 2024,
   "mes": 3,
   "casos": 14,
   "COMUNA": "Lo Espejo"
  },
  {
   "delito": "ROBOS EN LUGARES HABITADOS Y NO HABITADOS",
   "CODCOM": 13116,
   "anio": 2024,
   "mes": 4,
   "casos": 12,
   "COMUNA": "Lo Espejo"
  },
  {
   "delito": "ROBOS EN LUGARES HABITADOS Y NO HABITADOS",
   "CODCOM": 13116,
   "anio": 2024,
   "mes": 5,
   "casos": 8,
   "COMUNA": "Lo Espejo"
  },
  {
   "delito": "ROBOS EN LUGARES HABITADOS Y NO HABITADOS",
   "CODCOM": 13116,
   "anio": 2024,
   "mes": 6,
   "casos": 19,
   "COMUNA": "Lo Espejo"
  },
  {
   "delito": "ROBOS EN LUGARES HABITADOS Y NO HABITADOS",
   "CODCOM": 13116,
   "anio": 2024,
   "mes": 7,
   "casos": 24,
   "COMUNA": "Lo Espejo"
  },
  {
   "delito": "ROBOS EN LUGARES HABITADOS Y NO HABITADOS",
   "CODCOM": 13116,
   "anio": 2024,
   "mes": 8,
   "casos": 11,
   "COMUNA": "Lo Espejo"
  },
  {
   "delito": "ROBOS EN LUGARES HABITADOS Y NO HABITADOS",
   "CODCOM": 13116,
   "anio": 2024,
   "mes": 9,
   "casos": 18,
   "COMUNA": "Lo Espejo"
  },
  {
   "delito": "ROBOS EN LUGARES HABITADOS Y NO HABITADOS",
   "CODCOM": 13116,
   "anio": 2024,
   "mes": 10,
   "casos": 23,
   "COMUNA": "Lo Espejo"
  },
  {
   "delito": "ROBOS EN LUGARES HABITADOS Y NO HABITADOS",
   "CODCOM": 13116,
   "anio": 2024,
   "mes": 11,
   "casos": 30,
   "COMUNA": "Lo Espejo"
  },
  {
   "delito": "ROBOS EN LUGARES HABITADOS Y NO HABITADOS",
   "CODCOM": 13116,
   "anio": 2024,
   "mes": 12,
   "casos": 15,
   "COMUNA": "Lo Espejo"
  },
  {
   "delito": "ROBOS EN LUGARES HABITADOS Y NO HABITADOS",
   "CODCOM": 13116,
   "anio": 2025,
   "mes": 1,
   "casos": 12,
   "COMUNA": "Lo Espejo"
  },
  {
   "delito": "ROBOS EN LUGARES HABITADOS Y NO HABITADOS",
   "CODCOM": 13116,
   "anio": 2025,
   "mes": 2,
   "casos": 11,
   "COMUNA": "Lo Espejo"
  },
  {
   "delito": "ROBOS EN LUGARES HABITADOS Y NO HABITADOS",
   "CODCOM": 13116,
   "anio": 2025,
   "mes": 3,
   "casos": 16,
   "COMUNA": "Lo Espejo"
  },
  {
   "delito": "ROBOS EN LUGARES HABITADOS Y NO HABITADOS",
   "CODCOM": 13116,
   "anio": 2025,
   "mes": 4,
   "casos": 12,
   "COMUNA": "Lo Espejo"
  },
  {
   "delito": "ROBOS EN LUGARES HABITADOS Y NO HABITADOS",
   "CODCOM": 13116,
   "anio": 2025,
   "mes": 5,
   "casos": 21,
   "COMUNA": "Lo Espejo"
  },
  {
   "delito": "ROBOS EN LUGARES HABITADOS Y NO HABITADOS",
   "CODCOM": 13116,
   "anio": 2025,
   "mes": 6,
   "casos": 21,
   "COMUNA": "Lo Espejo"
  },
  {
   "delito": "ROBOS EN LUGARES HABITADOS Y NO HABITADOS",
   "CODCOM": 13116,
   "anio": 2025,
   "mes": 7,
   "casos": 14,
   "COMUNA": "Lo Espejo"
  },
  {
   "delito": "ROBOS EN LUGARES HABITADOS Y NO HABITADOS",
   "CODCOM": 13116,
   "anio": 2025,
   "mes": 8,
   "casos": 15,
   "COMUNA": "Lo Espejo"
  },
  {
   "delito": "ROBOS EN LUGARES HABITADOS Y NO HABITADOS",
   "CODCOM": 13116,
   "anio": 2025,
   "mes": 9,
   "casos": 16,
   "COMUNA": "Lo Espejo"
  },
  {
   "delito": "ROBOS EN LUGARES HABITADOS Y NO HABITADOS",
   "CODCOM": 13116,
   "anio": 2025,
   "mes": 10,
   "casos": 12,
   "COMUNA": "Lo Espejo"
  },
  {
   "delito": "ROBOS EN LUGARES HABITADOS Y NO HABITADOS",
   "CODCOM": 13116,
   "anio": 2025,
   "mes": 11,
   "casos": 3,
   "COMUNA": "Lo Espejo"
  },
  {
   "delito": "ROBOS POR SORPRESA",
   "CODCOM": 13116,
   "anio": 2024,
   "mes": 1,
   "casos": 28,
   "COMUNA": "Lo Espejo"
  },
  {
   "delito": "ROBOS POR SORPRESA",
   "CODCOM": 13116,
   "anio": 2024,
   "mes": 2,
   "casos": 20,
   "COMUNA": "Lo Espejo"
  },
  {
   "delito": "ROBOS POR SORPRESA",
   "CODCOM": 13116,
   "anio": 2024,
   "mes": 3,
   "casos": 25,
   "COMUNA": "Lo Espejo"
  },
  {
   "delito": "ROBOS POR SORPRESA",
   "CODCOM": 13116,
   "anio": 2024,
   "mes": 4,
   "casos": 29,
   "COMUNA": "Lo Espejo"
  },
  {
   "delito": "ROBOS POR SORPRESA",
   "CODCOM": 13116,
   "anio": 2024,
   "mes": 5,
   "casos": 27,
   "COMUNA": "Lo Espejo"
  },
  {
   "delito": "ROBOS POR SORPRESA",
   "CODCOM": 13116,
   "anio": 2024,
   "mes": 6,
   "casos": 23,
   "COMUNA": "Lo Espejo"
  },
  {
   "delito": "ROBOS POR SORPRESA",
   "CODCOM": 13116,
   "anio": 2024,
   "mes": 7,
   "casos": 23,
   "COMUNA": "Lo Espejo"
  },
  {
   "delito": "ROBOS POR SORPRESA",
   "CODCOM": 13116,
   "anio": 2024,
   "mes": 8,
   "casos": 25,
   "COMUNA": "Lo Espejo"
  },
  {
   "delito": "ROBOS POR SORPRESA",
   "CODCOM": 13116,
   "anio": 2024,
   "mes": 9,
   "casos": 26,
   "COMUNA": "Lo Espejo"
  },
  {
   "delito": "ROBOS POR SORPRESA",
   "CODCOM": 13116,
   "anio": 2024,
   "mes": 10,
   "casos": 20,
   "COMUNA": "Lo Espejo"
  },
  {
   "delito": "ROBOS POR SORPRESA",
   "CODCOM": 13116,
   "anio": 2024,
   "mes": 11,
   "casos": 26,
   "COMUNA": "Lo Espejo"
  },
  {
   "delito": "ROBOS POR SORPRESA",
   "CODCOM": 13116,
   "anio": 2024,
   "mes": 12,
   "casos": 15,
   "COMUNA": "Lo Espejo"
  },
  {
   "delito": "ROBOS POR SORPRESA",
   "CODCOM": 13116,
   "anio": 2025,
   "mes": 1,
   "casos": 27,
   "COMUNA": "Lo Espejo"
  },
  {
   "delito": "ROBOS POR SORPRESA",
   "CODCOM": 13116,
   "anio": 2025,
   "mes": 2,
   "casos": 16,
   "COMUNA": "Lo Espejo"
  },
  {
   "delito": "ROBOS POR SORPRESA",
   "CODCOM": 13116,
   "anio": 2025,
   "mes": 3,
   "casos": 27,
   "COMUNA": "Lo Espejo"
  },
  {
   "delito": "ROBOS POR SORPRESA",
   "CODCOM": 13116,
   "anio": 2025,
   "mes": 4,
   "casos": 12,
   "COMUNA": "Lo Espejo"
  },
  {
   "delito": "ROBOS POR SORPRESA",
   "CODCOM": 13116,
   "anio": 2025,
   "mes": 5,
   "casos": 8,
   "COMUNA": "Lo Espejo"
  },
  {
   "delito": "ROBOS POR SORPRESA",
   "CODCOM": 13116,
   "anio": 2025,
   "mes": 6,
   "casos": 19,
   "COMUNA": "Lo Espejo"
  },
  {
   "delito": "ROBOS POR SORPRESA",
   "CODCOM": 13116,
   "anio": 2025,
   "mes": 7,
   "casos": 22,
   "COMUNA": "Lo Espejo"
  },
  {
   "delito": "ROBOS POR SORPRESA",
   "CODCOM": 13116,
   "anio": 2025,
   "mes": 8,
   "casos": 20,
   "COMUNA": "Lo Espejo"
  },
  {
   "delito": "ROBOS POR SORPRESA",
   "CODCOM": 13116,
   "anio": 2025,
   "mes": 9,
   "casos": 27,
   "COMUNA": "Lo Espejo"
  },
  {
   "delito": "ROBOS POR SORPRESA",
   "CODCOM": 13116,
   "anio": 2025,
   "mes": 10,
   "casos": 15,
   "COMUNA": "Lo Espejo"
  },
  {
   "delito": "ROBOS POR SORPRESA",
   "CODCOM": 13116,
   "anio": 2025,
   "mes": 11,
   "casos": 6,
   "COMUNA": "Lo Espejo"
  },
  {
   "delito": "VIOLACIONES Y DELITOS SEXUALES",
   "CODCOM": 13116,
   "anio": 2024,
   "mes": 1,
   "casos": 5,
   "COMUNA": "Lo Espejo"
  },
  {
   "delito": "VIOLACIONES Y DELITOS SEXUALES",
   "CODCOM": 13116,
   "anio": 2024,
   "mes": 2,
   "casos": 1,
   "COMUNA": "Lo Espejo"
  },
  {
   "delito": "VIOLACIONES Y DELITOS SEXUALES",
   "CODCOM": 13116,
   "anio": 2024,
   "mes": 3,
   "casos": 6,
   "COMUNA": "Lo Espejo"
  },
  {
   "delito": "VIOLACIONES Y DELITOS SEXUALES",
   "CODCOM": 13116,
   "anio": 2024,
   "mes": 4,
   "casos": 12,
   "COMUNA": "Lo Espejo"
  },
  {
   "delito": "VIOLACIONES Y DELITOS SEXUALES",
   "CODCOM": 13116,
   "anio": 2024,
   "mes": 5,
   "casos": 5,
   "COMUNA": "Lo Espejo"
  },
  {
   "delito": "VIOLACIONES Y DELITOS SEXUALES",
   "CODCOM": 13116,
   "anio": 2024,
   "mes": 6,
   "casos": 3,
   "COMUNA": "Lo Espejo"
  },
  {
   "delito": "VIOLACIONES Y DELITOS SEXUALES",
   "CODCOM": 13116,
   "anio": 2024,
   "mes": 7,
   "casos": 3,
   "COMUNA": "Lo Espejo"
  },
  {
   "delito": "VIOLACIONES Y DELITOS SEXUALES",
   "CODCOM": 13116,
   "anio": 2024,
   "mes": 8,
   "casos": 6,
   "COMUNA": "Lo Espejo"
  },
  {
   "delito": "VIOLACIONES Y DELITOS SEXUALES",
   "CODCOM": 13116,
   "anio": 2024,
   "mes": 9,
   "casos": 9,
   "COMUNA": "Lo Espejo"
  },
  {
   "delito": "VIOLACIONES Y DELITOS SEXUALES",
   "CODCOM": 13116,
   "anio": 2024,
   "mes": 10,
   "casos": 8,
   "COMUNA": "Lo Espejo"
  },
  {
   "delito": "VIOLACIONES Y DELITOS SEXUALES",
   "CODCOM": 13116,
   "anio": 2024,
   "mes": 11,
   "casos": 3,
   "COMUNA": "Lo Espejo"
  },
  {
   "delito": "VIOLACIONES Y DELITOS SEXUALES",
   "CODCOM": 13116,
   "anio": 2024,
   "mes": 12,
   "casos": 3,
   "COMUNA": "Lo Espejo"
  },
  {
   "delito": "VIOLACIONES Y DELITOS SEXUALES",
   "CODCOM": 13116,
   "anio": 2025,
   "mes": 1,
   "casos": 4,
   "COMUNA": "Lo Espejo"
  },
  {
   "delito": "VIOLACIONES Y DELITOS SEXUALES",
   "CODCOM": 13116,
   "anio": 2025,
   "mes": 2,
   "casos": 3,
   "COMUNA": "Lo Espejo"
  },
  {
   "delito": "VIOLACIONES Y DELITOS SEXUALES",
   "CODCOM": 13116,
   "anio": 2025,
   "mes": 3,
   "casos": 5,
   "COMUNA": "Lo Espejo"
  },
  {
   "delito": "VIOLACIONES Y DELITOS SEXUALES",
   "CODCOM": 13116,
   "anio": 2025,
   "mes": 4,
   "casos": 2,
   "COMUNA": "Lo Espejo"
  },
  {
   "delito": "VIOLACIONES Y DELITOS SEXUALES",
   "CODCOM": 13116,
   "anio": 2025,
   "mes": 5,
   "casos": 7,
   "COMUNA": "Lo Espejo"
  },
  {
   "delito": "VIOLACIONES Y DELITOS SEXUALES",
   "CODCOM": 13116,
   "anio": 2025,
   "mes": 6,
   "casos": 4,
   "COMUNA": "Lo Espejo"
  },
  {
   "delito": "VIOLACIONES Y DELITOS SEXUALES",
   "CODCOM": 13116,
   "anio": 2025,
   "mes": 7,
   "casos": 6,
   "COMUNA": "Lo Espejo"
  },
  {
   "delito": "VIOLACIONES Y DELITOS SEXUALES",
   "CODCOM": 13116,
   "anio": 2025,
   "mes": 8,
   "casos": 2,
   "COMUNA": "Lo Espejo"
  },
  {
   "delito": "VIOLACIONES Y DELITOS SEXUALES",
   "CODCOM": 13116,
   "anio": 2025,
   "mes": 9,
   "casos": 5,
   "COMUNA": "Lo Espejo"
  },
  {
   "delito": "VIOLACIONES Y DELITOS SEXUALES",
   "CODCOM": 13116,
   "anio": 2025,
   "mes": 10,
   "casos": 1,
   "COMUNA": "Lo Espejo"
  },
  {
   "delito": "VIOLACIONES Y DELITOS SEXUALES",
   "CODCOM": 13116,
   "anio": 2025,
   "mes": 11,
   "casos": 0,
   "COMUNA": "Lo Espejo"
  }
 ],
 "info": [
  {
   "informacion": "Casos",
   "CODCOM": 13116,
   "delito": "AMENAZAS CON ARMAS",
   "2023": 16,
   "2024": 24,
   "2025": 16,
   "COMUNA": "Lo Espejo"
  },
  {
   "informacion": "Casos",
   "CODCOM": 13116,
   "delito": "AMENAZAS Y RIÑAS",
   "2023": 721,
   "2024": 784,
   "2025": 828,
   "COMUNA": "Lo Espejo"
  },
  {
   "informacion": "Casos",
   "CODCOM": 13116,
   "delito": "CONSUMO DE ALCOHOL Y DE DROGAS EN LA VÍA PÚBLICA",
   "2023": 254,
   "2024": 213,
   "2025": 116,
   "COMUNA": "Lo Espejo"
  },
  {
   "informacion": "Casos",
   "CODCOM": 13116,
   "delito": "DAÑOS",
   "2023": 361,
   "2024": 377,
   "2025": 365,
   "COMUNA": "Lo Espejo"
  },
  {
   "informacion": "Casos",
   "CODCOM": 13116,
   "delito": "DELITOS EN CONTEXTO DE VIOLENCIA INTRAFAMILIAR",
   "2023": 461,
   "2024": 519,
   "2025": 486,
   "COMUNA": "Lo Espejo"
  },
  {
   "informacion": "Casos",
   "CODCOM": 13116,
   "delito": "HOMICIDIOS Y FEMICIDIOS",
   "2023": 11,
   "2024": 3,
   "2025": 10,
   "COMUNA": "Lo Espejo"
  },
  {
   "informacion": "Casos",
   "CODCOM": 13116,
   "delito": "HURTOS",
   "2023": 133,
   "2024": 145,
   "2025": 153,
   "COMUNA": "Lo Espejo"
  },
  {
   "informacion": "Casos",
   "CODCOM": 13116,
   "delito": "INCIVILIDADES",
   "2023": 47,
   "2024": 53,
   "2025": 48,
   "COMUNA": "Lo Espejo"
  },
  {
   "informacion": "Casos",
   "CODCOM": 13116,
   "delito": "LESIONES GRAVES",
   "2023": 58,
   "2024": 55,
   "2025": 35,
   "COMUNA": "Lo Espejo"
  },
  {
   "informacion": "Casos",
   "CODCOM": 13116,
   "delito": "LESIONES LEVES",
   "2023": 234,
   "2024": 267,
   "2025": 258,
   "COMUNA": "Lo Espejo"
  },
  {
   "informacion": "Casos",
   "CODCOM": 13116,
   "delito": "LESIONES MENOS GRAVES",
   "2023": 50,
   "2024": 57,
   "2025": 55,
   "COMUNA": "Lo Espejo"
  },
  {
   "informacion": "Casos",
   "CODCOM": 13116,
   "delito": "LEY DE CONTROL DE ARMAS",
   "2023": 109,
   "2024": 155,
   "2025": 239,
   "COMUNA": "Lo Espejo"
  },
  {
   "informacion": "Casos",
   "CODCOM": 13116,
   "delito": "LEY DE DROGAS",
   "2023": 67,
   "2024": 53,
   "2025": 98,
   "COMUNA": "Lo Espejo"
  },
  {
   "informacion": "Casos",
   "CODCOM": 13116,
   "delito": "OTROS DESÓRDENES PÚBLICOS",
   "2023": 7,
   "2024": 7,
   "2025": 4,
   "COMUNA": "Lo Espejo"
  },
  {
   "informacion": "Casos",
   "CODCOM": 13116,
   "delito": "OTROS ROBOS CON FUERZA EN LAS COSAS",
   "2023": 29,
   "2024": 18,
   "2025": 34,
   "COMUNA": "Lo Espejo"
  },
  {
   "informacion": "Casos",
   "CODCOM": 13116,
   "delito": "RECEPTACIÓN",
   "2023": 51,
   "2024": 43,
   "2025": 69,
   "COMUNA": "Lo Espejo"
  },
  {
   "informacion": "Casos",
   "CODCOM": 13116,
   "delito": "ROBOS CON VIOLENCIA E INTIMIDACIÓN",
   "2023": 708,
   "2024": 579,
   "2025": 493,
   "COMUNA": "Lo Espejo"
  },
  {
   "informacion": "Casos",
   "CODCOM": 13116,
   "delito": "ROBOS DE VEHÍCULOS Y SUS ACCESORIOS",
   "2023": 307,
   "2024": 256,
   "2025": 288,
   "COMUNA": "Lo Espejo"
  },
  {
   "informacion": "Casos",
   "CODCOM": 13116,
   "delito": "ROBOS EN LUGARES HABITADOS Y NO HABITADOS",
   "2023": 135,
   "2024": 159,
   "2025": 153,
   "COMUNA": "Lo Espejo"
  },
  {
   "informacion": "Casos",
   "CODCOM": 13116,
   "delito": "ROBOS POR SORPRESA",
   "2023": 233,
   "2024": 248,
   "2025": 199,
   "COMUNA": "Lo Espejo"
  },
  {
   "informacion": "Casos",
   "CODCOM": 13116,
   "delito": "VIOLACIONES Y DELITOS SEXUALES",
   "2023": 53,
   "2024": 59,
   "2025": 39,
   "COMUNA": "Lo Espejo"
  }
 ],
 "meta": {
  "semana_id": "SEMANA 45/2025 (del 03/11/2025 al 09/11/2025)",
  "region": "Metropolitana"
 }
}