{
 "resumen": [
  {
   "delito": "AMENAZAS CON ARMAS",
   "CODCOM": 13122,
   "2025": 11.0,
   "2026": 6.0,
   "variacion": -45.0,
   "situación": "Disminución de Casos",
   "COMUNA": "Peñalolén"
  },
  {
   "delito": "AMENAZAS Y RIÑAS",
   "CODCOM": 13122,
   "2025": 211.0,
   "2026": 172.0,
   "variacion": -18.0,
   "situación": "Disminución de Casos",
   "COMUNA": "Peñalolén"
  },
  {
   "delito": "CONSUMO DE ALCOHOL Y DE DROGAS EN LA VÍA PÚBLICA",
   "CODCOM": 13122,
   "2025": 12.0,
   "2026": 11.0,
   "variacion": -8.0,
   "situación": "Disminución de Casos",
   "COMUNA": "Peñalolén"
  },
  {
   "delito": "DAÑOS",
   "CODCOM": 13122,
   "2025": 125.0,
   "2026": 111.0,
   "variacion": -11.0,
   "situación": "Disminución de Casos",
   "COMUNA": "Peñalolén"
  },
  {
   "delito": "DELITOS EN CONTEXTO DE VIOLENCIA INTRAFAMILIAR",
   "CODCOM": 13122,
   "2025": 229.0,
   "2026": 186.0,
   "variacion": -19.0,
   "situación": "Disminución de Casos",
   "COMUNA": "Peñalolén"
  },
  {
   "delito": "HOMICIDIOS Y FEMICIDIOS",
   "CODCOM": 13122,
   "2025": 0.0,
   "2026": 0.0,
   "variacion": 0.0,
   "situación": "Sin variación de Casos",
   "COMUNA": "Peñalolén"
  },
  {
   "delito": "HURTOS",
   "CODCOM": 13122,
   "2025": 87.0,
   "2026": 73.0,
   "variacion": -16.0,
   "situación": "Disminución de Casos",
   "COMUNA": "Peñalolén"
  },
  {
   "delito": "INCIVILIDADES",
   "CODCOM": 13122,
   "2025": 10.0,
   "2026": 11.0,
   "variacion": 10.0,
   "situación": "Aumento de Casos",
   "COMUNA": "Peñalolén"
  },
  {
   "delito": "LESIONES GRAVES",
   "CODCOM": 13122,
   "2025": 4.0,
   "2026": 4.0,
   "variacion": 0.0,
   "situación": "Sin variación de Casos",
   "COMUNA": "Peñalolén"
  },
  {
   "delito": "LESIONES LEVES",
   "CODCOM": 13122,
   "2025": 68.0,
   "2026": 63.0,
   "variacion": -7.0,
   "situación": "Disminución de Casos",
   "COMUNA": "Peñalolén"
  },
  {
   "delito": "LESIONES MENOS GRAVES",
   "CODCOM": 13122,
   "2025": 13.0,
   "2026": 15.0,
   "variacion": 15.0,
   "situación": "Aumento de Casos",
   "COMUNA": "Peñalolén"
  },
  {
   "delito": "LEY DE CONTROL DE ARMAS",
   "CODCOM": 13122,
   "2025": 13.0,
   "2026": 24.0,
   "variacion": 85.0,
   "situación": "Aumento de Casos",
   "COMUNA": "Peñalolén"
  },
  {
   "delito": "LEY DE DROGAS",
   "CODCOM": 13122,
   "2025": 6.0,
   "2026": 13.0,
   "variacion": 117.0,
   "situación": "Aumento de Casos",
   "COMUNA": "Peñalolén"
  },
  {
   "delito": "OTROS DESÓRDENES PÚBLICOS",
   "CODCOM": 13122,
   "2025": 1.0,
   "2026": 0.0,
   "variacion": -100.0,
   "situación": "Disminución de Casos",
   "COMUNA": "Peñalolén"
  },
  {
   "delito": "OTROS ROBOS CON FUERZA EN LAS COSAS",
   "CODCOM": 13122,
   "2025": 4.0,
   "2026": 3.0,
   "variacion": -25.0,
   "situación": "Disminución de Casos",
   "COMUNA": "Peñalolén"
  },
  {
   "delito": "RECEPTACIÓN",
   "CODCOM": 13122,
   "2025": 12.0,
   "2026": 11.0,
   "variacion": -8.0,
   "situación": "Disminución de Casos",
   "COMUNA": "Peñalolén"
  },
  {
   "delito": "ROBOS CON VIOLENCIA E INTIMIDACIÓN",
   "CODCOM": 13122,
   "2025": 110.0,
   "2026": 67.0,
   "variacion": -39.0,
   "situación": "Disminución de Casos",
   "COMUNA": "Peñalolén"
  },
  {
   "delito": "ROBOS DE VEHÍCULOS Y SUS ACCESORIOS",
   "CODCOM": 13122,
   "2025": 134.0,
   "2026": 83.0,
   "variacion": -38.0,
   "situación": "Disminución de Casos",
   "COMUNA": "Peñalolén"
  },
  {
   "delito": "ROBOS EN LUGARES HABITADOS Y NO HABITADOS",
   "CODCOM": 13122,
   "2025": 86.0,
   "2026": 43.0,
   "variacion": -50.0,
   "situación": "Disminución de Casos",
   "COMUNA": "Peñalolén"
  },
  {
   "delito": "ROBOS POR SORPRESA",
   "CODCOM": 13122,
   "2025": 40.0,
   "2026": 44.0,
   "variacion": 10.0,
   "situación": "Aumento de Casos",
   "COMUNA": "Peñalolén"
  },
  {
   "delito": "VIOLACIONES Y DELITOS SEXUALES",
   "CODCOM": 13122,
   "2025": 15.0,
   "2026": 13.0,
   "variacion": -13.0,
   "situación": "Disminución de Casos",
   "COMUNA": "Peñalolén"
  }
 ],
 "mensual": [
  {
   "delito": "AMENAZAS CON ARMAS",
   "CODCOM": 13122,
   "anio": 2025,
   "mes": 1,
   "casos": 9.0,
   "COMUNA": "Peñalolén"
  },
  {
   "delito": "AMENAZAS CON ARMAS",
   "CODCOM": 13122,
   "anio": 2025,
   "mes": 2,
   "casos": 4.0,
   "COMUNA": "Peñalolén"
  },
  {
   "delito": "AMENAZAS CON ARMAS",
   "CODCOM": 13122,
   "anio": 2025,
   "mes": 3,
   "casos": 2.0,
   "COMUNA": "Peñalolén"
  },
  {
   "delito": "AMENAZAS CON ARMAS",
   "CODCOM": 13122,
   "anio": 2025,
   "mes": 4,
   "casos": 3.0,
   "COMUNA": "Peñalolén"
  },
  {
   "delito": "AMENAZAS CON ARMAS",
   "CODCOM": 13122,
   "anio": 2025,
   "mes": 5,
   "casos": 1.0,
   "COMUNA": "Peñalolén"
  },
  {
   "delito": "AMENAZAS CON ARMAS",
   "CODCOM": 13122,
   "anio": 2025,
   "mes": 6,
   "casos": 3.0,
   "COMUNA": "Peñalolén"
  },
  {
   "delito": "AMENAZAS CON ARMAS",
   "CODCOM": 13122,
   "anio": 2025,
   "mes": 7,
   "casos": 0.0,
   "COMUNA": "Peñalolén"
  },
  {
   "delito": "AMENAZAS CON ARMAS",
   "CODCOM": 13122,
   "anio": 2025,
   "mes": 8,
   "casos": 2.0,
   "COMUNA": "Peñalolén"
  },
  {
   "delito": "AMENAZAS CON ARMAS",
   "CODCOM": 13122,
   "anio": 2025,
   "mes": 9,
   "casos": 3.0,
   "COMUNA": "Peñalolén"
  },
  {
   "delito": "AMENAZAS CON ARMAS",
   "CODCOM": 13122,
   "anio": 2025,
   "mes": 10,
   "casos": 2.0,
   "COMUNA": "Peñalolén"
  },
  {
   "delito": "AMENAZAS CON ARMAS",
   "CODCOM": 13122,
   "anio": 2025,
   "mes": 11,
   "casos": 0.0,
   "COMUNA": "Peñalolén"
  },
  {
   "delito": "AMENAZAS CON ARMAS",
   "CODCOM": 13122,
   "anio": 2025,
   "mes": 12,
   "casos": 4.0,
   "COMUNA": "Peñalolén"
  },
  {
   "delito": "AMENAZAS CON ARMAS",
   "CODCOM": 13122,
   "anio": 2026,
   "mes": 1,
   "casos": 6.0,
   "COMUNA": "Peñalolén"
  },
  {
   "delito": "AMENAZAS CON ARMAS",
   "CODCOM": 13122,
   "anio": 2026,
   "mes": 2,
   "casos": 0.0,
   "COMUNA": "Peñalolén"
  },
  {
   "delito": "AMENAZAS Y RIÑAS",
   "CODCOM": 13122,
   "anio": 2025,
   "mes": 1,
   "casos": 175.0,
   "COMUNA": "Peñalolén"
  },
  {
   "delito": "AMENAZAS Y RIÑAS",
   "CODCOM": 13122,
   "anio": 2025,
   "mes": 2,
   "casos": 118.0,
   "COMUNA": "Peñalolén"
  },
  {
   "delito": "AMENAZAS Y RIÑAS",
   "CODCOM": 13122,
   "anio": 2025,
   "mes": 3,
   "casos": 161.0,
   "COMUNA": "Peñalolén"
  },
  {
   "delito": "AMENAZAS Y RIÑAS",
   "CODCOM": 13122,
   "anio": 2025,
   "mes": 4,
   "casos": 118.0,
   "COMUNA": "Peñalolén"
  },
  {
   "delito": "AMENAZAS Y RIÑAS",
   "CODCOM": 13122,
   "anio": 2025,
   "mes": 5,
   "casos": 100.0,
   "COMUNA": "Peñalolén"
  },
  {
   "delito": "AMENAZAS Y RIÑAS",
   "CODCOM": 13122,
   "anio": 2025,
   "mes": 6,
   "casos": 139.0,
   "COMUNA": "Peñalolén"
  },
  {
   "delito": "AMENAZAS Y RIÑAS",
   "CODCOM": 13122,
   "anio": 2025,
   "mes": 7,
   "casos": 123.0,
   "COMUNA": "Peñalolén"
  },
  {
   "delito": "AMENAZAS Y RIÑAS",
   "CODCOM": 13122,
   "anio": 2025,
   "mes": 8,
   "casos": 110.0,
   "COMUNA": "Peñalolén"
  },
  {
   "delito": "AMENAZAS Y RIÑAS",
   "CODCOM": 13122,
   "anio": 2025,
   "mes": 9,
   "casos": 155.0,
   "COMUNA": "Peñalolén"
  },
  {
   "delito": "AMENAZAS Y RIÑAS",
   "CODCOM": 13122,
   "anio": 2025,
   "mes": 10,
   "casos": 92.0,
   "COMUNA": "Peñalolén"
  },
  {
   "delito": "AMENAZAS Y RIÑAS",
   "CODCOM": 13122,
   "anio": 2025,
   "mes": 11,
   "casos": 67.0,
   "COMUNA": "Peñalolén"
  },
  {
   "delito": "AMENAZAS Y RIÑAS",
   "CODCOM": 13122,
   "anio": 2025,
   "mes": 12,
   "casos": 140.0,
   "COMUNA": "Peñalolén"
  },
  {
   "delito": "AMENAZAS Y RIÑAS",
   "CODCOM": 13122,
   "anio": 2026,
   "mes": 1,
   "casos": 149.0,
   "COMUNA": "Peñalolén"
  },
  {
   "delito": "AMENAZAS Y RIÑAS",
   "CODCOM": 13122,
   "anio": 2026,
   "mes": 2,
   "casos": 23.0,
   "COMUNA": "Peñalolén"
  },
  {
   "delito": "CONSUMO DE ALCOHOL Y DE DROGAS EN LA VÍA PÚBLICA",
   "CODCOM": 13122,
   "anio": 2025,
   "mes": 1,
   "casos": 10.0,
   "COMUNA": "Peñalolén"
  },
  {
   "delito": "CONSUMO DE ALCOHOL Y DE DROGAS EN LA VÍA PÚBLICA",
   "CODCOM": 13122,
   "anio": 2025,
   "mes": 2,
   "casos": 11.0,
   "COMUNA": "Peñalolén"
  },
  {
   "delito": "CONSUMO DE ALCOHOL Y DE DROGAS EN LA VÍA PÚBLICA",
   "CODCOM": 13122,
   "anio": 2025,
   "mes": 3,
   "casos": 18.0,
   "COMUNA": "Peñalolén"
  },
  {
   "delito": "CONSUMO DE ALCOHOL Y DE DROGAS EN LA VÍA PÚBLICA",
   "CODCOM": 13122,
   "anio": 2025,
   "mes": 4,
   "casos": 14.0,
   "COMUNA": "Peñalolén"
  },
  {
   "delito": "CONSUMO DE ALCOHOL Y DE DROGAS EN LA VÍA PÚBLICA",
   "CODCOM": 13122,
   "anio": 2025,
   "mes": 5,
   "casos": 6.0,
   "COMUNA": "Peñalolén"
  },
  {
   "delito": "CONSUMO DE ALCOHOL Y DE DROGAS EN LA VÍA PÚBLICA",
   "CODCOM": 13122,
   "anio": 2025,
   "mes": 6,
   "casos": 10.0,
   "COMUNA": "Peñalolén"
  },
  {
   "delito": "CONSUMO DE ALCOHOL Y DE DROGAS EN LA VÍA PÚBLICA",
   "CODCOM": 13122,
   "anio": 2025,
   "mes": 7,
   "casos": 4.0,
   "COMUNA": "Peñalolén"
  },
  {
   "delito": "CONSUMO DE ALCOHOL Y DE DROGAS EN LA VÍA PÚBLICA",
   "CODCOM": 13122,
   "anio": 2025,
   "mes": 8,
   "casos": 15.0,
   "COMUNA": "Peñalolén"
  },
  {
   "delito": "CONSUMO DE ALCOHOL Y DE DROGAS EN LA VÍA PÚBLICA",
   "CODCOM": 13122,
   "anio": 2025,
   "mes": 9,
   "casos": 19.0,
   "COMUNA": "Peñalolén"
  },
  {
   "delito": "CONSUMO DE ALCOHOL Y DE DROGAS EN LA VÍA PÚBLICA",
   "CODCOM": 13122,
   "anio": 2025,
   "mes": 10,
   "casos": 6.0,
   "COMUNA": "Peñalolén"
  },
  {
   "delito": "CONSUMO DE ALCOHOL Y DE DROGAS EN LA VÍA PÚBLICA",
   "CODCOM": 13122,
   "anio": 2025,
   "mes": 11,
   "casos": 5.0,
   "COMUNA": "Peñalolén"
  },
  {
   "delito": "CONSUMO DE ALCOHOL Y DE DROGAS EN LA VÍA PÚBLICA",
   "CODCOM": 13122,
   "anio": 2025,
   "mes": 12,
   "casos": 8.0,
   "COMUNA": "Peñalolén"
  },
  {
   "delito": "CONSUMO DE ALCOHOL Y DE DROGAS EN LA VÍA PÚBLICA",
   "CODCOM": 13122,
   "anio": 2026,
   "mes": 1,
   "casos": 10.0,
   "COMUNA": "Peñalolén"
  },
  {
   "delito": "CONSUMO DE ALCOHOL Y DE DROGAS EN LA VÍA PÚBLICA",
   "CODCOM": 13122,
   "anio": 2026,
   "mes": 2,
   "casos": 1.0,
   "COMUNA": "Peñalolén"
  },
  {
   "delito": "DAÑOS",
   "CODCOM": 13122,
   "anio": 2025,
   "mes": 1,
   "casos": 108.0,
   "COMUNA": "Peñalolén"
  },
  {
   "delito": "DAÑOS",
   "CODCOM": 13122,
   "anio": 2025,
   "mes": 2,
   "casos": 77.0,
   "COMUNA": "Peñalolén"
  },
  {
   "delito": "DAÑOS",
   "CODCOM": 13122,
   "anio": 2025,
   "mes": 3,
   "casos": 102.0,
   "COMUNA": "Peñalolén"
  },
  {
   "delito": "DAÑOS",
   "CODCOM": 13122,
   "anio": 2025,
   "mes": 4,
   "casos": 80.0,
   "COMUNA": "Peñalolén"
  },
  {
   "delito": "DAÑOS",
   "CODCOM": 13122,
   "anio": 2025,
   "mes": 5,
   "casos": 82.0,
   "COMUNA": "Peñalolén"
  },
  {
   "delito": "DAÑOS",
   "CODCOM": 13122,
   "anio": 2025,
   "mes": 6,
   "casos": 105.0,
   "COMUNA": "Peñalolén"
  },
  {
   "delito": "DAÑOS",
   "CODCOM": 13122,
   "anio": 2025,
   "mes": 7,
   "casos": 87.0,
   "COMUNA": "Peñalolén"
  },
  {
   "delito": "DAÑOS",
   "CODCOM": 13122,
   "anio": 2025,
   "mes": 8,
   "casos": 80.0,
   "COMUNA": "Peñalolén"
  },
  {
   "delito": "DAÑOS",
   "CODCOM": 13122,
   "anio": 2025,
   "mes": 9,
   "casos": 95.0,
   "COMUNA": "Peñalolén"
  },
  {
   "delito": "DAÑOS",
   "CODCOM": 13122,
   "anio": 2025,
   "mes": 10,
   "casos": 55.0,
   "COMUNA": "Peñalolén"
  },
  {
   "delito": "DAÑOS",
   "CODCOM": 13122,
   "anio": 2025,
   "mes": 11,
   "casos": 48.0,
   "COMUNA": "Peñalolén"
  },
  {
   "delito": "DAÑOS",
   "CODCOM": 13122,
   "anio": 2025,
   "mes": 12,
   "casos": 82.0,
   "COMUNA": "Peñalolén"
  },
  {
   "delito": "DAÑOS",
   "CODCOM": 13122,
   "anio": 2026,
   "mes": 1,
   "casos": 97.0,
   "COMUNA": "Peñalolén"
  },
  {
   "delito": "DAÑOS",
   "CODCOM": 13122,
   "anio": 2026,
   "mes": 2,
   "casos": 14.0,
   "COMUNA": "Peñalolén"
  },
  {
   "delito": "DELITOS EN CONTEXTO DE VIOLENCIA INTRAFAMILIAR",
   "CODCOM": 13122,
   "anio": 2025,
   "mes": 1,
   "casos": 191.0,
   "COMUNA": "Peñalolén"
  },
  {
   "delito": "DELITOS EN CONTEXTO DE VIOLENCIA INTRAFAMILIAR",
   "CODCOM": 13122,
   "anio": 2025,
   "mes": 2,
   "casos": 106.0,
   "COMUNA": "Peñalolén"
  },
  {
   "delito": "DELITOS EN CONTEXTO DE VIOLENCIA INTRAFAMILIAR",
   "CODCOM": 13122,
   "anio": 2025,
   "mes": 3,
   "casos": 178.0,
   "COMUNA": "Peñalolén"
  },
  {
   "delito": "DELITOS EN CONTEXTO DE VIOLENCIA INTRAFAMILIAR",
   "CODCOM": 13122,
   "anio": 2025,
   "mes": 4,
   "casos": 113.0,
   "COMUNA": "Peñalolén"
  },
  {
   "delito": "DELITOS EN CONTEXTO DE VIOLENCIA INTRAFAMILIAR",
   "CODCOM": 13122,
   "anio": 2025,
   "mes": 5,
   "casos": 110.0,
   "COMUNA": "Peñalolén"
  },
  {
   "delito": "DELITOS EN CONTEXTO DE VIOLENCIA INTRAFAMILIAR",
   "CODCOM": 13122,
   "anio": 2025,
   "mes": 6,
   "casos": 138.0,
   "COMUNA": "Peñalolén"
  },
  {
   "delito": "DELITOS EN CONTEXTO DE VIOLENCIA INTRAFAMILIAR",
   "CODCOM": 13122,
   "anio": 2025,
   "mes": 7,
   "casos": 108.0,
   "COMUNA": "Peñalolén"
  },
  {
   "delito": "DELITOS EN CONTEXTO DE VIOLENCIA INTRAFAMILIAR",
   "CODCOM": 13122,
   "anio": 2025,
   "mes": 8,
   "casos": 115.0,
   "COMUNA": "Peñalolén"
  },
  {
   "delito": "DELITOS EN CONTEXTO DE VIOLENCIA INTRAFAMILIAR",
   "CODCOM": 13122,
   "anio": 2025,
   "mes": 9,
   "casos": 144.0,
   "COMUNA": "Peñalolén"
  },
  {
   "delito": "DELITOS EN CONTEXTO DE VIOLENCIA INTRAFAMILIAR",
   "CODCOM": 13122,
   "anio": 2025,
   "mes": 10,
   "casos": 63.0,
   "COMUNA": "Peñalolén"
  },
  {
   "delito": "DELITOS EN CONTEXTO DE VIOLENCIA INTRAFAMILIAR",
   "CODCOM": 13122,
   "anio": 2025,
   "mes": 11,
   "casos": 60.0,
   "COMUNA": "Peñalolén"
  },
  {
   "delito": "DELITOS EN CONTEXTO DE VIOLENCIA INTRAFAMILIAR",
   "CODCOM": 13122,
   "anio": 2025,
   "mes": 12,
   "casos": 116.0,
   "COMUNA": "Peñalolén"
  },
  {
   "delito": "DELITOS EN CONTEXTO DE VIOLENCIA INTRAFAMILIAR",
   "CODCOM": 13122,
   "anio": 2026,
   "mes": 1,
   "casos": 162.0,
   "COMUNA": "Peñalolén"
  },
  {
   "delito": "DELITOS EN CONTEXTO DE VIOLENCIA INTRAFAMILIAR",
   "CODCOM": 13122,
   "anio": 2026,
   "mes": 2,
   "casos": 24.0,
   "COMUNA": "Peñalolén"
  },
  {
   "delito": "HOMICIDIOS Y FEMICIDIOS",
   "CODCOM": 13122,
   "anio": 2025,
   "mes": 1,
   "casos": 0.0,
   "COMUNA": "Peñalolén"
  },
  {
   "delito": "HOMICIDIOS Y FEMICIDIOS",
   "CODCOM": 13122,
   "anio": 2025,
   "mes": 2,
   "casos": 0.0,
   "COMUNA": "Peñalolén"
  },
  {
   "delito": "HOMICIDIOS Y FEMICIDIOS",
   "CODCOM": 13122,
   "anio": 2025,
   "mes": 3,
   "casos": 4.0,
   "COMUNA": "Peñalolén"
  },
  {
   "delito": "HOMICIDIOS Y FEMICIDIOS",
   "CODCOM": 13122,
   "anio": 2025,
   "mes": 4,
   "casos": 0.0,
   "COMUNA": "Peñalolén"
  },
  {
   "delito": "HOMICIDIOS Y FEMICIDIOS",
   "CODCOM": 13122,
   "anio": 2025,
   "mes": 5,
   "casos": 0.0,
   "COMUNA": "Peñalolén"
  },
  {
   "delito": "HOMICIDIOS Y FEMICIDIOS",
   "CODCOM": 13122,
   "anio": 2025,
   "mes": 6,
   "casos": 2.0,
   "COMUNA": "Peñalolén"
  },
  {
   "delito": "HOMICIDIOS Y FEMICIDIOS",
   "CODCOM": 13122,
   "anio": 2025,
   "mes": 7,
   "casos": 1.0,
   "COMUNA": "Peñalolén"
  },
  {
   "delito": "HOMICIDIOS Y FEMICIDIOS",
   "CODCOM": 13122,
   "anio": 2025,
   "mes": 8,
   "casos": 1.0,
   "COMUNA": "Peñalolén"
  },
  {
   "delito": "HOMICIDIOS Y FEMICIDIOS",
   "CODCOM": 13122,
   "anio": 2025,
   "mes": 9,
   "casos": 2.0,
   "COMUNA": "Peñalolén"
  },
  {
   "delito": "HOMICIDIOS Y FEMICIDIOS",
   "CODCOM": 13122,
   "anio": 2025,
   "mes": 10,
   "casos": 0.0,
   "COMUNA": "Peñalolén"
  },
  {
   "delito": "HOMICIDIOS Y FEMICIDIOS",
   "CODCOM": 13122,
   "anio": 2025,
   "mes": 11,
   "casos": 1.0,
   "COMUNA": "Peñalolén"
  },
  {
   "delito": "HOMICIDIOS Y FEMICIDIOS",
   "CODCOM": 13122,
   "anio": 2025,
   "mes": 12,
   "casos": 1.0,
   "COMUNA": "Peñalolén"
  },
  {
   "delito": "HOMICIDIOS Y FEMICIDIOS",
   "CODCOM": 13122,
   "anio": 2026,
   "mes": 1,
   "casos": 0.0,
   "COMUNA": "Peñalolén"
  },
  {
   "delito": "HOMICIDIOS Y FEMICIDIOS",
   "CODCOM": 13122,
   "anio": 2026,
   "mes": 2,
   "casos": 0.0,
   "COMUNA": "Peñalolén"
  },
  {
   "delito": "HURTOS",
   "CODCOM": 13122,
   "anio": 2025,
   "mes": 1,
   "casos": 69.0,
   "COMUNA": "Peñalolén"
  },
  {
   "delito": "HURTOS",
   "CODCOM": 13122,
   "anio": 2025,
   "mes": 2,
   "casos": 63.0,
   "COMUNA": "Peñalolén"
  },
  {
   "delito": "HURTOS",
   "CODCOM": 13122,
   "anio": 2025,
   "mes": 3,
   "casos": 75.0,
   "COMUNA": "Peñalolén"
  },
  {
   "delito": "HURTOS",
   "CODCOM": 13122,
   "anio": 2025,
   "mes": 4,
   "casos": 64.0,
   "COMUNA": "Peñalolén"
  },
  {
   "delito": "HURTOS",
   "CODCOM": 13122,
   "anio": 2025,
   "mes": 5,
   "casos": 50.0,
   "COMUNA": "Peñalolén"
  },
  {
   "delito": "HURTOS",
   "CODCOM": 13122,
   "anio": 2025,
   "mes": 6,
   "casos": 72.0,
   "COMUNA": "Peñalolén"
  },
  {
   "delito": "HURTOS",
   "CODCOM": 13122,
   "anio": 2025,
   "mes": 7,
   "casos": 78.0,
   "COMUNA": "Peñalolén"
  },
  {
   "delito": "HURTOS",
   "CODCOM": 13122,
   "anio": 2025,
   "mes": 8,
   "casos": 44.0,
   "COMUNA": "Peñalolén"
  },
  {
   "delito": "HURTOS",
   "CODCOM": 13122,
   "anio": 2025,
   "mes": 9,
   "casos": 71.0,
   "COMUNA": "Peñalolén"
  },
  {
   "delito": "HURTOS",
   "CODCOM": 13122,
   "anio": 2025,
   "mes": 10,
   "casos": 42.0,
   "COMUNA": "Peñalolén"
  },
  {
   "delito": "HURTOS",
   "CODCOM": 13122,
   "anio": 2025,
   "mes": 11,
   "casos": 40.0,
   "COMUNA": "Peñalolén"
  },
  {
   "delito": "HURTOS",
   "CODCOM": 13122,
   "anio": 2025,
   "mes": 12,
   "casos": 63.0,
   "COMUNA": "Peñalolén"
  },
  {
   "delito": "HURTOS",
   "CODCOM": 13122,
   "anio": 2026,
   "mes": 1,
   "casos": 62.0,
   "COMUNA": "Peñalolén"
  },
  {
   "delito": "HURTOS",
   "CODCOM": 13122,
   "anio": 2026,
   "mes": 2,
   "casos": 11.0,
   "COMUNA": "Peñalolén"
  },
  {
   "delito": "INCIVILIDADES",
   "CODCOM": 13122,
   "anio": 2025,
   "mes": 1,
   "casos": 8.0,
   "COMUNA": "Peñalolén"
  },
  {
   "delito": "INCIVILIDADES",
   "CODCOM": 13122,
   "anio": 2025,
   "mes": 2,
   "casos": 5.0,
   "COMUNA": "Peñalolén"
  },
  {
   "delito": "INCIVILIDADES",
   "CODCOM": 13122,
   "anio": 2025,
   "mes": 3,
   "casos": 5.0,
   "COMUNA": "Peñalolén"
  },
  {
   "delito": "INCIVILIDADES",
   "CODCOM": 13122,
   "anio": 2025,
   "mes": 4,
   "casos": 6.0,
   "COMUNA": "Peñalolén"
  },
  {
   "delito": "INCIVILIDADES",
   "CODCOM": 13122,
   "anio": 2025,
   "mes": 5,
   "casos": 9.0,
   "COMUNA": "Peñalolén"
  },
  {
   "delito": "INCIVILIDADES",
   "CODCOM": 13122,
   "anio": 2025,
   "mes": 6,
   "casos": 15.0,
   "COMUNA": "Peñalolén"
  },
  {
   "delito": "INCIVILIDADES",
   "CODCOM": 13122,
   "anio": 2025,
   "mes": 7,
   "casos": 11.0,
   "COMUNA": "Peñalolén"
  },
  {
   "delito": "INCIVILIDADES",
   "CODCOM": 13122,
   "anio": 2025,
   "mes": 8,
   "casos": 6.0,
   "COMUNA": "Peñalolén"
  },
  {
   "delito": "INCIVILIDADES",
   "CODCOM": 13122,
   "anio": 2025,
   "mes": 9,
   "casos": 8.0,
   "COMUNA": "Peñalolén"
  },
  {
   "delito": "INCIVILIDADES",
   "CODCOM": 13122,
   "anio": 2025,
   "mes": 10,
   "casos": 12.0,
   "COMUNA": "Peñalolén"
  },
  {
   "delito": "INCIVILIDADES",
   "CODCOM": 13122,
   "anio": 2025,
   "mes": 11,
   "casos": 3.0,
   "COMUNA": "Peñalolén"
  },
  {
   "delito": "INCIVILIDADES",
   "CODCOM": 13122,
   "anio": 2025,
   "mes": 12,
   "casos": 7.0,
   "COMUNA": "Peñalolén"
  },
  {
   "delito": "INCIVILIDADES",
   "CODCOM": 13122,
   "anio": 2026,
   "mes": 1,
   "casos": 6.0,
   "COMUNA": "Peñalolén"
  },
  {
   "delito": "INCIVILIDADES",
   "CODCOM": 13122,
   "anio": 2026,
   "mes": 2,
   "casos": 5.0,
   "COMUNA": "Peñalolén"
  },
  {
   "delito": "LESIONES GRAVES",
   "CODCOM": 13122,
   "anio": 2025,
   "mes": 1,
   "casos": 3.0,
   "COMUNA": "Peñalolén"
  },
  {
   "delito": "LESIONES GRAVES",
   "CODCOM": 13122,
   "anio": 2025,
   "mes": 2,
   "casos": 2.0,
   "COMUNA": "Peñalolén"
  },
  {
   "delito": "LESIONES GRAVES",
   "CODCOM": 13122,
   "anio": 2025,
   "mes": 3,
   "casos": 2.0,
   "COMUNA": "Peñalolén"
  },
  {
   "delito": "LESIONES GRAVES",
   "CODCOM": 13122,
   "anio": 2025,
   "mes": 4,
   "casos": 4.0,
   "COMUNA": "Peñalolén"
  },
  {
   "delito": "LESIONES GRAVES",
   "CODCOM": 13122,
   "anio": 2025,
   "mes": 5,
   "casos": 4.0,
   "COMUNA": "Peñalolén"
  },
  {
   "delito": "LESIONES GRAVES",
   "CODCOM": 13122,
   "anio": 2025,
   "mes": 6,
   "casos": 1.0,
   "COMUNA": "Peñalolén"
  },
  {
   "delito": "LESIONES GRAVES",
   "CODCOM": 13122,
   "anio": 2025,
   "mes": 7,
   "casos": 1.0,
   "COMUNA": "Peñalolén"
  },
  {
   "delito": "LESIONES GRAVES",
   "CODCOM": 13122,
   "anio": 2025,
   "mes": 8,
   "casos": 2.0,
   "COMUNA": "Peñalolén"
  },
  {
   "delito": "LESIONES GRAVES",
   "CODCOM": 13122,
   "anio": 2025,
   "mes": 9,
   "casos": 9.0,
   "COMUNA": "Peñalolén"
  },
  {
   "delito": "LESIONES GRAVES",
   "CODCOM": 13122,
   "anio": 2025,
   "mes": 10,
   "casos": 2.0,
   "COMUNA": "Peñalolén"
  },
  {
   "delito": "LESIONES GRAVES",
   "CODCOM": 13122,
   "anio": 2025,
   "mes": 11,
   "casos": 1.0,
   "COMUNA": "Peñalolén"
  },
  {
   "delito": "LESIONES GRAVES",
   "CODCOM": 13122,
   "anio": 2025,
   "mes": 12,
   "casos": 5.0,
   "COMUNA": "Peñalolén"
  },
  {
   "delito": "LESIONES GRAVES",
   "CODCOM": 13122,
   "anio": 2026,
   "mes": 1,
   "casos": 3.0,
   "COMUNA": "Peñalolén"
  },
  {
   "delito": "LESIONES GRAVES",
   "CODCOM": 13122,
   "anio": 2026,
   "mes": 2,
   "casos": 1.0,
   "COMUNA": "Peñalolén"
  },
  {
   "delito": "LESIONES LEVES",
   "CODCOM": 13122,
   "anio": 2025,
   "mes": 1,
   "casos": 59.0,
   "COMUNA": "Peñalolén"
  },
  {
   "delito": "LESIONES LEVES",
   "CODCOM": 13122,
   "anio": 2025,
   "mes": 2,
   "casos": 35.0,
   "COMUNA": "Peñalolén"
  },
  {
   "delito": "LESIONES LEVES",
   "CODCOM": 13122,
   "anio": 2025,
   "mes": 3,
   "casos": 48.0,
   "COMUNA": "Peñalolén"
  },
  {
   "delito": "LESIONES LEVES",
   "CODCOM": 13122,
   "anio": 2025,
   "mes": 4,
   "casos": 39.0,
   "COMUNA": "Peñalolén"
  },
  {
   "delito": "LESIONES LEVES",
   "CODCOM": 13122,
   "anio": 2025,
   "mes": 5,
   "casos": 35.0,
   "COMUNA": "Peñalolén"
  },
  {
   "delito": "LESIONES LEVES",
   "CODCOM": 13122,
   "anio": 2025,
   "mes": 6,
   "casos": 42.0,
   "COMUNA": "Peñalolén"
  },
  {
   "delito": "LESIONES LEVES",
   "CODCOM": 13122,
   "anio": 2025,
   "mes": 7,
   "casos": 36.0,
   "COMUNA": "Peñalolén"
  },
  {
   "delito": "LESIONES LEVES",
   "CODCOM": 13122,
   "anio": 2025,
   "mes": 8,
   "casos": 31.0,
   "COMUNA": "Peñalolén"
  },
  {
   "delito": "LESIONES LEVES",
   "CODCOM": 13122,
   "anio": 2025,
   "mes": 9,
   "casos": 52.0,
   "COMUNA": "Peñalolén"
  },
  {
   "delito": "LESIONES LEVES",
   "CODCOM": 13122,
   "anio": 2025,
   "mes": 10,
   "casos": 38.0,
   "COMUNA": "Peñalolén"
  },
  {
   "delito": "LESIONES LEVES",
   "CODCOM": 13122,
   "anio": 2025,
   "mes": 11,
   "casos": 17.0,
   "COMUNA": "Peñalolén"
  },
  {
   "delito": "LESIONES LEVES",
   "CODCOM": 13122,
   "anio": 2025,
   "mes": 12,
   "casos": 51.0,
   "COMUNA": "Peñalolén"
  },
  {
   "delito": "LESIONES LEVES",
   "CODCOM": 13122,
   "anio": 2026,
   "mes": 1,
   "casos": 51.0,
   "COMUNA": "Peñalolén"
  },
  {
   "delito": "LESIONES LEVES",
   "CODCOM": 13122,
   "anio": 2026,
   "mes": 2,
   "casos": 12.0,
   "COMUNA": "Peñalolén"
  },
  {
   "delito": "LESIONES MENOS GRAVES",
   "CODCOM": 13122,
   "anio": 2025,
   "mes": 1,
   "casos": 12.0,
   "COMUNA": "Peñalolén"
  },
  {
   "delito": "LESIONES MENOS GRAVES",
   "CODCOM": 13122,
   "anio": 2025,
   "mes": 2,
   "casos": 7.0,
   "COMUNA": "Peñalolén"
  },
  {
   "delito": "LESIONES MENOS GRAVES",
   "CODCOM": 13122,
   "anio": 2025,
   "mes": 3,
   "casos": 11.0,
   "COMUNA": "Peñalolén"
  },
  {
   "delito": "LESIONES MENOS GRAVES",
   "CODCOM": 13122,
   "anio": 2025,
   "mes": 4,
   "casos": 7.0,
   "COMUNA": "Peñalolén"
  },
  {
   "delito": "LESIONES MENOS GRAVES",
   "CODCOM": 13122,
   "anio": 2025,
   "mes": 5,
   "casos": 4.0,
   "COMUNA": "Peñalolén"
  },
  {
   "delito": "LESIONES MENOS GRAVES",
   "CODCOM": 13122,
   "anio": 2025,
   "mes": 6,
   "casos": 4.0,
   "COMUNA": "Peñalolén"
  },
  {
   "delito": "LESIONES MENOS GRAVES",
   "CODCOM": 13122,
   "anio": 2025,
   "mes": 7,
   "casos": 5.0,
   "COMUNA": "Peñalolén"
  },
  {
   "delito": "LESIONES MENOS GRAVES",
   "CODCOM": 13122,
   "anio": 2025,
   "mes": 8,
   "casos": 6.0,
   "COMUNA": "Peñalolén"
  },
  {
   "delito": "LESIONES MENOS GRAVES",
   "CODCOM": 13122,
   "anio": 2025,
   "mes": 9,
   "casos": 7.0,
   "COMUNA": "Peñalolén"
  },
  {
   "delito": "LESIONES MENOS GRAVES",
   "CODCOM": 13122,
   "anio": 2025,
   "mes": 10,
   "casos": 3.0,
   "COMUNA": "Peñalolén"
  },
  {
   "delito": "LESIONES MENOS GRAVES",
   "CODCOM": 13122,
   "anio": 2025,
   "mes": 11,
   "casos": 4.0,
   "COMUNA": "Peñalolén"
  },
  {
   "delito": "LESIONES MENOS GRAVES",
   "CODCOM": 13122,
   "anio": 2025,
   "mes": 12,
   "casos": 11.0,
   "COMUNA": "Peñalolén"
  },
  {
   "delito": "LESIONES MENOS GRAVES",
   "CODCOM": 13122,
   "anio": 2026,
   "mes": 1,
   "casos": 14.0,
   "COMUNA": "Peñalolén"
  },
  {
   "delito": "LESIONES MENOS GRAVES",
   "CODCOM": 13122,
   "anio": 2026,
   "mes": 2,
   "casos": 1.0,
   "COMUNA": "Peñalolén"
  },
  {
   "delito": "LEY DE CONTROL DE ARMAS",
   "CODCOM": 13122,
   "anio": 2025,
   "mes": 1,
   "casos": 12.0,
   "COMUNA": "Peñalolén"
  },
  {
   "delito": "LEY DE CONTROL DE ARMAS",
   "CODCOM": 13122,
   "anio": 2025,
   "mes": 2,
   "casos": 9.0,
   "COMUNA": "Peñalolén"
  },
  {
   "delito": "LEY DE CONTROL DE ARMAS",
   "CODCOM": 13122,
   "anio": 2025,
   "mes": 3,
   "casos": 20.0,
   "COMUNA": "Peñalolén"
  },
  {
   "delito": "LEY DE CONTROL DE ARMAS",
   "CODCOM": 13122,
   "anio": 2025,
   "mes": 4,
   "casos": 33.0,
   "COMUNA": "Peñalolén"
  },
  {
   "delito": "LEY DE CONTROL DE ARMAS",
   "CODCOM": 13122,
   "anio": 2025,
   "mes": 5,
   "casos": 13.0,
   "COMUNA": "Peñalolén"
  },
  {
   "delito": "LEY DE CONTROL DE ARMAS",
   "CODCOM": 13122,
   "anio": 2025,
   "mes": 6,
   "casos": 20.0,
   "COMUNA": "Peñalolén"
  },
  {
   "delito": "LEY DE CONTROL DE ARMAS",
   "CODCOM": 13122,
   "anio": 2025,
   "mes": 7,
   "casos": 21.0,
   "COMUNA": "Peñalolén"
  },
  {
   "delito": "LEY DE CONTROL DE ARMAS",
   "CODCOM": 13122,
   "anio": 2025,
   "mes": 8,
   "casos": 26.0,
   "COMUNA": "Peñalolén"
  },
  {
   "delito": "LEY DE CONTROL DE ARMAS",
   "CODCOM": 13122,
   "anio": 2025,
   "mes": 9,
   "casos": 23.0,
   "COMUNA": "Peñalolén"
  },
  {
   "delito": "LEY DE CONTROL DE ARMAS",
   "CODCOM": 13122,
   "anio": 2025,
   "mes": 10,
   "casos": 16.0,
   "COMUNA": "Peñalolén"
  },
  {
   "delito": "LEY DE CONTROL DE ARMAS",
   "CODCOM": 13122,
   "anio": 2025,
   "mes": 11,
   "casos": 19.0,
   "COMUNA": "Peñalolén"
  },
  {
   "delito": "LEY DE CONTROL DE ARMAS",
   "CODCOM": 13122,
   "anio": 2025,
   "mes": 12,
   "casos": 23.0,
   "COMUNA": "Peñalolén"
  },
  {
   "delito": "LEY DE CONTROL DE ARMAS",
   "CODCOM": 13122,
   "anio": 2026,
   "mes": 1,
   "casos": 16.0,
   "COMUNA": "Peñalolén"
  },
  {
   "delito": "LEY DE CONTROL DE ARMAS",
   "CODCOM": 13122,
   "anio": 2026,
   "mes": 2,
   "casos": 8.0,
   "COMUNA": "Peñalolén"
  },
  {
   "delito": "LEY DE DROGAS",
   "CODCOM": 13122,
   "anio": 2025,
   "mes": 1,
   "casos": 5.0,
   "COMUNA": "Peñalolén"
  },
  {
   "delito": "LEY DE DROGAS",
   "CODCOM": 13122,
   "anio": 2025,
   "mes": 2,
   "casos": 11.0,
   "COMUNA": "Peñalolén"
  },
  {
   "delito": "LEY DE DROGAS",
   "CODCOM": 13122,
   "anio": 2025,
   "mes": 3,
   "casos": 13.0,
   "COMUNA": "Peñalolén"
  },
  {
   "delito": "LEY DE DROGAS",
   "CODCOM": 13122,
   "anio": 2025,
   "mes": 4,
   "casos": 8.0,
   "COMUNA": "Peñalolén"
  },
  {
   "delito": "LEY DE DROGAS",
   "CODCOM": 13122,
   "anio": 2025,
   "mes": 5,
   "casos": 10.0,
   "COMUNA": "Peñalolén"
  },
  {
   "delito": "LEY DE DROGAS",
   "CODCOM": 13122,
   "anio": 2025,
   "mes": 6,
   "casos": 7.0,
   "COMUNA": "Peñalolén"
  },
  {
   "delito": "LEY DE DROGAS",
   "CODCOM": 13122,
   "anio": 2025,
   "mes": 7,
   "casos": 10.0,
   "COMUNA": "Peñalolén"
  },
  {
   "delito": "LEY DE DROGAS",
   "CODCOM": 13122,
   "anio": 2025,
   "mes": 8,
   "casos": 11.0,
   "COMUNA": "Peñalolén"
  },
  {
   "delito": "LEY DE DROGAS",
   "CODCOM": 13122,
   "anio": 2025,
   "mes": 9,
   "casos": 13.0,
   "COMUNA": "Peñalolén"
  },
  {
   "delito": "LEY DE DROGAS",
   "CODCOM": 13122,
   "anio": 2025,
   "mes": 10,
   "casos": 8.0,
   "COMUNA": "Peñalolén"
  },
  {
   "delito": "LEY DE DROGAS",
   "CODCOM": 13122,
   "anio": 2025,
   "mes": 11,
   "casos": 8.0,
   "COMUNA": "Peñalolén"
  },
  {
   "delito": "LEY DE DROGAS",
   "CODCOM": 13122,
   "anio": 2025,
   "mes": 12,
   "casos": 15.0,
   "COMUNA": "Peñalolén"
  },
  {
   "delito": "LEY DE DROGAS",
   "CODCOM": 13122,
   "anio": 2026,
   "mes": 1,
   "casos": 10.0,
   "COMUNA": "Peñalolén"
  },
  {
   "delito": "LEY DE DROGAS",
   "CODCOM": 13122,
   "anio": 2026,
   "mes": 2,
   "casos": 3.0,
   "COMUNA": "Peñalolén"
  },
  {
   "delito": "OTROS DESÓRDENES PÚBLICOS",
   "CODCOM": 13122,
   "anio": 2025,
   "mes": 1,
   "casos": 0.0,
   "COMUNA": "Peñalolén"
  },
  {
   "delito": "OTROS DESÓRDENES PÚBLICOS",
   "CODCOM": 13122,
   "anio": 2025,
   "mes": 2,
   "casos": 1.0,
   "COMUNA": "Peñalolén"
  },
  {
   "delito": "OTROS DESÓRDENES PÚBLICOS",
   "CODCOM": 13122,
   "anio": 2025,
   "mes": 3,
   "casos": 2.0,
   "COMUNA": "Peñalolén"
  },
  {
   "delito": "OTROS DESÓRDENES PÚBLICOS",
   "CODCOM": 13122,
   "anio": 2025,
   "mes": 4,
   "casos": 6.0,
   "COMUNA": "Peñalolén"
  },
  {
   "delito": "OTROS DESÓRDENES PÚBLICOS",
   "CODCOM": 13122,
   "anio": 2025,
   "mes": 5,
   "casos": 1.0,
   "COMUNA": "Peñalolén"
  },
  {
   "delito": "OTROS DESÓRDENES PÚBLICOS",
   "CODCOM": 13122,
   "anio": 2025,
   "mes": 6,
   "casos": 1.0,
   "COMUNA": "Peñalolén"
  },
  {
   "delito": "OTROS DESÓRDENES PÚBLICOS",
   "CODCOM": 13122,
   "anio": 2025,
   "mes": 7,
   "casos": 1.0,
   "COMUNA": "Peñalolén"
  },
  {
   "delito": "OTROS DESÓRDENES PÚBLICOS",
   "CODCOM": 13122,
   "anio": 2025,
   "mes": 8,
   "casos": 2.0,
   "COMUNA": "Peñalolén"
  },
  {
   "delito": "OTROS DESÓRDENES PÚBLICOS",
   "CODCOM": 13122,
   "anio": 2025,
   "mes": 9,
   "casos": 5.0,
   "COMUNA": "Peñalolén"
  },
  {
   "delito": "OTROS DESÓRDENES PÚBLICOS",
   "CODCOM": 13122,
   "anio": 2025,
   "mes": 10,
   "casos": 4.0,
   "COMUNA": "Peñalolén"
  },
  {
   "delito": "OTROS DESÓRDENES PÚBLICOS",
   "CODCOM": 13122,
   "anio": 2025,
   "mes": 11,
   "casos": 3.0,
   "COMUNA": "Peñalolén"
  },
  {
   "delito": "OTROS DESÓRDENES PÚBLICOS",
   "CODCOM": 13122,
   "anio": 2025,
   "mes": 12,
   "casos": 0.0,
   "COMUNA": "Peñalolén"
  },
  {
   "delito": "OTROS DESÓRDENES PÚBLICOS",
   "CODCOM": 13122,
   "anio": 2026,
   "mes": 1,
   "casos": 0.0,
   "COMUNA": "Peñalolén"
  },
  {
   "delito": "OTROS DESÓRDENES PÚBLICOS",
   "CODCOM": 13122,
   "anio": 2026,
   "mes": 2,
   "casos": 0.0,
   "COMUNA": "Peñalolén"
  },
  {
   "delito": "OTROS ROBOS CON FUERZA EN LAS COSAS",
   "CODCOM": 13122,
   "anio": 2025,
   "mes": 1,
   "casos": 4.0,
   "COMUNA": "Peñalolén"
  },
  {
   "delito": "OTROS ROBOS CON FUERZA EN LAS COSAS",
   "CODCOM": 13122,
   "anio": 2025,
   "mes": 2,
   "casos": 4.0,
   "COMUNA": "Peñalolén"
  },
  {
   "delito": "OTROS ROBOS CON FUERZA EN LAS COSAS",
   "CODCOM": 13122,
   "anio": 2025,
   "mes": 3,
   "casos": 8.0,
   "COMUNA": "Peñalolén"
  },
  {
   "delito": "OTROS ROBOS CON FUERZA EN LAS COSAS",
   "CODCOM": 13122,
   "anio": 2025,
   "mes": 4,
   "casos": 6.0,
   "COMUNA": "Peñalolén"
  },
  {
   "delito": "OTROS ROBOS CON FUERZA EN LAS COSAS",
   "CODCOM": 13122,
   "anio": 2025,
   "mes": 5,
   "casos": 7.0,
   "COMUNA": "Peñalolén"
  },
  {
   "delito": "OTROS ROBOS CON FUERZA EN LAS COSAS",
   "CODCOM": 13122,
   "anio": 2025,
   "mes": 6,
   "casos": 6.0,
   "COMUNA": "Peñalolén"
  },
  {
   "delito": "OTROS ROBOS CON FUERZA EN LAS COSAS",
   "CODCOM": 13122,
   "anio": 2025,
   "mes": 7,
   "casos": 2.0,
   "COMUNA": "Peñalolén"
  },
  {
   "delito": "OTROS ROBOS CON FUERZA EN LAS COSAS",
   "CODCOM": 13122,
   "anio": 2025,
   "mes": 8,
   "casos": 6.0,
   "COMUNA": "Peñalolén"
  },
  {
   "delito": "OTROS ROBOS CON FUERZA EN LAS COSAS",
   "CODCOM": 13122,
   "anio": 2025,
   "mes": 9,
   "casos": 2.0,
   "COMUNA": "Peñalolén"
  },
  {
   "delito": "OTROS ROBOS CON FUERZA EN LAS COSAS",
   "CODCOM": 13122,
   "anio": 2025,
   "mes": 10,
   "casos": 4.0,
   "COMUNA": "Peñalolén"
  },
  {
   "delito": "OTROS ROBOS CON FUERZA EN LAS COSAS",
   "CODCOM": 13122,
   "anio": 2025,
   "mes": 11,
   "casos": 3.0,
   "COMUNA": "Peñalolén"
  },
  {
   "delito": "OTROS ROBOS CON FUERZA EN LAS COSAS",
   "CODCOM": 13122,
   "anio": 2025,
   "mes": 12,
   "casos": 4.0,
   "COMUNA": "Peñalolén"
  },
  {
   "delito": "OTROS ROBOS CON FUERZA EN LAS COSAS",
   "CODCOM": 13122,
   "anio": 2026,
   "mes": 1,
   "casos": 3.0,
   "COMUNA": "Peñalolén"
  },
  {
   "delito": "OTROS ROBOS CON FUERZA EN LAS COSAS",
   "CODCOM": 13122,
   "anio": 2026,
   "mes": 2,
   "casos": 0.0,
   "COMUNA": "Peñalolén"
  },
  {
   "delito": "RECEPTACIÓN",
   "CODCOM": 13122,
   "anio": 2025,
   "mes": 1,
   "casos": 10.0,
   "COMUNA": "Peñalolén"
  },
  {
   "delito": "RECEPTACIÓN",
   "CODCOM": 13122,
   "anio": 2025,
   "mes": 2,
   "casos": 5.0,
   "COMUNA": "Peñalolén"
  },
  {
   "delito": "RECEPTACIÓN",
   "CODCOM": 13122,
   "anio": 2025,
   "mes": 3,
   "casos": 10.0,
   "COMUNA": "Peñalolén"
  },
  {
   "delito": "RECEPTACIÓN",
   "CODCOM": 13122,
   "anio": 2025,
   "mes": 4,
   "casos": 6.0,
   "COMUNA": "Peñalolén"
  },
  {
   "delito": "RECEPTACIÓN",
   "CODCOM": 13122,
   "anio": 2025,
   "mes": 5,
   "casos": 5.0,
   "COMUNA": "Peñalolén"
  },
  {
   "delito": "RECEPTACIÓN",
   "CODCOM": 13122,
   "anio": 2025,
   "mes": 6,
   "casos": 8.0,
   "COMUNA": "Peñalolén"
  },
  {
   "delito": "RECEPTACIÓN",
   "CODCOM": 13122,
   "anio": 2025,
   "mes": 7,
   "casos": 6.0,
   "COMUNA": "Peñalolén"
  },
  {
   "delito": "RECEPTACIÓN",
   "CODCOM": 13122,
   "anio": 2025,
   "mes": 8,
   "casos": 3.0,
   "COMUNA": "Peñalolén"
  },
  {
   "delito": "RECEPTACIÓN",
   "CODCOM": 13122,
   "anio": 2025,
   "mes": 9,
   "casos": 6.0,
   "COMUNA": "Peñalolén"
  },
  {
   "delito": "RECEPTACIÓN",
   "CODCOM": 13122,
   "anio": 2025,
   "mes": 10,
   "casos": 1.0,
   "COMUNA": "Peñalolén"
  },
  {
   "delito": "RECEPTACIÓN",
   "CODCOM": 13122,
   "anio": 2025,
   "mes": 11,
   "casos": 2.0,
   "COMUNA": "Peñalolén"
  },
  {
   "delito": "RECEPTACIÓN",
   "CODCOM": 13122,
   "anio": 2025,
   "mes": 12,
   "casos": 9.0,
   "COMUNA": "Peñalolén"
  },
  {
   "delito": "RECEPTACIÓN",
   "CODCOM": 13122,
   "anio": 2026,
   "mes": 1,
   "casos": 10.0,
   "COMUNA": "Peñalolén"
  },
  {
   "delito": "RECEPTACIÓN",
   "CODCOM": 13122,
   "anio": 2026,
   "mes": 2,
   "casos": 1.0,
   "COMUNA": "Peñalolén"
  },
  {
   "delito": "ROBOS CON VIOLENCIA E INTIMIDACIÓN",
   "CODCOM": 13122,
   "anio": 2025,
   "mes": 1,
   "casos": 85.0,
   "COMUNA": "Peñalolén"
  },
  {
   "delito": "ROBOS CON VIOLENCIA E INTIMIDACIÓN",
   "CODCOM": 13122,
   "anio": 2025,
   "mes": 2,
   "casos": 82.0,
   "COMUNA": "Peñalolén"
  },
  {
   "delito": "ROBOS CON VIOLENCIA E INTIMIDACIÓN",
   "CODCOM": 13122,
   "anio": 2025,
   "mes": 3,
   "casos": 75.0,
   "COMUNA": "Peñalolén"
  },
  {
   "delito": "ROBOS CON VIOLENCIA E INTIMIDACIÓN",
   "CODCOM": 13122,
   "anio": 2025,
   "mes": 4,
   "casos": 65.0,
   "COMUNA": "Peñalolén"
  },
  {
   "delito": "ROBOS CON VIOLENCIA E INTIMIDACIÓN",
   "CODCOM": 13122,
   "anio": 2025,
   "mes": 5,
   "casos": 87.0,
   "COMUNA": "Peñalolén"
  },
  {
   "delito": "ROBOS CON VIOLENCIA E INTIMIDACIÓN",
   "CODCOM": 13122,
   "anio": 2025,
   "mes": 6,
   "casos": 102.0,
   "COMUNA": "Peñalolén"
  },
  {
   "delito": "ROBOS CON VIOLENCIA E INTIMIDACIÓN",
   "CODCOM": 13122,
   "anio": 2025,
   "mes": 7,
   "casos": 57.0,
   "COMUNA": "Peñalolén"
  },
  {
   "delito": "ROBOS CON VIOLENCIA E INTIMIDACIÓN",
   "CODCOM": 13122,
   "anio": 2025,
   "mes": 8,
   "casos": 73.0,
   "COMUNA": "Peñalolén"
  },
  {
   "delito": "ROBOS CON VIOLENCIA E INTIMIDACIÓN",
   "CODCOM": 13122,
   "anio": 2025,
   "mes": 9,
   "casos": 78.0,
   "COMUNA": "Peñalolén"
  },
  {
   "delito": "ROBOS CON VIOLENCIA E INTIMIDACIÓN",
   "CODCOM": 13122,
   "anio": 2025,
   "mes": 10,
   "casos": 41.0,
   "COMUNA": "Peñalolén"
  },
  {
   "delito": "ROBOS CON VIOLENCIA E INTIMIDACIÓN",
   "CODCOM": 13122,
   "anio": 2025,
   "mes": 11,
   "casos": 38.0,
   "COMUNA": "Peñalolén"
  },
  {
   "delito": "ROBOS CON VIOLENCIA E INTIMIDACIÓN",
   "CODCOM": 13122,
   "anio": 2025,
   "mes": 12,
   "casos": 57.0,
   "COMUNA": "Peñalolén"
  },
  {
   "delito": "ROBOS CON VIOLENCIA E INTIMIDACIÓN",
   "CODCOM": 13122,
   "anio": 2026,
   "mes": 1,
   "casos": 53.0,
   "COMUNA": "Peñalolén"
  },
  {
   "delito": "ROBOS CON VIOLENCIA E INTIMIDACIÓN",
   "CODCOM": 13122,
   "anio": 2026,
   "mes": 2,
   "casos": 14.0,
   "COMUNA": "Peñalolén"
  },
  {
   "delito": "ROBOS DE VEHÍCULOS Y SUS ACCESORIOS",
   "CODCOM": 13122,
   "anio": 2025,
   "mes": 1,
   "casos": 109.0,
   "COMUNA": "Peñalolén"
  },
  {
   "delito": "ROBOS DE VEHÍCULOS Y SUS ACCESORIOS",
   "CODCOM": 13122,
   "anio": 2025,
   "mes": 2,
   "casos": 96.0,
   "COMUNA": "Peñalolén"
  },
  {
   "delito": "ROBOS DE VEHÍCULOS Y SUS ACCESORIOS",
   "CODCOM": 13122,
   "anio": 2025,
   "mes": 3,
   "casos": 110.0,
   "COMUNA": "Peñalolén"
  },
  {
   "delito": "ROBOS DE VEHÍCULOS Y SUS ACCESORIOS",
   "CODCOM": 13122,
   "anio": 2025,
   "mes": 4,
   "casos": 111.0,
   "COMUNA": "Peñalolén"
  },
  {
   "delito": "ROBOS DE VEHÍCULOS Y SUS ACCESORIOS",
   "CODCOM": 13122,
   "anio": 2025,
   "mes": 5,
   "casos": 116.0,
   "COMUNA": "Peñalolén"
  },
  {
   "delito": "ROBOS DE VEHÍCULOS Y SUS ACCESORIOS",
   "CODCOM": 13122,
   "anio": 2025,
   "mes": 6,
   "casos": 149.0,
   "COMUNA": "Peñalolén"
  },
  {
   "delito": "ROBOS DE VEHÍCULOS Y SUS ACCESORIOS",
   "CODCOM": 13122,
   "anio": 2025,
   "mes": 7,
   "casos": 79.0,
   "COMUNA": "Peñalolén"
  },
  {
   "delito": "ROBOS DE VEHÍCULOS Y SUS ACCESORIOS",
   "CODCOM": 13122,
   "anio": 2025,
   "mes": 8,
   "casos": 116.0,
   "COMUNA": "Peñalolén"
  },
  {
   "delito": "ROBOS DE VEHÍCULOS Y SUS ACCESORIOS",
   "CODCOM": 13122,
   "anio": 2025,
   "mes": 9,
   "casos": 104.0,
   "COMUNA": "Peñalolén"
  },
  {
   "delito": "ROBOS DE VEHÍCULOS Y SUS ACCESORIOS",
   "CODCOM": 13122,
   "anio": 2025,
   "mes": 10,
   "casos": 66.0,
   "COMUNA": "Peñalolén"
  },
  {
   "delito": "ROBOS DE VEHÍCULOS Y SUS ACCESORIOS",
   "CODCOM": 13122,
   "anio": 2025,
   "mes": 11,
   "casos": 37.0,
   "COMUNA": "Peñalolén"
  },
  {
   "delito": "ROBOS DE VEHÍCULOS Y SUS ACCESORIOS",
   "CODCOM": 13122,
   "anio": 2025,
   "mes": 12,
   "casos": 75.0,
   "COMUNA": "Peñalolén"
  },
  {
   "delito": "ROBOS DE VEHÍCULOS Y SUS ACCESORIOS",
   "CODCOM": 13122,
   "anio": 2026,
   "mes": 1,
   "casos": 71.0,
   "COMUNA": "Peñalolén"
  },
  {
   "delito": "ROBOS DE VEHÍCULOS Y SUS ACCESORIOS",
   "CODCOM": 13122,
   "anio": 2026,
   "mes": 2,
   "casos": 12.0,
   "COMUNA": "Peñalolén"
  },
  {
   "delito": "ROBOS EN LUGARES HABITADOS Y NO HABITADOS",
   "CODCOM": 13122,
   "anio": 2025,
   "mes": 1,
   "casos": 67.0,
   "COMUNA": "Peñalolén"
  },
  {
   "delito": "ROBOS EN LUGARES HABITADOS Y NO HABITADOS",
   "CODCOM": 13122,
   "anio": 2025,
   "mes": 2,
   "casos": 61.0,
   "COMUNA": "Peñalolén"
  },
  {
   "delito": "ROBOS EN LUGARES HABITADOS Y NO HABITADOS",
   "CODCOM": 13122,
   "anio": 2025,
   "mes": 3,
   "casos": 63.0,
   "COMUNA": "Peñalolén"
  },
  {
   "delito": "ROBOS EN LUGARES HABITADOS Y NO HABITADOS",
   "CODCOM": 13122,
   "anio": 2025,
   "mes": 4,
   "casos": 49.0,
   "COMUNA": "Peñalolén"
  },
  {
   "delito": "ROBOS EN LUGARES HABITADOS Y NO HABITADOS",
   "CODCOM": 13122,
   "anio": 2025,
   "mes": 5,
   "casos": 61.0,
   "COMUNA": "Peñalolén"
  },
  {
   "delito": "ROBOS EN LUGARES HABITADOS Y NO HABITADOS",
   "CODCOM": 13122,
   "anio": 2025,
   "mes": 6,
   "casos": 74.0,
   "COMUNA": "Peñalolén"
  },
  {
   "delito": "ROBOS EN LUGARES HABITADOS Y NO HABITADOS",
   "CODCOM": 13122,
   "anio": 2025,
   "mes": 7,
   "casos": 48.0,
   "COMUNA": "Peñalolén"
  },
  {
   "delito": "ROBOS EN LUGARES HABITADOS Y NO HABITADOS",
   "CODCOM": 13122,
   "anio": 2025,
   "mes": 8,
   "casos": 68.0,
   "COMUNA": "Peñalolén"
  },
  {
   "delito": "ROBOS EN LUGARES HABITADOS Y NO HABITADOS",
   "CODCOM": 13122,
   "anio": 2025,
   "mes": 9,
   "casos": 48.0,
   "COMUNA": "Peñalolén"
  },
  {
   "delito": "ROBOS EN LUGARES HABITADOS Y NO HABITADOS",
   "CODCOM": 13122,
   "anio": 2025,
   "mes": 10,
   "casos": 30.0,
   "COMUNA": "Peñalolén"
  },
  {
   "delito": "ROBOS EN LUGARES HABITADOS Y NO HABITADOS",
   "CODCOM": 13122,
   "anio": 2025,
   "mes": 11,
   "casos": 18.0,
   "COMUNA": "Peñalolén"
  },
  {
   "delito": "ROBOS EN LUGARES HABITADOS Y NO HABITADOS",
   "CODCOM": 13122,
   "anio": 2025,
   "mes": 12,
   "casos": 39.0,
   "COMUNA": "Peñalolén"
  },
  {
   "delito": "ROBOS EN LUGARES HABITADOS Y NO HABITADOS",
   "CODCOM": 13122,
   "anio": 2026,
   "mes": 1,
   "casos": 35.0,
   "COMUNA": "Peñalolén"
  },
  {
   "delito": "ROBOS EN LUGARES HABITADOS Y NO HABITADOS",
   "CODCOM": 13122,
   "anio": 2026,
   "mes": 2,
   "casos": 8.0,
   "COMUNA": "Peñalolén"
  },
  {
   "delito": "ROBOS POR SORPRESA",
   "CODCOM": 13122,
   "anio": 2025,
   "mes": 1,
   "casos": 33.0,
   "COMUNA": "Peñalolén"
  },
  {
   "delito": "ROBOS POR SORPRESA",
   "CODCOM": 13122,
   "anio": 2025,
   "mes": 2,
   "casos": 26.0,
   "COMUNA": "Peñalolén"
  },
  {
   "delito": "ROBOS POR SORPRESA",
   "CODCOM": 13122,
   "anio": 2025,
   "mes": 3,
   "casos": 41.0,
   "COMUNA": "Peñalolén"
  },
  {
   "delito": "ROBOS POR SORPRESA",
   "CODCOM": 13122,
   "anio": 2025,
   "mes": 4,
   "casos": 21.0,
   "COMUNA": "Peñalolén"
  },
  {
   "delito": "ROBOS POR SORPRESA",
   "CODCOM": 13122,
   "anio": 2025,
   "mes": 5,
   "casos": 28.0,
   "COMUNA": "Peñalolén"
  },
  {
   "delito": "ROBOS POR SORPRESA",
   "CODCOM": 13122,
   "anio": 2025,
   "mes": 6,
   "casos": 40.0,
   "COMUNA": "Peñalolén"
  },
  {
   "delito": "ROBOS POR SORPRESA",
   "CODCOM": 13122,
   "anio": 2025,
   "mes": 7,
   "casos": 38.0,
   "COMUNA": "Peñalolén"
  },
  {
   "delito": "ROBOS POR SORPRESA",
   "CODCOM": 13122,
   "anio": 2025,
   "mes": 8,
   "casos": 29.0,
   "COMUNA": "Peñalolén"
  },
  {
   "delito": "ROBOS POR SORPRESA",
   "CODCOM": 13122,
   "anio": 2025,
   "mes": 9,
   "casos": 39.0,
   "COMUNA": "Peñalolén"
  },
  {
   "delito": "ROBOS POR SORPRESA",
   "CODCOM": 13122,
   "anio": 2025,
   "mes": 10,
   "casos": 17.0,
   "COMUNA": "Peñalolén"
  },
  {
   "delito": "ROBOS POR SORPRESA",
   "CODCOM": 13122,
   "anio": 2025,
   "mes": 11,
   "casos": 22.0,
   "COMUNA": "Peñalolén"
  },
  {
   "delito": "ROBOS POR SORPRESA",
   "CODCOM": 13122,
   "anio": 2025,
   "mes": 12,
   "casos": 29.0,
   "COMUNA": "Peñalolén"
  },
  {
   "delito": "ROBOS POR SORPRESA",
   "CODCOM": 13122,
   "anio": 2026,
   "mes": 1,
   "casos": 32.0,
   "COMUNA": "Peñalolén"
  },
  {
   "delito": "ROBOS POR SORPRESA",
   "CODCOM": 13122,
   "anio": 2026,
   "mes": 2,
   "casos": 12.0,
   "COMUNA": "Peñalolén"
  },
  {
   "delito": "VIOLACIONES Y DELITOS SEXUALES",
   "CODCOM": 13122,
   "anio": 2025,
   "mes": 1,
   "casos": 12.0,
   "COMUNA": "Peñalolén"
  },
  {
   "delito": "VIOLACIONES Y DELITOS SEXUALES",
   "CODCOM": 13122,
   "anio": 2025,
   "mes": 2,
   "casos": 9.0,
   "COMUNA": "Peñalolén"
  },
  {
   "delito": "VIOLACIONES Y DELITOS SEXUALES",
   "CODCOM": 13122,
   "anio": 2025,
   "mes": 3,
   "casos": 14.0,
   "COMUNA": "Peñalolén"
  },
  {
   "delito": "VIOLACIONES Y DELITOS SEXUALES",
   "CODCOM": 13122,
   "anio": 2025,
   "mes": 4,
   "casos": 12.0,
   "COMUNA": "Peñalolén"
  },
  {
   "delito": "VIOLACIONES Y DELITOS SEXUALES",
   "CODCOM": 13122,
   "anio": 2025,
   "mes": 5,
   "casos": 12.0,
   "COMUNA": "Peñalolén"
  },
  {
   "delito": "VIOLACIONES Y DELITOS SEXUALES",
   "CODCOM": 13122,
   "anio": 2025,
   "mes": 6,
   "casos": 9.0,
   "COMUNA": "Peñalolén"
  },
  {
   "delito": "VIOLACIONES Y DELITOS SEXUALES",
   "CODCOM": 13122,
   "anio": 2025,
   "mes": 7,
   "casos": 11.0,
   "COMUNA": "Peñalolén"
  },
  {
   "delito": "VIOLACIONES Y DELITOS SEXUALES",
   "CODCOM": 13122,
   "anio": 2025,
   "mes": 8,
   "casos": 6.0,
   "COMUNA": "Peñalolén"
  },
  {
   "delito": "VIOLACIONES Y DELITOS SEXUALES",
   "CODCOM": 13122,
   "anio": 2025,
   "mes": 9,
   "casos": 14.0,
   "COMUNA": "Peñalolén"
  },
  {
   "delito": "VIOLACIONES Y DELITOS SEXUALES",
   "CODCOM": 13122,
   "anio": 2025,
   "mes": 10,
   "casos": 5.0,
   "COMUNA": "Peñalolén"
  },
  {
   "delito": "VIOLACIONES Y DELITOS SEXUALES",
   "CODCOM": 13122,
   "anio": 2025,
   "mes": 11,
   "casos": 5.0,
   "COMUNA": "Peñalolén"
  },
  {
   "delito": "VIOLACIONES Y DELITOS SEXUALES",
   "CODCOM": 13122,
   "anio": 2025,
   "mes": 12,
   "casos": 3.0,
   "COMUNA": "Peñalolén"
  },
  {
   "delito": "VIOLACIONES Y DELITOS SEXUALES",
   "CODCOM": 13122,
   "anio": 2026,
   "mes": 1,
   "casos": 11.0,
   "COMUNA": "Peñalolén"
  },
  {
   "delito": "VIOLACIONES Y DELITOS SEXUALES",
   "CODCOM": 13122,
   "anio": 2026,
   "mes": 2,
   "casos": 2.0,
   "COMUNA": "Peñalolén"
  }
 ],
 "info": [
  {
   "informacion": "Casos",
   "CODCOM": 13122,
   "delito": "AMENAZAS CON ARMAS",
   "2024": 32.0,
   "2025": 33.0,
   "2026": 6.0,
   "COMUNA": "Peñalolén"
  },
  {
   "informacion": "Casos",
   "CODCOM": 13122,
   "delito": "AMENAZAS Y RIÑAS",
   "2024": 1657.0,
   "2025": 1498.0,
   "2026": 172.0,
   "COMUNA": "Peñalolén"
  },
  {
   "informacion": "Casos",
   "CODCOM": 13122,
   "delito": "CONSUMO DE ALCOHOL Y DE DROGAS EN LA VÍA PÚBLICA",
   "2024": 188.0,
   "2025": 126.0,
   "2026": 11.0,
   "COMUNA": "Peñalolén"
  },
  {
   "informacion": "Casos",
   "CODCOM": 13122,
   "delito": "DAÑOS",
   "2024": 1064.0,
   "2025": 1001.0,
   "2026": 111.0,
   "COMUNA": "Peñalolén"
  },
  {
   "informacion": "Casos",
   "CODCOM": 13122,
   "delito": "DELITOS EN CONTEXTO DE VIOLENCIA INTRAFAMILIAR",
   "2024": 1441.0,
   "2025": 1442.0,
   "2026": 186.0,
   "COMUNA": "Peñalolén"
  },
  {
   "informacion": "Casos",
   "CODCOM": 13122,
   "delito": "HOMICIDIOS Y FEMICIDIOS",
   "2024": 4.0,
   "2025": 12.0,
   "2026": 0.0,
   "COMUNA": "Peñalolén"
  },
  {
   "informacion": "Casos",
   "CODCOM": 13122,
   "delito": "HURTOS",
   "2024": 729.0,
   "2025": 731.0,
   "2026": 73.0,
   "COMUNA": "Peñalolén"
  },
  {
   "informacion": "Casos",
   "CODCOM": 13122,
   "delito": "INCIVILIDADES",
   "2024": 89.0,
   "2025": 95.0,
   "2026": 11.0,
   "COMUNA": "Peñalolén"
  },
  {
   "informacion": "Casos",
   "CODCOM": 13122,
   "delito": "LESIONES GRAVES",
   "2024": 64.0,
   "2025": 36.0,
   "2026": 4.0,
   "COMUNA": "Peñalolén"
  },
  {
   "informacion": "Casos",
   "CODCOM": 13122,
   "delito": "LESIONES LEVES",
   "2024": 546.0,
   "2025": 483.0,
   "2026": 63.0,
   "COMUNA": "Peñalolén"
  },
  {
   "informacion": "Casos",
   "CODCOM": 13122,
   "delito": "LESIONES MENOS GRAVES",
   "2024": 75.0,
   "2025": 81.0,
   "2026": 15.0,
   "COMUNA": "Peñalolén"
  },
  {
   "informacion": "Casos",
   "CODCOM": 13122,
   "delito": "LEY DE CONTROL DE ARMAS",
   "2024": 222.0,
   "2025": 235.0,
   "2026": 24.0,
   "COMUNA": "Peñalolén"
  },
  {
   "informacion": "Casos",
   "CODCOM": 13122,
   "delito": "LEY DE DROGAS",
   "2024": 72.0,
   "2025": 119.0,
   "2026": 13.0,
   "COMUNA": "Peñalolén"
  },
  {
   "informacion": "Casos",
   "CODCOM": 13122,
   "delito": "OTROS DESÓRDENES PÚBLICOS",
   "2024": 29.0,
   "2025": 26.0,
   "2026": 0.0,
   "COMUNA": "Peñalolén"
  },
  {
   "informacion": "Casos",
   "CODCOM": 13122,
   "delito": "OTROS ROBOS CON FUERZA EN LAS COSAS",
   "2024": 52.0,
   "2025": 56.0,
   "2026": 3.0,
   "COMUNA": "Peñalolén"
  },
  {
   "informacion": "Casos",
   "CODCOM": 13122,
   "delito": "RECEPTACIÓN",
   "2024": 88.0,
   "2025": 71.0,
   "2026": 11.0,
   "COMUNA": "Peñalolén"
  },
  {
   "informacion": "Casos",
   "CODCOM": 13122,
   "delito": "ROBOS CON VIOLENCIA E INTIMIDACIÓN",
   "2024": 880.0,
   "2025": 840.0,
   "2026": 67.0,
   "COMUNA": "Peñalolén"
  },
  {
   "informacion": "Casos",
   "CODCOM": 13122,
   "delito": "ROBOS DE VEHÍCULOS Y SUS ACCESORIOS",
   "2024": 1056.0,
   "2025": 1168.0,
   "2026": 83.0,
   "COMUNA": "Peñalolén"
  },
  {
   "informacion": "Casos",
   "CODCOM": 13122,
   "delito": "ROBOS EN LUGARES HABITADOS Y NO HABITADOS",
   "2024": 566.0,
   "2025": 626.0,
   "2026": 43.0,
   "COMUNA": "Peñalolén"
  },
  {
   "informacion": "Casos",
   "CODCOM": 13122,
   "delito": "ROBOS POR SORPRESA",
   "2024": 341.0,
   "2025": 363.0,
   "2026": 44.0,
   "COMUNA": "Peñalolén"
  },
  {
   "informacion": "Casos",
   "CODCOM": 13122,
   "delito": "VIOLACIONES Y DELITOS SEXUALES",
   "2024": 120.0,
   "2025": 112.0,
   "2026": 13.0,
   "COMUNA": "Peñalolén"
  }
 ],
 "meta": {
  "semana_id": "SEMANA 06/2026 (del 02/02/2026 al 08/02/2026)",
  "region": "Metropolitana"
 }
}